Workbook

Sheet Panel
B1: PANEL DE CONTROL | Q1: =TEXT(EDATE(TODAY(),-14),"YYYY-MM") | R1: Lista de meses del desplegable de periodo. No la borres.
B2: Elige un escenario en el desplegable y TODO el panel cambia: los importes, los semáforos, los gráficos y la proyección de la hoja Tesorería. | Q2: =TEXT(EDATE(TODAY(),-13),"YYYY-MM")
Q3: =TEXT(EDATE(TODAY(),-12),"YYYY-MM")
B4: ESCENARIO: | C4: Actual (hoy) | G4: PERIODO: | H4: 2026-08 | I4: =IF(ISNUMBER($H$4),TEXT($H$4,"YYYY-MM"),TRIM($H$4&"")) | J4: ← periodo normalizado (técnico, no borrar) | Q4: =TEXT(EDATE(TODAY(),-11),"YYYY-MM")
D5: =MATCH($C$4,Escenarios!$D$4:$H$4,0) | E5: ← columna del escenario (técnico, no borrar) | H5: =IFERROR(DATEVALUE($I$4&"-01"),TODAY()) | I5: ← primer día del periodo (técnico) | Q5: =TEXT(EDATE(TODAY(),-10),"YYYY-MM")
G6: El periodo filtra los tres estados financieros: Resultados, Balance y FlujoCaja. | Q6: =TEXT(EDATE(TODAY(),-9),"YYYY-MM")
B7: 1. ¿DÓNDE ME CONVIENE VIVIR? | K7: Datos para los gráficos | Q7: =TEXT(EDATE(TODAY(),-8),"YYYY-MM")
B8: INGRESO MENSUAL | D8: TE QUEDA PARA TI | F8: APORTAS A LA CASA | H8: AHORRAS AL MES | K8: Concepto | L8: Importe (€) | Q8: =TEXT(EDATE(TODAY(),-7),"YYYY-MM")
B9: {=INDEX(Escenarios!$D$6:$H$6,$D$5)} | D9: {=INDEX(Escenarios!$D$30:$H$30,$D$5)} | F9: {=INDEX(Escenarios!$D$29:$H$29,$D$5)} | H9: {=INDEX(Escenarios!$D$31:$H$31,$D$5)} | K9: Inversión | L9: {=INDEX(Escenarios!$D$13:$H$13,$D$5)} | Q9: =TEXT(EDATE(TODAY(),-6),"YYYY-MM")
B10: Del escenario elegido | D10: Estilo de vida − hipoteca | F10: Margen + aporte hipoteca | H10: Inversión + fondo emergencia | K10: Fondo de emergencia | L10: {=INDEX(Escenarios!$D$14:$H$14,$D$5)} | Q10: =TEXT(EDATE(TODAY(),-5),"YYYY-MM")
K11: Aporte a la hipoteca | L11: {=INDEX(Escenarios!$D$28:$H$28,$D$5)} | Q11: =TEXT(EDATE(TODAY(),-4),"YYYY-MM")
B12: Comparativa de los 5 escenarios | C12: Ingreso | D12: Gastos personales | E12: Aportas a la casa | F12: Te queda para ti | G12: Ahorro e inversión | H12: Capacidad total | K12: Tus gastos personales | L12: {=INDEX(Escenarios!$D$26:$H$26,$D$5)} | Q12: =TEXT(EDATE(TODAY(),-3),"YYYY-MM")
B13: =Escenarios!$D$4 | C13: =Escenarios!$D$6 | D13: =Escenarios!$D$26 | E13: =Escenarios!$D$29 | F13: =Escenarios!$D$30 | G13: =Escenarios!$D$31 | H13: =Escenarios!$D$54 | K13: Margen aportado a la casa | L13: {=INDEX(Escenarios!$D$27:$H$27,$D$5)} | Q13: =TEXT(EDATE(TODAY(),-2),"YYYY-MM")
B14: =Escenarios!$E$4 | C14: =Escenarios!$E$6 | D14: =Escenarios!$E$26 | E14: =Escenarios!$E$29 | F14: =Escenarios!$E$30 | G14: =Escenarios!$E$31 | H14: =Escenarios!$E$54 | K14: Te queda para ti | L14: {=INDEX(Escenarios!$D$30:$H$30,$D$5)} | Q14: =TEXT(EDATE(TODAY(),-1),"YYYY-MM")
B15: =Escenarios!$F$4 | C15: =Escenarios!$F$6 | D15: =Escenarios!$F$26 | E15: =Escenarios!$F$29 | F15: =Escenarios!$F$30 | G15: =Escenarios!$F$31 | H15: =Escenarios!$F$54 | K15: TOTAL | L15: =SUM($L$9:$L$14) | Q15: =TEXT(EDATE(TODAY(),0),"YYYY-MM")
B16: =Escenarios!$G$4 | C16: =Escenarios!$G$6 | D16: =Escenarios!$G$26 | E16: =Escenarios!$G$29 | F16: =Escenarios!$G$30 | G16: =Escenarios!$G$31 | H16: =Escenarios!$G$54 | K16: Control: debe igualar el ingreso | L16: {=$L$15-INDEX(Escenarios!$D$6:$H$6,$D$5)} | Q16: =TEXT(EDATE(TODAY(),1),"YYYY-MM")
B17: =Escenarios!$H$4 | C17: =Escenarios!$H$6 | D17: =Escenarios!$H$26 | E17: =Escenarios!$H$29 | F17: =Escenarios!$H$30 | G17: =Escenarios!$H$31 | H17: =Escenarios!$H$54 | Q17: =TEXT(EDATE(TODAY(),2),"YYYY-MM")
B18: 🏆 MEJOR EN CADA COLUMNA | C18: {=IFERROR(INDEX($B$13:$B$17,MATCH(MAX(C13:C17),C13:C17,0)),"")} | D18: {=IFERROR(INDEX($B$13:$B$17,MATCH(MIN(D13:D17),D13:D17,0)),"")} | E18: =IFERROR(INDEX($B$13:$B$17,MATCH(MAX(E13:E17),E13:E17,0)),"") | F18: =IFERROR(INDEX($B$13:$B$17,MATCH(MAX(F13:F17),F13:F17,0)),"") | G18: =IFERROR(INDEX($B$13:$B$17,MATCH(MAX(G13:G17),G13:G17,0)),"") | H18: =IFERROR(INDEX($B$13:$B$17,MATCH(MAX(H13:H17),H13:H17,0)),"") | K18: Escenario | L18: Te queda | M18: Ahorro | N18: Superávit hogar | Q18: =TEXT(EDATE(TODAY(),3),"YYYY-MM")
B19: En "Gastos personales" gana el más bajo; en el resto, el más alto. Cuidado: el escenario que más aporta a la casa puede ser el que menos te deja a ti. | K19: =Escenarios!$D$4 | L19: =Escenarios!$D$30 | M19: =Escenarios!$D$31 | N19: =Escenarios!$D$49 | Q19: =TEXT(EDATE(TODAY(),4),"YYYY-MM")
K20: =Escenarios!$E$4 | L20: =Escenarios!$E$30 | M20: =Escenarios!$E$31 | N20: =Escenarios!$E$49 | Q20: =TEXT(EDATE(TODAY(),5),"YYYY-MM")
B21: 2. ¿ME ALCANZA ESTE MES? | K21: =Escenarios!$F$4 | L21: =Escenarios!$F$30 | M21: =Escenarios!$F$31 | N21: =Escenarios!$F$49 | Q21: =TEXT(EDATE(TODAY(),6),"YYYY-MM")
B22: Disponible bancario hoy | C22: =Disponibilidad!$G$33 | K22: =Escenarios!$G$4 | L22: =Escenarios!$G$30 | M22: =Escenarios!$G$31 | N22: =Escenarios!$G$49 | Q22: =TEXT(EDATE(TODAY(),7),"YYYY-MM")
B23: Saldo pendiente de facturas | C23: =Facturas!$AG$20 | K23: =Escenarios!$H$4 | L23: =Escenarios!$H$30 | M23: =Escenarios!$H$31 | N23: =Escenarios!$H$49 | Q23: =TEXT(EDATE(TODAY(),8),"YYYY-MM")
B24: — de ello, vencido | C24: =Facturas!$AG$24 | Q24: =TEXT(EDATE(TODAY(),9),"YYYY-MM")
B25: Vencen en 7 días o menos | C25: =Facturas!$AG$25
B26: Te quedaría después de pagarlo todo | C26: =Disponibilidad!$G$40 | K26: Objetivo | L26: Importe (€)
B27: Cobertura (veces) | C27: =IFERROR(Disponibilidad!$G$41,"") | K27: Patrimonio hoy | L27: {=INDEX(Escenarios!$D$64:$H$64,$D$5)}
B28: Días de autonomía | C28: =IFERROR(Disponibilidad!$G$43,"") | K28: Objetivo 120 meses | L28: {=INDEX(Escenarios!$D$61:$H$61,$D$5)}
B29: Saldo mínimo proyectado en 30 días | C29: =Tesoreria!$P$67 | K29: Objetivo regla 4% | L29: {=INDEX(Escenarios!$D$63:$H$63,$D$5)}
B30: DIAGNÓSTICO | C30: =Disponibilidad!$G$44
B32: 3. ¿CUÁNDO LLEGO A LA INDEPENDENCIA FINANCIERA?
B33: Gasto mensual que tendrías que cubrir sin trabajar | C33: {=INDEX(Escenarios!$D$59:$H$59,$D$5)}
B34: Objetivo con TU regla (gasto × 120 meses) | C34: {=INDEX(Escenarios!$D$61:$H$61,$D$5)}
B35: Objetivo con la regla del 4% (gasto × 300 meses) | C35: {=INDEX(Escenarios!$D$63:$H$63,$D$5)}
B36: Patrimonio invertido hoy | C36: {=INDEX(Escenarios!$D$64:$H$64,$D$5)}
B37: Aporte mensual a inversión | C37: {=INDEX(Escenarios!$D$13:$H$13,$D$5)}
B38: Progreso hacia el objetivo del 4% | C38: {=INDEX(Escenarios!$D$68:$H$68,$D$5)}
B39: Barra de progreso | C39: =IF($C$38="","",REPT("█",MAX(0,ROUND($C$38*40,0)))&REPT("░",40-MAX(0,ROUND($C$38*40,0))))
B40: Años hasta TU objetivo | C40: {=INDEX(Escenarios!$D$66:$H$66,$D$5)}
B41: Años hasta el objetivo del 4% | C41: {=INDEX(Escenarios!$D$67:$H$67,$D$5)}
B42: Edad estimada al llegar al 4% (si hoy tienes 40) | C42: =IF($C$41="","",40+$C$41)
B43: Tu archivo calculaba el objetivo como salario × 120. Dos correcciones: se calcula sobre el GASTO (el salario desaparece cuando dejas de trabajar) y 120 meses son 10 años de gasto, no independencia perpetua. Para eso hace falta unas 300 veces el gasto mensual (regla del 4%).
B45: 4. ¿CÓMO VA EL PRESUPUESTO DEL HOGAR?
B46: Ingreso total del hogar | C46: {=INDEX(Escenarios!$D$39:$H$39,$D$5)}
B47: — Nómina de Iris | C47: {=INDEX(Escenarios!$D$35:$H$35,$D$5)}
B48: — Ingreso de Stalin | C48: {=INDEX(Escenarios!$D$36:$H$36,$D$5)}
B49: — Ingreso de Tony | C49: {=INDEX(Escenarios!$D$37:$H$37,$D$5)}
B50: — Tu aporte | C50: {=INDEX(Escenarios!$D$29:$H$29,$D$5)}
B51: Total gastos del hogar | C51: {=INDEX(Escenarios!$D$48:$H$48,$D$5)}
B52: SUPERÁVIT / DÉFICIT DEL HOGAR | C52: {=INDEX(Escenarios!$D$49:$H$49,$D$5)}
B53: Gastos / ingresos del hogar | C53: {=INDEX(Escenarios!$D$50:$H$50,$D$5)}
B54: Estado | C54: =IF($C$51="","",IF($C$51<0,"🔴 Déficit: la casa gasta más de lo que entra",IF($C$52>0.9,"🟡 Muy justo: menos del 10% de margen","✅ La casa se sostiene")))
B56: 5. ESTADOS FINANCIEROS
B57: RESULTADO DEL MES | D57: PATRIMONIO NETO | F57: VARIACIÓN DE CAJA | H57: SALDO MÍNIMO 12 M
B58: =Resultados!$F$43 | D58: =Balance!$E$41 | F58: =FlujoCaja!$F$27 | H58: =FlujoCaja!$C$57
B59: Ingresos − gastos (consolidado) | D59: Activo − pasivo | F59: Lo que crece la cuenta este mes | H59: Punto más bajo proyectado
B61: El resultado del mes y la variación de caja no coinciden: la diferencia es lo que destinas a amortizar deuda y a invertir, que sale de la cuenta pero no empobrece. La conciliación completa está en la hoja FlujoCaja.
B63: 6. CARTERA DE INVERSIONES
B64: VALOR DE LA CARTERA | D64: RESULTADO ACUMULADO | F64: ROI DE LA CARTERA | H64: COMISIONES PAGADAS
B65: =Inversiones!$L$48 | D65: =Inversiones!$R$48 | F65: =IFERROR(Inversiones!$E$59,"") | H65: =Inversiones!$N$48+Inversiones!$O$48
B66: Todas las posiciones | D66: Plusvalía + rentas − comisiones | F66: Sobre el coste total | H66: Compra + custodia y gestión
B70: 7. SALUD FINANCIERA
B71: PUNTUACIÓN GLOBAL | D71: CALIFICACIÓN | F71: RATIOS EN ROJO | H71: RATIOS EN VERDE
B72: =Ratios!$D$40 | D72: =Ratios!$D$41 | F72: =COUNTIF(Ratios!F$11:$F$37,"🔴") | H72: =COUNTIF(Ratios!F$11:$F$37,"✅")
B73: Sobre 100 | D73: Evaluación del desempeño | F73: A corregir | H73: Bajo control
B77: 8. EVOLUCIÓN DEL MES
B78: INGRESOS DEL MES | D78: GASTOS DEL MES | F78: VARIACIÓN DE GASTOS | H78: CONCILIACIÓN
B79: {=IFERROR(INDEX(Resultados!$C$60:$C$71,MATCH(Panel!$I$4,Resultados!$B$60:$B$71,0)),"")} | D79: {=IFERROR(INDEX(Resultados!$D$60:$D$71,MATCH(Panel!$I$4,Resultados!$B$60:$B$71,0)),"")} | F79: {=IFERROR(INDEX(Resultados!$G$60:$G$71,MATCH(Panel!$I$4,Resultados!$B$60:$B$71,0)),"")} | H79: =Disponibilidad!$T$19
B80: Reales si hay caja; si no, presupuesto | D80: Mismo criterio | F80: Frente al mes anterior | H80: Caja frente a banco
B84: 9. FACTURAS PRIORIZADAS
B85: MARCADAS PARA PAGAR | D85: IMPORTE SELECCIONADO | F85: TE QUEDARÍA | H85: ¿ALCANZA?
B86: =COUNTIFS(Facturas!$P$6:$P$205,"<>",Facturas!$K$6:$K$205,">0") | D86: =SUMIFS(Facturas!$K$6:$K$205,Facturas!$P$6:$P$205,"<>") | F86: =Disponibilidad!$G$33-(SUMIFS(Facturas!$K$6:$K$205,Facturas!$P$6:$P$205,"<>")) | H86: =IF(COUNTIFS(Facturas!$P$6:$P$205,"<>",Facturas!$K$6:$K$205,">0")=0,"—",IF(Disponibilidad!$G$33>=(SUMIFS(Facturas!$K$6:$K$205,Facturas!$P$6:$P$205,"<>")),"✅ Sí","🔴 No"))
B87: Hoja Prioridad | D87: Suma de sus saldos | F87: Después de pagarlas | H87: Disponible vs selección

Sheet Citas
B1: CALENDARIO DE CITAS
B2: Arriba tienes el mes actual (o el que elijas) en grande, y más abajo los doce meses del año de un vistazo. Escribe tus citas en el REGISTRO del final y todo se pinta solo, con el color de la prioridad más alta de cada día. Las filas de ejemplo están marcadas "(ejemplo)": bórralas cuando metas las tuyas.
B4: AÑO: | D4: 2026 | G4: MES: | I4: Actual (hoy) | M4: =IFERROR(IF(OR($I$4="Actual (hoy)",$I$4=""),MONTH(TODAY()),MATCH($I$4,{"Enero";"Febrero";"Marzo";"Abril";"Mayo";"Junio";"Julio";"Agosto";"Septiembre";"Octubre";"Noviembre";"Diciembre"},0)),MONTH(TODAY())) | O4: =" Mostrando: "&INDEX({"Enero";"Febrero";"Marzo";"Abril";"Mayo";"Junio";"Julio";"Agosto";"Septiembre";"Octubre";"Noviembre";"Diciembre"},$M$4)&" de "&$D$4&" ▸ pinta el calendario grande de arriba"
B5: LEYENDA: | J5: 1 · Urgente | M5: 2 · Alta | P5: 3 · Media | S5: 4 · Baja | V5: Sin prioridad
B7: CITAS DEL AÑO | H7: PENDIENTES | N7: URGENTES PENDIENTES | T7: PRÓXIMA CITA
B8: =COUNTIFS($B$62:$B$211,">="&DATE($D$4,1,1),$B$62:$B$211,"<="&DATE($D$4,12,31),$V$62:$V$211,"<>4 · Cancelada") | H8: =COUNTIFS($B$62:$B$211,">="&TODAY(),$V$62:$V$211,"<>4 · Cancelada",$V$62:$V$211,"<>3 · Hecha") | N8: =COUNTIFS($B$62:$B$211,">="&TODAY(),$S$62:$S$211,"1 · Urgente",$V$62:$V$211,"<>4 · Cancelada",$V$62:$V$211,"<>3 · Hecha") | T8: =IF(COUNT($Z$62:$Z$211)=0,"—",MIN($Z$62:$Z$211))
B9: Sin contar las canceladas | H9: Aún por celebrar | N9: Prioridad 1 sin celebrar | T9: La primera que llega
B10: =IFERROR(IF(COUNT($Z$62:$Z$211)=0,"📭 No tienes ninguna cita futura registrada.","📌 Siguiente: "&TEXT(MIN($Z$62:$Z$211),"DD/MM/YYYY")&" · "&INDEX($G$62:$G$211,MATCH(MIN($Z$62:$Z$211),$B$62:$B$211,0))&" · "&IF(MIN($Z$62:$Z$211)=TODAY(),"es HOY","faltan "&(MIN($Z$62:$Z$211)-TODAY())&" días")),"")
B12: ="★ "&UPPER(INDEX({"Enero";"Febrero";"Marzo";"Abril";"Mayo";"Junio";"Julio";"Agosto";"Septiembre";"Octubre";"Noviembre";"Diciembre"},$M$4))&" "&$D$4 | G12: =COUNTIFS($B$62:$B$211,">="&DATE($D$4,$M$4,1),$B$62:$B$211,"<="&EOMONTH(DATE($D$4,$M$4,1),0),$V$62:$V$211,"<>4 · Cancelada")&" citas"
B13: L | C13: M | D13: X | E13: J | F13: V | G13: S | H13: D
B14: =IF(MONTH(DATE($D$4,$M$4,1)-WEEKDAY(DATE($D$4,$M$4,1),2)+1+0)<>$M$4,"",DATE($D$4,$M$4,1)-WEEKDAY(DATE($D$4,$M$4,1),2)+1+0) | C14: =IF(MONTH(DATE($D$4,$M$4,1)-WEEKDAY(DATE($D$4,$M$4,1),2)+1+1)<>$M$4,"",DATE($D$4,$M$4,1)-WEEKDAY(DATE($D$4,$M$4,1),2)+1+1) | D14: =IF(MONTH(DATE($D$4,$M$4,1)-WEEKDAY(DATE($D$4,$M$4,1),2)+1+2)<>$M$4,"",DATE($D$4,$M$4,1)-WEEKDAY(DATE($D$4,$M$4,1),2)+1+2) | E14: =IF(MONTH(DATE($D$4,$M$4,1)-WEEKDAY(DATE($D$4,$M$4,1),2)+1+3)<>$M$4,"",DATE($D$4,$M$4,1)-WEEKDAY(DATE($D$4,$M$4,1),2)+1+3) | F14: =IF(MONTH(DATE($D$4,$M$4,1)-WEEKDAY(DATE($D$4,$M$4,1),2)+1+4)<>$M$4,"",DATE($D$4,$M$4,1)-WEEKDAY(DATE($D$4,$M$4,1),2)+1+4) | G14: =IF(MONTH(DATE($D$4,$M$4,1)-WEEKDAY(DATE($D$4,$M$4,1),2)+1+5)<>$M$4,"",DATE($D$4,$M$4,1)-WEEKDAY(DATE($D$4,$M$4,1),2)+1+5) | H14: =IF(MONTH(DATE($D$4,$M$4,1)-WEEKDAY(DATE($D$4,$M$4,1),2)+1+6)<>$M$4,"",DATE($D$4,$M$4,1)-WEEKDAY(DATE($D$4,$M$4,1),2)+1+6)
B15: =IF(MONTH(DATE($D$4,$M$4,1)-WEEKDAY(DATE($D$4,$M$4,1),2)+1+7)<>$M$4,"",DATE($D$4,$M$4,1)-WEEKDAY(DATE($D$4,$M$4,1),2)+1+7) | C15: =IF(MONTH(DATE($D$4,$M$4,1)-WEEKDAY(DATE($D$4,$M$4,1),2)+1+8)<>$M$4,"",DATE($D$4,$M$4,1)-WEEKDAY(DATE($D$4,$M$4,1),2)+1+8) | D15: =IF(MONTH(DATE($D$4,$M$4,1)-WEEKDAY(DATE($D$4,$M$4,1),2)+1+9)<>$M$4,"",DATE($D$4,$M$4,1)-WEEKDAY(DATE($D$4,$M$4,1),2)+1+9) | E15: =IF(MONTH(DATE($D$4,$M$4,1)-WEEKDAY(DATE($D$4,$M$4,1),2)+1+10)<>$M$4,"",DATE($D$4,$M$4,1)-WEEKDAY(DATE($D$4,$M$4,1),2)+1+10) | F15: =IF(MONTH(DATE($D$4,$M$4,1)-WEEKDAY(DATE($D$4,$M$4,1),2)+1+11)<>$M$4,"",DATE($D$4,$M$4,1)-WEEKDAY(DATE($D$4,$M$4,1),2)+1+11) | G15: =IF(MONTH(DATE($D$4,$M$4,1)-WEEKDAY(DATE($D$4,$M$4,1),2)+1+12)<>$M$4,"",DATE($D$4,$M$4,1)-WEEKDAY(DATE($D$4,$M$4,1),2)+1+12) | H15: =IF(MONTH(DATE($D$4,$M$4,1)-WEEKDAY(DATE($D$4,$M$4,1),2)+1+13)<>$M$4,"",DATE($D$4,$M$4,1)-WEEKDAY(DATE($D$4,$M$4,1),2)+1+13)
B16: =IF(MONTH(DATE($D$4,$M$4,1)-WEEKDAY(DATE($D$4,$M$4,1),2)+1+14)<>$M$4,"",DATE($D$4,$M$4,1)-WEEKDAY(DATE($D$4,$M$4,1),2)+1+14) | C16: =IF(MONTH(DATE($D$4,$M$4,1)-WEEKDAY(DATE($D$4,$M$4,1),2)+1+15)<>$M$4,"",DATE($D$4,$M$4,1)-WEEKDAY(DATE($D$4,$M$4,1),2)+1+15) | D16: =IF(MONTH(DATE($D$4,$M$4,1)-WEEKDAY(DATE($D$4,$M$4,1),2)+1+16)<>$M$4,"",DATE($D$4,$M$4,1)-WEEKDAY(DATE($D$4,$M$4,1),2)+1+16) | E16: =IF(MONTH(DATE($D$4,$M$4,1)-WEEKDAY(DATE($D$4,$M$4,1),2)+1+17)<>$M$4,"",DATE($D$4,$M$4,1)-WEEKDAY(DATE($D$4,$M$4,1),2)+1+17) | F16: =IF(MONTH(DATE($D$4,$M$4,1)-WEEKDAY(DATE($D$4,$M$4,1),2)+1+18)<>$M$4,"",DATE($D$4,$M$4,1)-WEEKDAY(DATE($D$4,$M$4,1),2)+1+18) | G16: =IF(MONTH(DATE($D$4,$M$4,1)-WEEKDAY(DATE($D$4,$M$4,1),2)+1+19)<>$M$4,"",DATE($D$4,$M$4,1)-WEEKDAY(DATE($D$4,$M$4,1),2)+1+19) | H16: =IF(MONTH(DATE($D$4,$M$4,1)-WEEKDAY(DATE($D$4,$M$4,1),2)+1+20)<>$M$4,"",DATE($D$4,$M$4,1)-WEEKDAY(DATE($D$4,$M$4,1),2)+1+20)
B17: =IF(MONTH(DATE($D$4,$M$4,1)-WEEKDAY(DATE($D$4,$M$4,1),2)+1+21)<>$M$4,"",DATE($D$4,$M$4,1)-WEEKDAY(DATE($D$4,$M$4,1),2)+1+21) | C17: =IF(MONTH(DATE($D$4,$M$4,1)-WEEKDAY(DATE($D$4,$M$4,1),2)+1+22)<>$M$4,"",DATE($D$4,$M$4,1)-WEEKDAY(DATE($D$4,$M$4,1),2)+1+22) | D17: =IF(MONTH(DATE($D$4,$M$4,1)-WEEKDAY(DATE($D$4,$M$4,1),2)+1+23)<>$M$4,"",DATE($D$4,$M$4,1)-WEEKDAY(DATE($D$4,$M$4,1),2)+1+23) | E17: =IF(MONTH(DATE($D$4,$M$4,1)-WEEKDAY(DATE($D$4,$M$4,1),2)+1+24)<>$M$4,"",DATE($D$4,$M$4,1)-WEEKDAY(DATE($D$4,$M$4,1),2)+1+24) | F17: =IF(MONTH(DATE($D$4,$M$4,1)-WEEKDAY(DATE($D$4,$M$4,1),2)+1+25)<>$M$4,"",DATE($D$4,$M$4,1)-WEEKDAY(DATE($D$4,$M$4,1),2)+1+25) | G17: =IF(MONTH(DATE($D$4,$M$4,1)-WEEKDAY(DATE($D$4,$M$4,1),2)+1+26)<>$M$4,"",DATE($D$4,$M$4,1)-WEEKDAY(DATE($D$4,$M$4,1),2)+1+26) | H17: =IF(MONTH(DATE($D$4,$M$4,1)-WEEKDAY(DATE($D$4,$M$4,1),2)+1+27)<>$M$4,"",DATE($D$4,$M$4,1)-WEEKDAY(DATE($D$4,$M$4,1),2)+1+27)
B18: =IF(MONTH(DATE($D$4,$M$4,1)-WEEKDAY(DATE($D$4,$M$4,1),2)+1+28)<>$M$4,"",DATE($D$4,$M$4,1)-WEEKDAY(DATE($D$4,$M$4,1),2)+1+28) | C18: =IF(MONTH(DATE($D$4,$M$4,1)-WEEKDAY(DATE($D$4,$M$4,1),2)+1+29)<>$M$4,"",DATE($D$4,$M$4,1)-WEEKDAY(DATE($D$4,$M$4,1),2)+1+29) | D18: =IF(MONTH(DATE($D$4,$M$4,1)-WEEKDAY(DATE($D$4,$M$4,1),2)+1+30)<>$M$4,"",DATE($D$4,$M$4,1)-WEEKDAY(DATE($D$4,$M$4,1),2)+1+30) | E18: =IF(MONTH(DATE($D$4,$M$4,1)-WEEKDAY(DATE($D$4,$M$4,1),2)+1+31)<>$M$4,"",DATE($D$4,$M$4,1)-WEEKDAY(DATE($D$4,$M$4,1),2)+1+31) | F18: =IF(MONTH(DATE($D$4,$M$4,1)-WEEKDAY(DATE($D$4,$M$4,1),2)+1+32)<>$M$4,"",DATE($D$4,$M$4,1)-WEEKDAY(DATE($D$4,$M$4,1),2)+1+32) | G18: =IF(MONTH(DATE($D$4,$M$4,1)-WEEKDAY(DATE($D$4,$M$4,1),2)+1+33)<>$M$4,"",DATE($D$4,$M$4,1)-WEEKDAY(DATE($D$4,$M$4,1),2)+1+33) | H18: =IF(MONTH(DATE($D$4,$M$4,1)-WEEKDAY(DATE($D$4,$M$4,1),2)+1+34)<>$M$4,"",DATE($D$4,$M$4,1)-WEEKDAY(DATE($D$4,$M$4,1),2)+1+34)
B19: =IF(MONTH(DATE($D$4,$M$4,1)-WEEKDAY(DATE($D$4,$M$4,1),2)+1+35)<>$M$4,"",DATE($D$4,$M$4,1)-WEEKDAY(DATE($D$4,$M$4,1),2)+1+35) | C19: =IF(MONTH(DATE($D$4,$M$4,1)-WEEKDAY(DATE($D$4,$M$4,1),2)+1+36)<>$M$4,"",DATE($D$4,$M$4,1)-WEEKDAY(DATE($D$4,$M$4,1),2)+1+36) | D19: =IF(MONTH(DATE($D$4,$M$4,1)-WEEKDAY(DATE($D$4,$M$4,1),2)+1+37)<>$M$4,"",DATE($D$4,$M$4,1)-WEEKDAY(DATE($D$4,$M$4,1),2)+1+37) | E19: =IF(MONTH(DATE($D$4,$M$4,1)-WEEKDAY(DATE($D$4,$M$4,1),2)+1+38)<>$M$4,"",DATE($D$4,$M$4,1)-WEEKDAY(DATE($D$4,$M$4,1),2)+1+38) | F19: =IF(MONTH(DATE($D$4,$M$4,1)-WEEKDAY(DATE($D$4,$M$4,1),2)+1+39)<>$M$4,"",DATE($D$4,$M$4,1)-WEEKDAY(DATE($D$4,$M$4,1),2)+1+39) | G19: =IF(MONTH(DATE($D$4,$M$4,1)-WEEKDAY(DATE($D$4,$M$4,1),2)+1+40)<>$M$4,"",DATE($D$4,$M$4,1)-WEEKDAY(DATE($D$4,$M$4,1),2)+1+40) | H19: =IF(MONTH(DATE($D$4,$M$4,1)-WEEKDAY(DATE($D$4,$M$4,1),2)+1+41)<>$M$4,"",DATE($D$4,$M$4,1)-WEEKDAY(DATE($D$4,$M$4,1),2)+1+41)
B21: LOS 12 MESES DEL AÑO — de un vistazo
B23: ="ENERO "&$D$4 | G23: =IF(COUNTIFS($B$62:$B$211,">="&DATE($D$4,1,1),$B$62:$B$211,"<="&EOMONTH(DATE($D$4,1,1),0),$V$62:$V$211,"<>4 · Cancelada")=1,"1 cita",COUNTIFS($B$62:$B$211,">="&DATE($D$4,1,1),$B$62:$B$211,"<="&EOMONTH(DATE($D$4,1,1),0),$V$62:$V$211,"<>4 · Cancelada")&" citas") | J23: ="FEBRERO "&$D$4 | O23: =IF(COUNTIFS($B$62:$B$211,">="&DATE($D$4,2,1),$B$62:$B$211,"<="&EOMONTH(DATE($D$4,2,1),0),$V$62:$V$211,"<>4 · Cancelada")=1,"1 cita",COUNTIFS($B$62:$B$211,">="&DATE($D$4,2,1),$B$62:$B$211,"<="&EOMONTH(DATE($D$4,2,1),0),$V$62:$V$211,"<>4 · Cancelada")&" citas") | R23: ="MARZO "&$D$4 | W23: =IF(COUNTIFS($B$62:$B$211,">="&DATE($D$4,3,1),$B$62:$B$211,"<="&EOMONTH(DATE($D$4,3,1),0),$V$62:$V$211,"<>4 · Cancelada")=1,"1 cita",COUNTIFS($B$62:$B$211,">="&DATE($D$4,3,1),$B$62:$B$211,"<="&EOMONTH(DATE($D$4,3,1),0),$V$62:$V$211,"<>4 · Cancelada")&" citas")
B24: L | C24: M | D24: X | E24: J | F24: V | G24: S | H24: D | J24: L | K24: M | L24: X | M24: J | N24: V | O24: S | P24: D | R24: L | S24: M | T24: X | U24: J | V24: V | W24: S | X24: D
B25: =IF(MONTH(DATE($D$4,1,1)-WEEKDAY(DATE($D$4,1,1),2)+1+0)<>1,"",DATE($D$4,1,1)-WEEKDAY(DATE($D$4,1,1),2)+1+0) | C25: =IF(MONTH(DATE($D$4,1,1)-WEEKDAY(DATE($D$4,1,1),2)+1+1)<>1,"",DATE($D$4,1,1)-WEEKDAY(DATE($D$4,1,1),2)+1+1) | D25: =IF(MONTH(DATE($D$4,1,1)-WEEKDAY(DATE($D$4,1,1),2)+1+2)<>1,"",DATE($D$4,1,1)-WEEKDAY(DATE($D$4,1,1),2)+1+2) | E25: =IF(MONTH(DATE($D$4,1,1)-WEEKDAY(DATE($D$4,1,1),2)+1+3)<>1,"",DATE($D$4,1,1)-WEEKDAY(DATE($D$4,1,1),2)+1+3) | F25: =IF(MONTH(DATE($D$4,1,1)-WEEKDAY(DATE($D$4,1,1),2)+1+4)<>1,"",DATE($D$4,1,1)-WEEKDAY(DATE($D$4,1,1),2)+1+4) | G25: =IF(MONTH(DATE($D$4,1,1)-WEEKDAY(DATE($D$4,1,1),2)+1+5)<>1,"",DATE($D$4,1,1)-WEEKDAY(DATE($D$4,1,1),2)+1+5) | H25: =IF(MONTH(DATE($D$4,1,1)-WEEKDAY(DATE($D$4,1,1),2)+1+6)<>1,"",DATE($D$4,1,1)-WEEKDAY(DATE($D$4,1,1),2)+1+6) | J25: =IF(MONTH(DATE($D$4,2,1)-WEEKDAY(DATE($D$4,2,1),2)+1+0)<>2,"",DATE($D$4,2,1)-WEEKDAY(DATE($D$4,2,1),2)+1+0) | K25: =IF(MONTH(DATE($D$4,2,1)-WEEKDAY(DATE($D$4,2,1),2)+1+1)<>2,"",DATE($D$4,2,1)-WEEKDAY(DATE($D$4,2,1),2)+1+1) | L25: =IF(MONTH(DATE($D$4,2,1)-WEEKDAY(DATE($D$4,2,1),2)+1+2)<>2,"",DATE($D$4,2,1)-WEEKDAY(DATE($D$4,2,1),2)+1+2) | M25: =IF(MONTH(DATE($D$4,2,1)-WEEKDAY(DATE($D$4,2,1),2)+1+3)<>2,"",DATE($D$4,2,1)-WEEKDAY(DATE($D$4,2,1),2)+1+3) | N25: =IF(MONTH(DATE($D$4,2,1)-WEEKDAY(DATE($D$4,2,1),2)+1+4)<>2,"",DATE($D$4,2,1)-WEEKDAY(DATE($D$4,2,1),2)+1+4) | O25: =IF(MONTH(DATE($D$4,2,1)-WEEKDAY(DATE($D$4,2,1),2)+1+5)<>2,"",DATE($D$4,2,1)-WEEKDAY(DATE($D$4,2,1),2)+1+5) | P25: =IF(MONTH(DATE($D$4,2,1)-WEEKDAY(DATE($D$4,2,1),2)+1+6)<>2,"",DATE($D$4,2,1)-WEEKDAY(DATE($D$4,2,1),2)+1+6) | R25: =IF(MONTH(DATE($D$4,3,1)-WEEKDAY(DATE($D$4,3,1),2)+1+0)<>3,"",DATE($D$4,3,1)-WEEKDAY(DATE($D$4,3,1),2)+1+0) | S25: =IF(MONTH(DATE($D$4,3,1)-WEEKDAY(DATE($D$4,3,1),2)+1+1)<>3,"",DATE($D$4,3,1)-WEEKDAY(DATE($D$4,3,1),2)+1+1) | T25: =IF(MONTH(DATE($D$4,3,1)-WEEKDAY(DATE($D$4,3,1),2)+1+2)<>3,"",DATE($D$4,3,1)-WEEKDAY(DATE($D$4,3,1),2)+1+2) | U25: =IF(MONTH(DATE($D$4,3,1)-WEEKDAY(DATE($D$4,3,1),2)+1+3)<>3,"",DATE($D$4,3,1)-WEEKDAY(DATE($D$4,3,1),2)+1+3) | V25: =IF(MONTH(DATE($D$4,3,1)-WEEKDAY(DATE($D$4,3,1),2)+1+4)<>3,"",DATE($D$4,3,1)-WEEKDAY(DATE($D$4,3,1),2)+1+4) | W25: =IF(MONTH(DATE($D$4,3,1)-WEEKDAY(DATE($D$4,3,1),2)+1+5)<>3,"",DATE($D$4,3,1)-WEEKDAY(DATE($D$4,3,1),2)+1+5) | X25: =IF(MONTH(DATE($D$4,3,1)-WEEKDAY(DATE($D$4,3,1),2)+1+6)<>3,"",DATE($D$4,3,1)-WEEKDAY(DATE($D$4,3,1),2)+1+6)
B26: =IF(MONTH(DATE($D$4,1,1)-WEEKDAY(DATE($D$4,1,1),2)+1+7)<>1,"",DATE($D$4,1,1)-WEEKDAY(DATE($D$4,1,1),2)+1+7) | C26: =IF(MONTH(DATE($D$4,1,1)-WEEKDAY(DATE($D$4,1,1),2)+1+8)<>1,"",DATE($D$4,1,1)-WEEKDAY(DATE($D$4,1,1),2)+1+8) | D26: =IF(MONTH(DATE($D$4,1,1)-WEEKDAY(DATE($D$4,1,1),2)+1+9)<>1,"",DATE($D$4,1,1)-WEEKDAY(DATE($D$4,1,1),2)+1+9) | E26: =IF(MONTH(DATE($D$4,1,1)-WEEKDAY(DATE($D$4,1,1),2)+1+10)<>1,"",DATE($D$4,1,1)-WEEKDAY(DATE($D$4,1,1),2)+1+10) | F26: =IF(MONTH(DATE($D$4,1,1)-WEEKDAY(DATE($D$4,1,1),2)+1+11)<>1,"",DATE($D$4,1,1)-WEEKDAY(DATE($D$4,1,1),2)+1+11) | G26: =IF(MONTH(DATE($D$4,1,1)-WEEKDAY(DATE($D$4,1,1),2)+1+12)<>1,"",DATE($D$4,1,1)-WEEKDAY(DATE($D$4,1,1),2)+1+12) | H26: =IF(MONTH(DATE($D$4,1,1)-WEEKDAY(DATE($D$4,1,1),2)+1+13)<>1,"",DATE($D$4,1,1)-WEEKDAY(DATE($D$4,1,1),2)+1+13) | J26: =IF(MONTH(DATE($D$4,2,1)-WEEKDAY(DATE($D$4,2,1),2)+1+7)<>2,"",DATE($D$4,2,1)-WEEKDAY(DATE($D$4,2,1),2)+1+7) | K26: =IF(MONTH(DATE($D$4,2,1)-WEEKDAY(DATE($D$4,2,1),2)+1+8)<>2,"",DATE($D$4,2,1)-WEEKDAY(DATE($D$4,2,1),2)+1+8) | L26: =IF(MONTH(DATE($D$4,2,1)-WEEKDAY(DATE($D$4,2,1),2)+1+9)<>2,"",DATE($D$4,2,1)-WEEKDAY(DATE($D$4,2,1),2)+1+9) | M26: =IF(MONTH(DATE($D$4,2,1)-WEEKDAY(DATE($D$4,2,1),2)+1+10)<>2,"",DATE($D$4,2,1)-WEEKDAY(DATE($D$4,2,1),2)+1+10) | N26: =IF(MONTH(DATE($D$4,2,1)-WEEKDAY(DATE($D$4,2,1),2)+1+11)<>2,"",DATE($D$4,2,1)-WEEKDAY(DATE($D$4,2,1),2)+1+11) | O26: =IF(MONTH(DATE($D$4,2,1)-WEEKDAY(DATE($D$4,2,1),2)+1+12)<>2,"",DATE($D$4,2,1)-WEEKDAY(DATE($D$4,2,1),2)+1+12) | P26: =IF(MONTH(DATE($D$4,2,1)-WEEKDAY(DATE($D$4,2,1),2)+1+13)<>2,"",DATE($D$4,2,1)-WEEKDAY(DATE($D$4,2,1),2)+1+13) | R26: =IF(MONTH(DATE($D$4,3,1)-WEEKDAY(DATE($D$4,3,1),2)+1+7)<>3,"",DATE($D$4,3,1)-WEEKDAY(DATE($D$4,3,1),2)+1+7) | S26: =IF(MONTH(DATE($D$4,3,1)-WEEKDAY(DATE($D$4,3,1),2)+1+8)<>3,"",DATE($D$4,3,1)-WEEKDAY(DATE($D$4,3,1),2)+1+8) | T26: =IF(MONTH(DATE($D$4,3,1)-WEEKDAY(DATE($D$4,3,1),2)+1+9)<>3,"",DATE($D$4,3,1)-WEEKDAY(DATE($D$4,3,1),2)+1+9) | U26: =IF(MONTH(DATE($D$4,3,1)-WEEKDAY(DATE($D$4,3,1),2)+1+10)<>3,"",DATE($D$4,3,1)-WEEKDAY(DATE($D$4,3,1),2)+1+10) | V26: =IF(MONTH(DATE($D$4,3,1)-WEEKDAY(DATE($D$4,3,1),2)+1+11)<>3,"",DATE($D$4,3,1)-WEEKDAY(DATE($D$4,3,1),2)+1+11) | W26: =IF(MONTH(DATE($D$4,3,1)-WEEKDAY(DATE($D$4,3,1),2)+1+12)<>3,"",DATE($D$4,3,1)-WEEKDAY(DATE($D$4,3,1),2)+1+12) | X26: =IF(MONTH(DATE($D$4,3,1)-WEEKDAY(DATE($D$4,3,1),2)+1+13)<>3,"",DATE($D$4,3,1)-WEEKDAY(DATE($D$4,3,1),2)+1+13)
B27: =IF(MONTH(DATE($D$4,1,1)-WEEKDAY(DATE($D$4,1,1),2)+1+14)<>1,"",DATE($D$4,1,1)-WEEKDAY(DATE($D$4,1,1),2)+1+14) | C27: =IF(MONTH(DATE($D$4,1,1)-WEEKDAY(DATE($D$4,1,1),2)+1+15)<>1,"",DATE($D$4,1,1)-WEEKDAY(DATE($D$4,1,1),2)+1+15) | D27: =IF(MONTH(DATE($D$4,1,1)-WEEKDAY(DATE($D$4,1,1),2)+1+16)<>1,"",DATE($D$4,1,1)-WEEKDAY(DATE($D$4,1,1),2)+1+16) | E27: =IF(MONTH(DATE($D$4,1,1)-WEEKDAY(DATE($D$4,1,1),2)+1+17)<>1,"",DATE($D$4,1,1)-WEEKDAY(DATE($D$4,1,1),2)+1+17) | F27: =IF(MONTH(DATE($D$4,1,1)-WEEKDAY(DATE($D$4,1,1),2)+1+18)<>1,"",DATE($D$4,1,1)-WEEKDAY(DATE($D$4,1,1),2)+1+18) | G27: =IF(MONTH(DATE($D$4,1,1)-WEEKDAY(DATE($D$4,1,1),2)+1+19)<>1,"",DATE($D$4,1,1)-WEEKDAY(DATE($D$4,1,1),2)+1+19) | H27: =IF(MONTH(DATE($D$4,1,1)-WEEKDAY(DATE($D$4,1,1),2)+1+20)<>1,"",DATE($D$4,1,1)-WEEKDAY(DATE($D$4,1,1),2)+1+20) | J27: =IF(MONTH(DATE($D$4,2,1)-WEEKDAY(DATE($D$4,2,1),2)+1+14)<>2,"",DATE($D$4,2,1)-WEEKDAY(DATE($D$4,2,1),2)+1+14) | K27: =IF(MONTH(DATE($D$4,2,1)-WEEKDAY(DATE($D$4,2,1),2)+1+15)<>2,"",DATE($D$4,2,1)-WEEKDAY(DATE($D$4,2,1),2)+1+15) | L27: =IF(MONTH(DATE($D$4,2,1)-WEEKDAY(DATE($D$4,2,1),2)+1+16)<>2,"",DATE($D$4,2,1)-WEEKDAY(DATE($D$4,2,1),2)+1+16) | M27: =IF(MONTH(DATE($D$4,2,1)-WEEKDAY(DATE($D$4,2,1),2)+1+17)<>2,"",DATE($D$4,2,1)-WEEKDAY(DATE($D$4,2,1),2)+1+17) | N27: =IF(MONTH(DATE($D$4,2,1)-WEEKDAY(DATE($D$4,2,1),2)+1+18)<>2,"",DATE($D$4,2,1)-WEEKDAY(DATE($D$4,2,1),2)+1+18) | O27: =IF(MONTH(DATE($D$4,2,1)-WEEKDAY(DATE($D$4,2,1),2)+1+19)<>2,"",DATE($D$4,2,1)-WEEKDAY(DATE($D$4,2,1),2)+1+19) | P27: =IF(MONTH(DATE($D$4,2,1)-WEEKDAY(DATE($D$4,2,1),2)+1+20)<>2,"",DATE($D$4,2,1)-WEEKDAY(DATE($D$4,2,1),2)+1+20) | R27: =IF(MONTH(DATE($D$4,3,1)-WEEKDAY(DATE($D$4,3,1),2)+1+14)<>3,"",DATE($D$4,3,1)-WEEKDAY(DATE($D$4,3,1),2)+1+14) | S27: =IF(MONTH(DATE($D$4,3,1)-WEEKDAY(DATE($D$4,3,1),2)+1+15)<>3,"",DATE($D$4,3,1)-WEEKDAY(DATE($D$4,3,1),2)+1+15) | T27: =IF(MONTH(DATE($D$4,3,1)-WEEKDAY(DATE($D$4,3,1),2)+1+16)<>3,"",DATE($D$4,3,1)-WEEKDAY(DATE($D$4,3,1),2)+1+16) | U27: =IF(MONTH(DATE($D$4,3,1)-WEEKDAY(DATE($D$4,3,1),2)+1+17)<>3,"",DATE($D$4,3,1)-WEEKDAY(DATE($D$4,3,1),2)+1+17) | V27: =IF(MONTH(DATE($D$4,3,1)-WEEKDAY(DATE($D$4,3,1),2)+1+18)<>3,"",DATE($D$4,3,1)-WEEKDAY(DATE($D$4,3,1),2)+1+18) | W27: =IF(MONTH(DATE($D$4,3,1)-WEEKDAY(DATE($D$4,3,1),2)+1+19)<>3,"",DATE($D$4,3,1)-WEEKDAY(DATE($D$4,3,1),2)+1+19) | X27: =IF(MONTH(DATE($D$4,3,1)-WEEKDAY(DATE($D$4,3,1),2)+1+20)<>3,"",DATE($D$4,3,1)-WEEKDAY(DATE($D$4,3,1),2)+1+20)
B28: =IF(MONTH(DATE($D$4,1,1)-WEEKDAY(DATE($D$4,1,1),2)+1+21)<>1,"",DATE($D$4,1,1)-WEEKDAY(DATE($D$4,1,1),2)+1+21) | C28: =IF(MONTH(DATE($D$4,1,1)-WEEKDAY(DATE($D$4,1,1),2)+1+22)<>1,"",DATE($D$4,1,1)-WEEKDAY(DATE($D$4,1,1),2)+1+22) | D28: =IF(MONTH(DATE($D$4,1,1)-WEEKDAY(DATE($D$4,1,1),2)+1+23)<>1,"",DATE($D$4,1,1)-WEEKDAY(DATE($D$4,1,1),2)+1+23) | E28: =IF(MONTH(DATE($D$4,1,1)-WEEKDAY(DATE($D$4,1,1),2)+1+24)<>1,"",DATE($D$4,1,1)-WEEKDAY(DATE($D$4,1,1),2)+1+24) | F28: =IF(MONTH(DATE($D$4,1,1)-WEEKDAY(DATE($D$4,1,1),2)+1+25)<>1,"",DATE($D$4,1,1)-WEEKDAY(DATE($D$4,1,1),2)+1+25) | G28: =IF(MONTH(DATE($D$4,1,1)-WEEKDAY(DATE($D$4,1,1),2)+1+26)<>1,"",DATE($D$4,1,1)-WEEKDAY(DATE($D$4,1,1),2)+1+26) | H28: =IF(MONTH(DATE($D$4,1,1)-WEEKDAY(DATE($D$4,1,1),2)+1+27)<>1,"",DATE($D$4,1,1)-WEEKDAY(DATE($D$4,1,1),2)+1+27) | J28: =IF(MONTH(DATE($D$4,2,1)-WEEKDAY(DATE($D$4,2,1),2)+1+21)<>2,"",DATE($D$4,2,1)-WEEKDAY(DATE($D$4,2,1),2)+1+21) | K28: =IF(MONTH(DATE($D$4,2,1)-WEEKDAY(DATE($D$4,2,1),2)+1+22)<>2,"",DATE($D$4,2,1)-WEEKDAY(DATE($D$4,2,1),2)+1+22) | L28: =IF(MONTH(DATE($D$4,2,1)-WEEKDAY(DATE($D$4,2,1),2)+1+23)<>2,"",DATE($D$4,2,1)-WEEKDAY(DATE($D$4,2,1),2)+1+23) | M28: =IF(MONTH(DATE($D$4,2,1)-WEEKDAY(DATE($D$4,2,1),2)+1+24)<>2,"",DATE($D$4,2,1)-WEEKDAY(DATE($D$4,2,1),2)+1+24) | N28: =IF(MONTH(DATE($D$4,2,1)-WEEKDAY(DATE($D$4,2,1),2)+1+25)<>2,"",DATE($D$4,2,1)-WEEKDAY(DATE($D$4,2,1),2)+1+25) | O28: =IF(MONTH(DATE($D$4,2,1)-WEEKDAY(DATE($D$4,2,1),2)+1+26)<>2,"",DATE($D$4,2,1)-WEEKDAY(DATE($D$4,2,1),2)+1+26) | P28: =IF(MONTH(DATE($D$4,2,1)-WEEKDAY(DATE($D$4,2,1),2)+1+27)<>2,"",DATE($D$4,2,1)-WEEKDAY(DATE($D$4,2,1),2)+1+27) | R28: =IF(MONTH(DATE($D$4,3,1)-WEEKDAY(DATE($D$4,3,1),2)+1+21)<>3,"",DATE($D$4,3,1)-WEEKDAY(DATE($D$4,3,1),2)+1+21) | S28: =IF(MONTH(DATE($D$4,3,1)-WEEKDAY(DATE($D$4,3,1),2)+1+22)<>3,"",DATE($D$4,3,1)-WEEKDAY(DATE($D$4,3,1),2)+1+22) | T28: =IF(MONTH(DATE($D$4,3,1)-WEEKDAY(DATE($D$4,3,1),2)+1+23)<>3,"",DATE($D$4,3,1)-WEEKDAY(DATE($D$4,3,1),2)+1+23) | U28: =IF(MONTH(DATE($D$4,3,1)-WEEKDAY(DATE($D$4,3,1),2)+1+24)<>3,"",DATE($D$4,3,1)-WEEKDAY(DATE($D$4,3,1),2)+1+24) | V28: =IF(MONTH(DATE($D$4,3,1)-WEEKDAY(DATE($D$4,3,1),2)+1+25)<>3,"",DATE($D$4,3,1)-WEEKDAY(DATE($D$4,3,1),2)+1+25) | W28: =IF(MONTH(DATE($D$4,3,1)-WEEKDAY(DATE($D$4,3,1),2)+1+26)<>3,"",DATE($D$4,3,1)-WEEKDAY(DATE($D$4,3,1),2)+1+26) | X28: =IF(MONTH(DATE($D$4,3,1)-WEEKDAY(DATE($D$4,3,1),2)+1+27)<>3,"",DATE($D$4,3,1)-WEEKDAY(DATE($D$4,3,1),2)+1+27)
B29: =IF(MONTH(DATE($D$4,1,1)-WEEKDAY(DATE($D$4,1,1),2)+1+28)<>1,"",DATE($D$4,1,1)-WEEKDAY(DATE($D$4,1,1),2)+1+28) | C29: =IF(MONTH(DATE($D$4,1,1)-WEEKDAY(DATE($D$4,1,1),2)+1+29)<>1,"",DATE($D$4,1,1)-WEEKDAY(DATE($D$4,1,1),2)+1+29) | D29: =IF(MONTH(DATE($D$4,1,1)-WEEKDAY(DATE($D$4,1,1),2)+1+30)<>1,"",DATE($D$4,1,1)-WEEKDAY(DATE($D$4,1,1),2)+1+30) | E29: =IF(MONTH(DATE($D$4,1,1)-WEEKDAY(DATE($D$4,1,1),2)+1+31)<>1,"",DATE($D$4,1,1)-WEEKDAY(DATE($D$4,1,1),2)+1+31) | F29: =IF(MONTH(DATE($D$4,1,1)-WEEKDAY(DATE($D$4,1,1),2)+1+32)<>1,"",DATE($D$4,1,1)-WEEKDAY(DATE($D$4,1,1),2)+1+32) | G29: =IF(MONTH(DATE($D$4,1,1)-WEEKDAY(DATE($D$4,1,1),2)+1+33)<>1,"",DATE($D$4,1,1)-WEEKDAY(DATE($D$4,1,1),2)+1+33) | H29: =IF(MONTH(DATE($D$4,1,1)-WEEKDAY(DATE($D$4,1,1),2)+1+34)<>1,"",DATE($D$4,1,1)-WEEKDAY(DATE($D$4,1,1),2)+1+34) | J29: =IF(MONTH(DATE($D$4,2,1)-WEEKDAY(DATE($D$4,2,1),2)+1+28)<>2,"",DATE($D$4,2,1)-WEEKDAY(DATE($D$4,2,1),2)+1+28) | K29: =IF(MONTH(DATE($D$4,2,1)-WEEKDAY(DATE($D$4,2,1),2)+1+29)<>2,"",DATE($D$4,2,1)-WEEKDAY(DATE($D$4,2,1),2)+1+29) | L29: =IF(MONTH(DATE($D$4,2,1)-WEEKDAY(DATE($D$4,2,1),2)+1+30)<>2,"",DATE($D$4,2,1)-WEEKDAY(DATE($D$4,2,1),2)+1+30) | M29: =IF(MONTH(DATE($D$4,2,1)-WEEKDAY(DATE($D$4,2,1),2)+1+31)<>2,"",DATE($D$4,2,1)-WEEKDAY(DATE($D$4,2,1),2)+1+31) | N29: =IF(MONTH(DATE($D$4,2,1)-WEEKDAY(DATE($D$4,2,1),2)+1+32)<>2,"",DATE($D$4,2,1)-WEEKDAY(DATE($D$4,2,1),2)+1+32) | O29: =IF(MONTH(DATE($D$4,2,1)-WEEKDAY(DATE($D$4,2,1),2)+1+33)<>2,"",DATE($D$4,2,1)-WEEKDAY(DATE($D$4,2,1),2)+1+33) | P29: =IF(MONTH(DATE($D$4,2,1)-WEEKDAY(DATE($D$4,2,1),2)+1+34)<>2,"",DATE($D$4,2,1)-WEEKDAY(DATE($D$4,2,1),2)+1+34) | R29: =IF(MONTH(DATE($D$4,3,1)-WEEKDAY(DATE($D$4,3,1),2)+1+28)<>3,"",DATE($D$4,3,1)-WEEKDAY(DATE($D$4,3,1),2)+1+28) | S29: =IF(MONTH(DATE($D$4,3,1)-WEEKDAY(DATE($D$4,3,1),2)+1+29)<>3,"",DATE($D$4,3,1)-WEEKDAY(DATE($D$4,3,1),2)+1+29) | T29: =IF(MONTH(DATE($D$4,3,1)-WEEKDAY(DATE($D$4,3,1),2)+1+30)<>3,"",DATE($D$4,3,1)-WEEKDAY(DATE($D$4,3,1),2)+1+30) | U29: =IF(MONTH(DATE($D$4,3,1)-WEEKDAY(DATE($D$4,3,1),2)+1+31)<>3,"",DATE($D$4,3,1)-WEEKDAY(DATE($D$4,3,1),2)+1+31) | V29: =IF(MONTH(DATE($D$4,3,1)-WEEKDAY(DATE($D$4,3,1),2)+1+32)<>3,"",DATE($D$4,3,1)-WEEKDAY(DATE($D$4,3,1),2)+1+32) | W29: =IF(MONTH(DATE($D$4,3,1)-WEEKDAY(DATE($D$4,3,1),2)+1+33)<>3,"",DATE($D$4,3,1)-WEEKDAY(DATE($D$4,3,1),2)+1+33) | X29: =IF(MONTH(DATE($D$4,3,1)-WEEKDAY(DATE($D$4,3,1),2)+1+34)<>3,"",DATE($D$4,3,1)-WEEKDAY(DATE($D$4,3,1),2)+1+34)
B30: =IF(MONTH(DATE($D$4,1,1)-WEEKDAY(DATE($D$4,1,1),2)+1+35)<>1,"",DATE($D$4,1,1)-WEEKDAY(DATE($D$4,1,1),2)+1+35) | C30: =IF(MONTH(DATE($D$4,1,1)-WEEKDAY(DATE($D$4,1,1),2)+1+36)<>1,"",DATE($D$4,1,1)-WEEKDAY(DATE($D$4,1,1),2)+1+36) | D30: =IF(MONTH(DATE($D$4,1,1)-WEEKDAY(DATE($D$4,1,1),2)+1+37)<>1,"",DATE($D$4,1,1)-WEEKDAY(DATE($D$4,1,1),2)+1+37) | E30: =IF(MONTH(DATE($D$4,1,1)-WEEKDAY(DATE($D$4,1,1),2)+1+38)<>1,"",DATE($D$4,1,1)-WEEKDAY(DATE($D$4,1,1),2)+1+38) | F30: =IF(MONTH(DATE($D$4,1,1)-WEEKDAY(DATE($D$4,1,1),2)+1+39)<>1,"",DATE($D$4,1,1)-WEEKDAY(DATE($D$4,1,1),2)+1+39) | G30: =IF(MONTH(DATE($D$4,1,1)-WEEKDAY(DATE($D$4,1,1),2)+1+40)<>1,"",DATE($D$4,1,1)-WEEKDAY(DATE($D$4,1,1),2)+1+40) | H30: =IF(MONTH(DATE($D$4,1,1)-WEEKDAY(DATE($D$4,1,1),2)+1+41)<>1,"",DATE($D$4,1,1)-WEEKDAY(DATE($D$4,1,1),2)+1+41) | J30: =IF(MONTH(DATE($D$4,2,1)-WEEKDAY(DATE($D$4,2,1),2)+1+35)<>2,"",DATE($D$4,2,1)-WEEKDAY(DATE($D$4,2,1),2)+1+35) | K30: =IF(MONTH(DATE($D$4,2,1)-WEEKDAY(DATE($D$4,2,1),2)+1+36)<>2,"",DATE($D$4,2,1)-WEEKDAY(DATE($D$4,2,1),2)+1+36) | L30: =IF(MONTH(DATE($D$4,2,1)-WEEKDAY(DATE($D$4,2,1),2)+1+37)<>2,"",DATE($D$4,2,1)-WEEKDAY(DATE($D$4,2,1),2)+1+37) | M30: =IF(MONTH(DATE($D$4,2,1)-WEEKDAY(DATE($D$4,2,1),2)+1+38)<>2,"",DATE($D$4,2,1)-WEEKDAY(DATE($D$4,2,1),2)+1+38) | N30: =IF(MONTH(DATE($D$4,2,1)-WEEKDAY(DATE($D$4,2,1),2)+1+39)<>2,"",DATE($D$4,2,1)-WEEKDAY(DATE($D$4,2,1),2)+1+39) | O30: =IF(MONTH(DATE($D$4,2,1)-WEEKDAY(DATE($D$4,2,1),2)+1+40)<>2,"",DATE($D$4,2,1)-WEEKDAY(DATE($D$4,2,1),2)+1+40) | P30: =IF(MONTH(DATE($D$4,2,1)-WEEKDAY(DATE($D$4,2,1),2)+1+41)<>2,"",DATE($D$4,2,1)-WEEKDAY(DATE($D$4,2,1),2)+1+41) | R30: =IF(MONTH(DATE($D$4,3,1)-WEEKDAY(DATE($D$4,3,1),2)+1+35)<>3,"",DATE($D$4,3,1)-WEEKDAY(DATE($D$4,3,1),2)+1+35) | S30: =IF(MONTH(DATE($D$4,3,1)-WEEKDAY(DATE($D$4,3,1),2)+1+36)<>3,"",DATE($D$4,3,1)-WEEKDAY(DATE($D$4,3,1),2)+1+36) | T30: =IF(MONTH(DATE($D$4,3,1)-WEEKDAY(DATE($D$4,3,1),2)+1+37)<>3,"",DATE($D$4,3,1)-WEEKDAY(DATE($D$4,3,1),2)+1+37) | U30: =IF(MONTH(DATE($D$4,3,1)-WEEKDAY(DATE($D$4,3,1),2)+1+38)<>3,"",DATE($D$4,3,1)-WEEKDAY(DATE($D$4,3,1),2)+1+38) | V30: =IF(MONTH(DATE($D$4,3,1)-WEEKDAY(DATE($D$4,3,1),2)+1+39)<>3,"",DATE($D$4,3,1)-WEEKDAY(DATE($D$4,3,1),2)+1+39) | W30: =IF(MONTH(DATE($D$4,3,1)-WEEKDAY(DATE($D$4,3,1),2)+1+40)<>3,"",DATE($D$4,3,1)-WEEKDAY(DATE($D$4,3,1),2)+1+40) | X30: =IF(MONTH(DATE($D$4,3,1)-WEEKDAY(DATE($D$4,3,1),2)+1+41)<>3,"",DATE($D$4,3,1)-WEEKDAY(DATE($D$4,3,1),2)+1+41)
B32: ="ABRIL "&$D$4 | G32: =IF(COUNTIFS($B$62:$B$211,">="&DATE($D$4,4,1),$B$62:$B$211,"<="&EOMONTH(DATE($D$4,4,1),0),$V$62:$V$211,"<>4 · Cancelada")=1,"1 cita",COUNTIFS($B$62:$B$211,">="&DATE($D$4,4,1),$B$62:$B$211,"<="&EOMONTH(DATE($D$4,4,1),0),$V$62:$V$211,"<>4 · Cancelada")&" citas") | J32: ="MAYO "&$D$4 | O32: =IF(COUNTIFS($B$62:$B$211,">="&DATE($D$4,5,1),$B$62:$B$211,"<="&EOMONTH(DATE($D$4,5,1),0),$V$62:$V$211,"<>4 · Cancelada")=1,"1 cita",COUNTIFS($B$62:$B$211,">="&DATE($D$4,5,1),$B$62:$B$211,"<="&EOMONTH(DATE($D$4,5,1),0),$V$62:$V$211,"<>4 · Cancelada")&" citas") | R32: ="JUNIO "&$D$4 | W32: =IF(COUNTIFS($B$62:$B$211,">="&DATE($D$4,6,1),$B$62:$B$211,"<="&EOMONTH(DATE($D$4,6,1),0),$V$62:$V$211,"<>4 · Cancelada")=1,"1 cita",COUNTIFS($B$62:$B$211,">="&DATE($D$4,6,1),$B$62:$B$211,"<="&EOMONTH(DATE($D$4,6,1),0),$V$62:$V$211,"<>4 · Cancelada")&" citas")
B33: L | C33: M | D33: X | E33: J | F33: V | G33: S | H33: D | J33: L | K33: M | L33: X | M33: J | N33: V | O33: S | P33: D | R33: L | S33: M | T33: X | U33: J | V33: V | W33: S | X33: D
B34: =IF(MONTH(DATE($D$4,4,1)-WEEKDAY(DATE($D$4,4,1),2)+1+0)<>4,"",DATE($D$4,4,1)-WEEKDAY(DATE($D$4,4,1),2)+1+0) | C34: =IF(MONTH(DATE($D$4,4,1)-WEEKDAY(DATE($D$4,4,1),2)+1+1)<>4,"",DATE($D$4,4,1)-WEEKDAY(DATE($D$4,4,1),2)+1+1) | D34: =IF(MONTH(DATE($D$4,4,1)-WEEKDAY(DATE($D$4,4,1),2)+1+2)<>4,"",DATE($D$4,4,1)-WEEKDAY(DATE($D$4,4,1),2)+1+2) | E34: =IF(MONTH(DATE($D$4,4,1)-WEEKDAY(DATE($D$4,4,1),2)+1+3)<>4,"",DATE($D$4,4,1)-WEEKDAY(DATE($D$4,4,1),2)+1+3) | F34: =IF(MONTH(DATE($D$4,4,1)-WEEKDAY(DATE($D$4,4,1),2)+1+4)<>4,"",DATE($D$4,4,1)-WEEKDAY(DATE($D$4,4,1),2)+1+4) | G34: =IF(MONTH(DATE($D$4,4,1)-WEEKDAY(DATE($D$4,4,1),2)+1+5)<>4,"",DATE($D$4,4,1)-WEEKDAY(DATE($D$4,4,1),2)+1+5) | H34: =IF(MONTH(DATE($D$4,4,1)-WEEKDAY(DATE($D$4,4,1),2)+1+6)<>4,"",DATE($D$4,4,1)-WEEKDAY(DATE($D$4,4,1),2)+1+6) | J34: =IF(MONTH(DATE($D$4,5,1)-WEEKDAY(DATE($D$4,5,1),2)+1+0)<>5,"",DATE($D$4,5,1)-WEEKDAY(DATE($D$4,5,1),2)+1+0) | K34: =IF(MONTH(DATE($D$4,5,1)-WEEKDAY(DATE($D$4,5,1),2)+1+1)<>5,"",DATE($D$4,5,1)-WEEKDAY(DATE($D$4,5,1),2)+1+1) | L34: =IF(MONTH(DATE($D$4,5,1)-WEEKDAY(DATE($D$4,5,1),2)+1+2)<>5,"",DATE($D$4,5,1)-WEEKDAY(DATE($D$4,5,1),2)+1+2) | M34: =IF(MONTH(DATE($D$4,5,1)-WEEKDAY(DATE($D$4,5,1),2)+1+3)<>5,"",DATE($D$4,5,1)-WEEKDAY(DATE($D$4,5,1),2)+1+3) | N34: =IF(MONTH(DATE($D$4,5,1)-WEEKDAY(DATE($D$4,5,1),2)+1+4)<>5,"",DATE($D$4,5,1)-WEEKDAY(DATE($D$4,5,1),2)+1+4) | O34: =IF(MONTH(DATE($D$4,5,1)-WEEKDAY(DATE($D$4,5,1),2)+1+5)<>5,"",DATE($D$4,5,1)-WEEKDAY(DATE($D$4,5,1),2)+1+5) | P34: =IF(MONTH(DATE($D$4,5,1)-WEEKDAY(DATE($D$4,5,1),2)+1+6)<>5,"",DATE($D$4,5,1)-WEEKDAY(DATE($D$4,5,1),2)+1+6) | R34: =IF(MONTH(DATE($D$4,6,1)-WEEKDAY(DATE($D$4,6,1),2)+1+0)<>6,"",DATE($D$4,6,1)-WEEKDAY(DATE($D$4,6,1),2)+1+0) | S34: =IF(MONTH(DATE($D$4,6,1)-WEEKDAY(DATE($D$4,6,1),2)+1+1)<>6,"",DATE($D$4,6,1)-WEEKDAY(DATE($D$4,6,1),2)+1+1) | T34: =IF(MONTH(DATE($D$4,6,1)-WEEKDAY(DATE($D$4,6,1),2)+1+2)<>6,"",DATE($D$4,6,1)-WEEKDAY(DATE($D$4,6,1),2)+1+2) | U34: =IF(MONTH(DATE($D$4,6,1)-WEEKDAY(DATE($D$4,6,1),2)+1+3)<>6,"",DATE($D$4,6,1)-WEEKDAY(DATE($D$4,6,1),2)+1+3) | V34: =IF(MONTH(DATE($D$4,6,1)-WEEKDAY(DATE($D$4,6,1),2)+1+4)<>6,"",DATE($D$4,6,1)-WEEKDAY(DATE($D$4,6,1),2)+1+4) | W34: =IF(MONTH(DATE($D$4,6,1)-WEEKDAY(DATE($D$4,6,1),2)+1+5)<>6,"",DATE($D$4,6,1)-WEEKDAY(DATE($D$4,6,1),2)+1+5) | X34: =IF(MONTH(DATE($D$4,6,1)-WEEKDAY(DATE($D$4,6,1),2)+1+6)<>6,"",DATE($D$4,6,1)-WEEKDAY(DATE($D$4,6,1),2)+1+6)
B35: =IF(MONTH(DATE($D$4,4,1)-WEEKDAY(DATE($D$4,4,1),2)+1+7)<>4,"",DATE($D$4,4,1)-WEEKDAY(DATE($D$4,4,1),2)+1+7) | C35: =IF(MONTH(DATE($D$4,4,1)-WEEKDAY(DATE($D$4,4,1),2)+1+8)<>4,"",DATE($D$4,4,1)-WEEKDAY(DATE($D$4,4,1),2)+1+8) | D35: =IF(MONTH(DATE($D$4,4,1)-WEEKDAY(DATE($D$4,4,1),2)+1+9)<>4,"",DATE($D$4,4,1)-WEEKDAY(DATE($D$4,4,1),2)+1+9) | E35: =IF(MONTH(DATE($D$4,4,1)-WEEKDAY(DATE($D$4,4,1),2)+1+10)<>4,"",DATE($D$4,4,1)-WEEKDAY(DATE($D$4,4,1),2)+1+10) | F35: =IF(MONTH(DATE($D$4,4,1)-WEEKDAY(DATE($D$4,4,1),2)+1+11)<>4,"",DATE($D$4,4,1)-WEEKDAY(DATE($D$4,4,1),2)+1+11) | G35: =IF(MONTH(DATE($D$4,4,1)-WEEKDAY(DATE($D$4,4,1),2)+1+12)<>4,"",DATE($D$4,4,1)-WEEKDAY(DATE($D$4,4,1),2)+1+12) | H35: =IF(MONTH(DATE($D$4,4,1)-WEEKDAY(DATE($D$4,4,1),2)+1+13)<>4,"",DATE($D$4,4,1)-WEEKDAY(DATE($D$4,4,1),2)+1+13) | J35: =IF(MONTH(DATE($D$4,5,1)-WEEKDAY(DATE($D$4,5,1),2)+1+7)<>5,"",DATE($D$4,5,1)-WEEKDAY(DATE($D$4,5,1),2)+1+7) | K35: =IF(MONTH(DATE($D$4,5,1)-WEEKDAY(DATE($D$4,5,1),2)+1+8)<>5,"",DATE($D$4,5,1)-WEEKDAY(DATE($D$4,5,1),2)+1+8) | L35: =IF(MONTH(DATE($D$4,5,1)-WEEKDAY(DATE($D$4,5,1),2)+1+9)<>5,"",DATE($D$4,5,1)-WEEKDAY(DATE($D$4,5,1),2)+1+9) | M35: =IF(MONTH(DATE($D$4,5,1)-WEEKDAY(DATE($D$4,5,1),2)+1+10)<>5,"",DATE($D$4,5,1)-WEEKDAY(DATE($D$4,5,1),2)+1+10) | N35: =IF(MONTH(DATE($D$4,5,1)-WEEKDAY(DATE($D$4,5,1),2)+1+11)<>5,"",DATE($D$4,5,1)-WEEKDAY(DATE($D$4,5,1),2)+1+11) | O35: =IF(MONTH(DATE($D$4,5,1)-WEEKDAY(DATE($D$4,5,1),2)+1+12)<>5,"",DATE($D$4,5,1)-WEEKDAY(DATE($D$4,5,1),2)+1+12) | P35: =IF(MONTH(DATE($D$4,5,1)-WEEKDAY(DATE($D$4,5,1),2)+1+13)<>5,"",DATE($D$4,5,1)-WEEKDAY(DATE($D$4,5,1),2)+1+13) | R35: =IF(MONTH(DATE($D$4,6,1)-WEEKDAY(DATE($D$4,6,1),2)+1+7)<>6,"",DATE($D$4,6,1)-WEEKDAY(DATE($D$4,6,1),2)+1+7) | S35: =IF(MONTH(DATE($D$4,6,1)-WEEKDAY(DATE($D$4,6,1),2)+1+8)<>6,"",DATE($D$4,6,1)-WEEKDAY(DATE($D$4,6,1),2)+1+8) | T35: =IF(MONTH(DATE($D$4,6,1)-WEEKDAY(DATE($D$4,6,1),2)+1+9)<>6,"",DATE($D$4,6,1)-WEEKDAY(DATE($D$4,6,1),2)+1+9) | U35: =IF(MONTH(DATE($D$4,6,1)-WEEKDAY(DATE($D$4,6,1),2)+1+10)<>6,"",DATE($D$4,6,1)-WEEKDAY(DATE($D$4,6,1),2)+1+10) | V35: =IF(MONTH(DATE($D$4,6,1)-WEEKDAY(DATE($D$4,6,1),2)+1+11)<>6,"",DATE($D$4,6,1)-WEEKDAY(DATE($D$4,6,1),2)+1+11) | W35: =IF(MONTH(DATE($D$4,6,1)-WEEKDAY(DATE($D$4,6,1),2)+1+12)<>6,"",DATE($D$4,6,1)-WEEKDAY(DATE($D$4,6,1),2)+1+12) | X35: =IF(MONTH(DATE($D$4,6,1)-WEEKDAY(DATE($D$4,6,1),2)+1+13)<>6,"",DATE($D$4,6,1)-WEEKDAY(DATE($D$4,6,1),2)+1+13)
B36: =IF(MONTH(DATE($D$4,4,1)-WEEKDAY(DATE($D$4,4,1),2)+1+14)<>4,"",DATE($D$4,4,1)-WEEKDAY(DATE($D$4,4,1),2)+1+14) | C36: =IF(MONTH(DATE($D$4,4,1)-WEEKDAY(DATE($D$4,4,1),2)+1+15)<>4,"",DATE($D$4,4,1)-WEEKDAY(DATE($D$4,4,1),2)+1+15) | D36: =IF(MONTH(DATE($D$4,4,1)-WEEKDAY(DATE($D$4,4,1),2)+1+16)<>4,"",DATE($D$4,4,1)-WEEKDAY(DATE($D$4,4,1),2)+1+16) | E36: =IF(MONTH(DATE($D$4,4,1)-WEEKDAY(DATE($D$4,4,1),2)+1+17)<>4,"",DATE($D$4,4,1)-WEEKDAY(DATE($D$4,4,1),2)+1+17) | F36: =IF(MONTH(DATE($D$4,4,1)-WEEKDAY(DATE($D$4,4,1),2)+1+18)<>4,"",DATE($D$4,4,1)-WEEKDAY(DATE($D$4,4,1),2)+1+18) | G36: =IF(MONTH(DATE($D$4,4,1)-WEEKDAY(DATE($D$4,4,1),2)+1+19)<>4,"",DATE($D$4,4,1)-WEEKDAY(DATE($D$4,4,1),2)+1+19) | H36: =IF(MONTH(DATE($D$4,4,1)-WEEKDAY(DATE($D$4,4,1),2)+1+20)<>4,"",DATE($D$4,4,1)-WEEKDAY(DATE($D$4,4,1),2)+1+20) | J36: =IF(MONTH(DATE($D$4,5,1)-WEEKDAY(DATE($D$4,5,1),2)+1+14)<>5,"",DATE($D$4,5,1)-WEEKDAY(DATE($D$4,5,1),2)+1+14) | K36: =IF(MONTH(DATE($D$4,5,1)-WEEKDAY(DATE($D$4,5,1),2)+1+15)<>5,"",DATE($D$4,5,1)-WEEKDAY(DATE($D$4,5,1),2)+1+15) | L36: =IF(MONTH(DATE($D$4,5,1)-WEEKDAY(DATE($D$4,5,1),2)+1+16)<>5,"",DATE($D$4,5,1)-WEEKDAY(DATE($D$4,5,1),2)+1+16) | M36: =IF(MONTH(DATE($D$4,5,1)-WEEKDAY(DATE($D$4,5,1),2)+1+17)<>5,"",DATE($D$4,5,1)-WEEKDAY(DATE($D$4,5,1),2)+1+17) | N36: =IF(MONTH(DATE($D$4,5,1)-WEEKDAY(DATE($D$4,5,1),2)+1+18)<>5,"",DATE($D$4,5,1)-WEEKDAY(DATE($D$4,5,1),2)+1+18) | O36: =IF(MONTH(DATE($D$4,5,1)-WEEKDAY(DATE($D$4,5,1),2)+1+19)<>5,"",DATE($D$4,5,1)-WEEKDAY(DATE($D$4,5,1),2)+1+19) | P36: =IF(MONTH(DATE($D$4,5,1)-WEEKDAY(DATE($D$4,5,1),2)+1+20)<>5,"",DATE($D$4,5,1)-WEEKDAY(DATE($D$4,5,1),2)+1+20) | R36: =IF(MONTH(DATE($D$4,6,1)-WEEKDAY(DATE($D$4,6,1),2)+1+14)<>6,"",DATE($D$4,6,1)-WEEKDAY(DATE($D$4,6,1),2)+1+14) | S36: =IF(MONTH(DATE($D$4,6,1)-WEEKDAY(DATE($D$4,6,1),2)+1+15)<>6,"",DATE($D$4,6,1)-WEEKDAY(DATE($D$4,6,1),2)+1+15) | T36: =IF(MONTH(DATE($D$4,6,1)-WEEKDAY(DATE($D$4,6,1),2)+1+16)<>6,"",DATE($D$4,6,1)-WEEKDAY(DATE($D$4,6,1),2)+1+16) | U36: =IF(MONTH(DATE($D$4,6,1)-WEEKDAY(DATE($D$4,6,1),2)+1+17)<>6,"",DATE($D$4,6,1)-WEEKDAY(DATE($D$4,6,1),2)+1+17) | V36: =IF(MONTH(DATE($D$4,6,1)-WEEKDAY(DATE($D$4,6,1),2)+1+18)<>6,"",DATE($D$4,6,1)-WEEKDAY(DATE($D$4,6,1),2)+1+18) | W36: =IF(MONTH(DATE($D$4,6,1)-WEEKDAY(DATE($D$4,6,1),2)+1+19)<>6,"",DATE($D$4,6,1)-WEEKDAY(DATE($D$4,6,1),2)+1+19) | X36: =IF(MONTH(DATE($D$4,6,1)-WEEKDAY(DATE($D$4,6,1),2)+1+20)<>6,"",DATE($D$4,6,1)-WEEKDAY(DATE($D$4,6,1),2)+1+20)
B37: =IF(MONTH(DATE($D$4,4,1)-WEEKDAY(DATE($D$4,4,1),2)+1+21)<>4,"",DATE($D$4,4,1)-WEEKDAY(DATE($D$4,4,1),2)+1+21) | C37: =IF(MONTH(DATE($D$4,4,1)-WEEKDAY(DATE($D$4,4,1),2)+1+22)<>4,"",DATE($D$4,4,1)-WEEKDAY(DATE($D$4,4,1),2)+1+22) | D37: =IF(MONTH(DATE($D$4,4,1)-WEEKDAY(DATE($D$4,4,1),2)+1+23)<>4,"",DATE($D$4,4,1)-WEEKDAY(DATE($D$4,4,1),2)+1+23) | E37: =IF(MONTH(DATE($D$4,4,1)-WEEKDAY(DATE($D$4,4,1),2)+1+24)<>4,"",DATE($D$4,4,1)-WEEKDAY(DATE($D$4,4,1),2)+1+24) | F37: =IF(MONTH(DATE($D$4,4,1)-WEEKDAY(DATE($D$4,4,1),2)+1+25)<>4,"",DATE($D$4,4,1)-WEEKDAY(DATE($D$4,4,1),2)+1+25) | G37: =IF(MONTH(DATE($D$4,4,1)-WEEKDAY(DATE($D$4,4,1),2)+1+26)<>4,"",DATE($D$4,4,1)-WEEKDAY(DATE($D$4,4,1),2)+1+26) | H37: =IF(MONTH(DATE($D$4,4,1)-WEEKDAY(DATE($D$4,4,1),2)+1+27)<>4,"",DATE($D$4,4,1)-WEEKDAY(DATE($D$4,4,1),2)+1+27) | J37: =IF(MONTH(DATE($D$4,5,1)-WEEKDAY(DATE($D$4,5,1),2)+1+21)<>5,"",DATE($D$4,5,1)-WEEKDAY(DATE($D$4,5,1),2)+1+21) | K37: =IF(MONTH(DATE($D$4,5,1)-WEEKDAY(DATE($D$4,5,1),2)+1+22)<>5,"",DATE($D$4,5,1)-WEEKDAY(DATE($D$4,5,1),2)+1+22) | L37: =IF(MONTH(DATE($D$4,5,1)-WEEKDAY(DATE($D$4,5,1),2)+1+23)<>5,"",DATE($D$4,5,1)-WEEKDAY(DATE($D$4,5,1),2)+1+23) | M37: =IF(MONTH(DATE($D$4,5,1)-WEEKDAY(DATE($D$4,5,1),2)+1+24)<>5,"",DATE($D$4,5,1)-WEEKDAY(DATE($D$4,5,1),2)+1+24) | N37: =IF(MONTH(DATE($D$4,5,1)-WEEKDAY(DATE($D$4,5,1),2)+1+25)<>5,"",DATE($D$4,5,1)-WEEKDAY(DATE($D$4,5,1),2)+1+25) | O37: =IF(MONTH(DATE($D$4,5,1)-WEEKDAY(DATE($D$4,5,1),2)+1+26)<>5,"",DATE($D$4,5,1)-WEEKDAY(DATE($D$4,5,1),2)+1+26) | P37: =IF(MONTH(DATE($D$4,5,1)-WEEKDAY(DATE($D$4,5,1),2)+1+27)<>5,"",DATE($D$4,5,1)-WEEKDAY(DATE($D$4,5,1),2)+1+27) | R37: =IF(MONTH(DATE($D$4,6,1)-WEEKDAY(DATE($D$4,6,1),2)+1+21)<>6,"",DATE($D$4,6,1)-WEEKDAY(DATE($D$4,6,1),2)+1+21) | S37: =IF(MONTH(DATE($D$4,6,1)-WEEKDAY(DATE($D$4,6,1),2)+1+22)<>6,"",DATE($D$4,6,1)-WEEKDAY(DATE($D$4,6,1),2)+1+22) | T37: =IF(MONTH(DATE($D$4,6,1)-WEEKDAY(DATE($D$4,6,1),2)+1+23)<>6,"",DATE($D$4,6,1)-WEEKDAY(DATE($D$4,6,1),2)+1+23) | U37: =IF(MONTH(DATE($D$4,6,1)-WEEKDAY(DATE($D$4,6,1),2)+1+24)<>6,"",DATE($D$4,6,1)-WEEKDAY(DATE($D$4,6,1),2)+1+24) | V37: =IF(MONTH(DATE($D$4,6,1)-WEEKDAY(DATE($D$4,6,1),2)+1+25)<>6,"",DATE($D$4,6,1)-WEEKDAY(DATE($D$4,6,1),2)+1+25) | W37: =IF(MONTH(DATE($D$4,6,1)-WEEKDAY(DATE($D$4,6,1),2)+1+26)<>6,"",DATE($D$4,6,1)-WEEKDAY(DATE($D$4,6,1),2)+1+26) | X37: =IF(MONTH(DATE($D$4,6,1)-WEEKDAY(DATE($D$4,6,1),2)+1+27)<>6,"",DATE($D$4,6,1)-WEEKDAY(DATE($D$4,6,1),2)+1+27)
B38: =IF(MONTH(DATE($D$4,4,1)-WEEKDAY(DATE($D$4,4,1),2)+1+28)<>4,"",DATE($D$4,4,1)-WEEKDAY(DATE($D$4,4,1),2)+1+28) | C38: =IF(MONTH(DATE($D$4,4,1)-WEEKDAY(DATE($D$4,4,1),2)+1+29)<>4,"",DATE($D$4,4,1)-WEEKDAY(DATE($D$4,4,1),2)+1+29) | D38: =IF(MONTH(DATE($D$4,4,1)-WEEKDAY(DATE($D$4,4,1),2)+1+30)<>4,"",DATE($D$4,4,1)-WEEKDAY(DATE($D$4,4,1),2)+1+30) | E38: =IF(MONTH(DATE($D$4,4,1)-WEEKDAY(DATE($D$4,4,1),2)+1+31)<>4,"",DATE($D$4,4,1)-WEEKDAY(DATE($D$4,4,1),2)+1+31) | F38: =IF(MONTH(DATE($D$4,4,1)-WEEKDAY(DATE($D$4,4,1),2)+1+32)<>4,"",DATE($D$4,4,1)-WEEKDAY(DATE($D$4,4,1),2)+1+32) | G38: =IF(MONTH(DATE($D$4,4,1)-WEEKDAY(DATE($D$4,4,1),2)+1+33)<>4,"",DATE($D$4,4,1)-WEEKDAY(DATE($D$4,4,1),2)+1+33) | H38: =IF(MONTH(DATE($D$4,4,1)-WEEKDAY(DATE($D$4,4,1),2)+1+34)<>4,"",DATE($D$4,4,1)-WEEKDAY(DATE($D$4,4,1),2)+1+34) | J38: =IF(MONTH(DATE($D$4,5,1)-WEEKDAY(DATE($D$4,5,1),2)+1+28)<>5,"",DATE($D$4,5,1)-WEEKDAY(DATE($D$4,5,1),2)+1+28) | K38: =IF(MONTH(DATE($D$4,5,1)-WEEKDAY(DATE($D$4,5,1),2)+1+29)<>5,"",DATE($D$4,5,1)-WEEKDAY(DATE($D$4,5,1),2)+1+29) | L38: =IF(MONTH(DATE($D$4,5,1)-WEEKDAY(DATE($D$4,5,1),2)+1+30)<>5,"",DATE($D$4,5,1)-WEEKDAY(DATE($D$4,5,1),2)+1+30) | M38: =IF(MONTH(DATE($D$4,5,1)-WEEKDAY(DATE($D$4,5,1),2)+1+31)<>5,"",DATE($D$4,5,1)-WEEKDAY(DATE($D$4,5,1),2)+1+31) | N38: =IF(MONTH(DATE($D$4,5,1)-WEEKDAY(DATE($D$4,5,1),2)+1+32)<>5,"",DATE($D$4,5,1)-WEEKDAY(DATE($D$4,5,1),2)+1+32) | O38: =IF(MONTH(DATE($D$4,5,1)-WEEKDAY(DATE($D$4,5,1),2)+1+33)<>5,"",DATE($D$4,5,1)-WEEKDAY(DATE($D$4,5,1),2)+1+33) | P38: =IF(MONTH(DATE($D$4,5,1)-WEEKDAY(DATE($D$4,5,1),2)+1+34)<>5,"",DATE($D$4,5,1)-WEEKDAY(DATE($D$4,5,1),2)+1+34) | R38: =IF(MONTH(DATE($D$4,6,1)-WEEKDAY(DATE($D$4,6,1),2)+1+28)<>6,"",DATE($D$4,6,1)-WEEKDAY(DATE($D$4,6,1),2)+1+28) | S38: =IF(MONTH(DATE($D$4,6,1)-WEEKDAY(DATE($D$4,6,1),2)+1+29)<>6,"",DATE($D$4,6,1)-WEEKDAY(DATE($D$4,6,1),2)+1+29) | T38: =IF(MONTH(DATE($D$4,6,1)-WEEKDAY(DATE($D$4,6,1),2)+1+30)<>6,"",DATE($D$4,6,1)-WEEKDAY(DATE($D$4,6,1),2)+1+30) | U38: =IF(MONTH(DATE($D$4,6,1)-WEEKDAY(DATE($D$4,6,1),2)+1+31)<>6,"",DATE($D$4,6,1)-WEEKDAY(DATE($D$4,6,1),2)+1+31) | V38: =IF(MONTH(DATE($D$4,6,1)-WEEKDAY(DATE($D$4,6,1),2)+1+32)<>6,"",DATE($D$4,6,1)-WEEKDAY(DATE($D$4,6,1),2)+1+32) | W38: =IF(MONTH(DATE($D$4,6,1)-WEEKDAY(DATE($D$4,6,1),2)+1+33)<>6,"",DATE($D$4,6,1)-WEEKDAY(DATE($D$4,6,1),2)+1+33) | X38: =IF(MONTH(DATE($D$4,6,1)-WEEKDAY(DATE($D$4,6,1),2)+1+34)<>6,"",DATE($D$4,6,1)-WEEKDAY(DATE($D$4,6,1),2)+1+34)
B39: =IF(MONTH(DATE($D$4,4,1)-WEEKDAY(DATE($D$4,4,1),2)+1+35)<>4,"",DATE($D$4,4,1)-WEEKDAY(DATE($D$4,4,1),2)+1+35) | C39: =IF(MONTH(DATE($D$4,4,1)-WEEKDAY(DATE($D$4,4,1),2)+1+36)<>4,"",DATE($D$4,4,1)-WEEKDAY(DATE($D$4,4,1),2)+1+36) | D39: =IF(MONTH(DATE($D$4,4,1)-WEEKDAY(DATE($D$4,4,1),2)+1+37)<>4,"",DATE($D$4,4,1)-WEEKDAY(DATE($D$4,4,1),2)+1+37) | E39: =IF(MONTH(DATE($D$4,4,1)-WEEKDAY(DATE($D$4,4,1),2)+1+38)<>4,"",DATE($D$4,4,1)-WEEKDAY(DATE($D$4,4,1),2)+1+38) | F39: =IF(MONTH(DATE($D$4,4,1)-WEEKDAY(DATE($D$4,4,1),2)+1+39)<>4,"",DATE($D$4,4,1)-WEEKDAY(DATE($D$4,4,1),2)+1+39) | G39: =IF(MONTH(DATE($D$4,4,1)-WEEKDAY(DATE($D$4,4,1),2)+1+40)<>4,"",DATE($D$4,4,1)-WEEKDAY(DATE($D$4,4,1),2)+1+40) | H39: =IF(MONTH(DATE($D$4,4,1)-WEEKDAY(DATE($D$4,4,1),2)+1+41)<>4,"",DATE($D$4,4,1)-WEEKDAY(DATE($D$4,4,1),2)+1+41) | J39: =IF(MONTH(DATE($D$4,5,1)-WEEKDAY(DATE($D$4,5,1),2)+1+35)<>5,"",DATE($D$4,5,1)-WEEKDAY(DATE($D$4,5,1),2)+1+35) | K39: =IF(MONTH(DATE($D$4,5,1)-WEEKDAY(DATE($D$4,5,1),2)+1+36)<>5,"",DATE($D$4,5,1)-WEEKDAY(DATE($D$4,5,1),2)+1+36) | L39: =IF(MONTH(DATE($D$4,5,1)-WEEKDAY(DATE($D$4,5,1),2)+1+37)<>5,"",DATE($D$4,5,1)-WEEKDAY(DATE($D$4,5,1),2)+1+37) | M39: =IF(MONTH(DATE($D$4,5,1)-WEEKDAY(DATE($D$4,5,1),2)+1+38)<>5,"",DATE($D$4,5,1)-WEEKDAY(DATE($D$4,5,1),2)+1+38) | N39: =IF(MONTH(DATE($D$4,5,1)-WEEKDAY(DATE($D$4,5,1),2)+1+39)<>5,"",DATE($D$4,5,1)-WEEKDAY(DATE($D$4,5,1),2)+1+39) | O39: =IF(MONTH(DATE($D$4,5,1)-WEEKDAY(DATE($D$4,5,1),2)+1+40)<>5,"",DATE($D$4,5,1)-WEEKDAY(DATE($D$4,5,1),2)+1+40) | P39: =IF(MONTH(DATE($D$4,5,1)-WEEKDAY(DATE($D$4,5,1),2)+1+41)<>5,"",DATE($D$4,5,1)-WEEKDAY(DATE($D$4,5,1),2)+1+41) | R39: =IF(MONTH(DATE($D$4,6,1)-WEEKDAY(DATE($D$4,6,1),2)+1+35)<>6,"",DATE($D$4,6,1)-WEEKDAY(DATE($D$4,6,1),2)+1+35) | S39: =IF(MONTH(DATE($D$4,6,1)-WEEKDAY(DATE($D$4,6,1),2)+1+36)<>6,"",DATE($D$4,6,1)-WEEKDAY(DATE($D$4,6,1),2)+1+36) | T39: =IF(MONTH(DATE($D$4,6,1)-WEEKDAY(DATE($D$4,6,1),2)+1+37)<>6,"",DATE($D$4,6,1)-WEEKDAY(DATE($D$4,6,1),2)+1+37) | U39: =IF(MONTH(DATE($D$4,6,1)-WEEKDAY(DATE($D$4,6,1),2)+1+38)<>6,"",DATE($D$4,6,1)-WEEKDAY(DATE($D$4,6,1),2)+1+38) | V39: =IF(MONTH(DATE($D$4,6,1)-WEEKDAY(DATE($D$4,6,1),2)+1+39)<>6,"",DATE($D$4,6,1)-WEEKDAY(DATE($D$4,6,1),2)+1+39) | W39: =IF(MONTH(DATE($D$4,6,1)-WEEKDAY(DATE($D$4,6,1),2)+1+40)<>6,"",DATE($D$4,6,1)-WEEKDAY(DATE($D$4,6,1),2)+1+40) | X39: =IF(MONTH(DATE($D$4,6,1)-WEEKDAY(DATE($D$4,6,1),2)+1+41)<>6,"",DATE($D$4,6,1)-WEEKDAY(DATE($D$4,6,1),2)+1+41)
B41: ="JULIO "&$D$4 | G41: =IF(COUNTIFS($B$62:$B$211,">="&DATE($D$4,7,1),$B$62:$B$211,"<="&EOMONTH(DATE($D$4,7,1),0),$V$62:$V$211,"<>4 · Cancelada")=1,"1 cita",COUNTIFS($B$62:$B$211,">="&DATE($D$4,7,1),$B$62:$B$211,"<="&EOMONTH(DATE($D$4,7,1),0),$V$62:$V$211,"<>4 · Cancelada")&" citas") | J41: ="AGOSTO "&$D$4 | O41: =IF(COUNTIFS($B$62:$B$211,">="&DATE($D$4,8,1),$B$62:$B$211,"<="&EOMONTH(DATE($D$4,8,1),0),$V$62:$V$211,"<>4 · Cancelada")=1,"1 cita",COUNTIFS($B$62:$B$211,">="&DATE($D$4,8,1),$B$62:$B$211,"<="&EOMONTH(DATE($D$4,8,1),0),$V$62:$V$211,"<>4 · Cancelada")&" citas") | R41: ="SEPTIEMBRE "&$D$4 | W41: =IF(COUNTIFS($B$62:$B$211,">="&DATE($D$4,9,1),$B$62:$B$211,"<="&EOMONTH(DATE($D$4,9,1),0),$V$62:$V$211,"<>4 · Cancelada")=1,"1 cita",COUNTIFS($B$62:$B$211,">="&DATE($D$4,9,1),$B$62:$B$211,"<="&EOMONTH(DATE($D$4,9,1),0),$V$62:$V$211,"<>4 · Cancelada")&" citas")
B42: L | C42: M | D42: X | E42: J | F42: V | G42: S | H42: D | J42: L | K42: M | L42: X | M42: J | N42: V | O42: S | P42: D | R42: L | S42: M | T42: X | U42: J | V42: V | W42: S | X42: D
B43: =IF(MONTH(DATE($D$4,7,1)-WEEKDAY(DATE($D$4,7,1),2)+1+0)<>7,"",DATE($D$4,7,1)-WEEKDAY(DATE($D$4,7,1),2)+1+0) | C43: =IF(MONTH(DATE($D$4,7,1)-WEEKDAY(DATE($D$4,7,1),2)+1+1)<>7,"",DATE($D$4,7,1)-WEEKDAY(DATE($D$4,7,1),2)+1+1) | D43: =IF(MONTH(DATE($D$4,7,1)-WEEKDAY(DATE($D$4,7,1),2)+1+2)<>7,"",DATE($D$4,7,1)-WEEKDAY(DATE($D$4,7,1),2)+1+2) | E43: =IF(MONTH(DATE($D$4,7,1)-WEEKDAY(DATE($D$4,7,1),2)+1+3)<>7,"",DATE($D$4,7,1)-WEEKDAY(DATE($D$4,7,1),2)+1+3) | F43: =IF(MONTH(DATE($D$4,7,1)-WEEKDAY(DATE($D$4,7,1),2)+1+4)<>7,"",DATE($D$4,7,1)-WEEKDAY(DATE($D$4,7,1),2)+1+4) | G43: =IF(MONTH(DATE($D$4,7,1)-WEEKDAY(DATE($D$4,7,1),2)+1+5)<>7,"",DATE($D$4,7,1)-WEEKDAY(DATE($D$4,7,1),2)+1+5) | H43: =IF(MONTH(DATE($D$4,7,1)-WEEKDAY(DATE($D$4,7,1),2)+1+6)<>7,"",DATE($D$4,7,1)-WEEKDAY(DATE($D$4,7,1),2)+1+6) | J43: =IF(MONTH(DATE($D$4,8,1)-WEEKDAY(DATE($D$4,8,1),2)+1+0)<>8,"",DATE($D$4,8,1)-WEEKDAY(DATE($D$4,8,1),2)+1+0) | K43: =IF(MONTH(DATE($D$4,8,1)-WEEKDAY(DATE($D$4,8,1),2)+1+1)<>8,"",DATE($D$4,8,1)-WEEKDAY(DATE($D$4,8,1),2)+1+1) | L43: =IF(MONTH(DATE($D$4,8,1)-WEEKDAY(DATE($D$4,8,1),2)+1+2)<>8,"",DATE($D$4,8,1)-WEEKDAY(DATE($D$4,8,1),2)+1+2) | M43: =IF(MONTH(DATE($D$4,8,1)-WEEKDAY(DATE($D$4,8,1),2)+1+3)<>8,"",DATE($D$4,8,1)-WEEKDAY(DATE($D$4,8,1),2)+1+3) | N43: =IF(MONTH(DATE($D$4,8,1)-WEEKDAY(DATE($D$4,8,1),2)+1+4)<>8,"",DATE($D$4,8,1)-WEEKDAY(DATE($D$4,8,1),2)+1+4) | O43: =IF(MONTH(DATE($D$4,8,1)-WEEKDAY(DATE($D$4,8,1),2)+1+5)<>8,"",DATE($D$4,8,1)-WEEKDAY(DATE($D$4,8,1),2)+1+5) | P43: =IF(MONTH(DATE($D$4,8,1)-WEEKDAY(DATE($D$4,8,1),2)+1+6)<>8,"",DATE($D$4,8,1)-WEEKDAY(DATE($D$4,8,1),2)+1+6) | R43: =IF(MONTH(DATE($D$4,9,1)-WEEKDAY(DATE($D$4,9,1),2)+1+0)<>9,"",DATE($D$4,9,1)-WEEKDAY(DATE($D$4,9,1),2)+1+0) | S43: =IF(MONTH(DATE($D$4,9,1)-WEEKDAY(DATE($D$4,9,1),2)+1+1)<>9,"",DATE($D$4,9,1)-WEEKDAY(DATE($D$4,9,1),2)+1+1) | T43: =IF(MONTH(DATE($D$4,9,1)-WEEKDAY(DATE($D$4,9,1),2)+1+2)<>9,"",DATE($D$4,9,1)-WEEKDAY(DATE($D$4,9,1),2)+1+2) | U43: =IF(MONTH(DATE($D$4,9,1)-WEEKDAY(DATE($D$4,9,1),2)+1+3)<>9,"",DATE($D$4,9,1)-WEEKDAY(DATE($D$4,9,1),2)+1+3) | V43: =IF(MONTH(DATE($D$4,9,1)-WEEKDAY(DATE($D$4,9,1),2)+1+4)<>9,"",DATE($D$4,9,1)-WEEKDAY(DATE($D$4,9,1),2)+1+4) | W43: =IF(MONTH(DATE($D$4,9,1)-WEEKDAY(DATE($D$4,9,1),2)+1+5)<>9,"",DATE($D$4,9,1)-WEEKDAY(DATE($D$4,9,1),2)+1+5) | X43: =IF(MONTH(DATE($D$4,9,1)-WEEKDAY(DATE($D$4,9,1),2)+1+6)<>9,"",DATE($D$4,9,1)-WEEKDAY(DATE($D$4,9,1),2)+1+6)
B44: =IF(MONTH(DATE($D$4,7,1)-WEEKDAY(DATE($D$4,7,1),2)+1+7)<>7,"",DATE($D$4,7,1)-WEEKDAY(DATE($D$4,7,1),2)+1+7) | C44: =IF(MONTH(DATE($D$4,7,1)-WEEKDAY(DATE($D$4,7,1),2)+1+8)<>7,"",DATE($D$4,7,1)-WEEKDAY(DATE($D$4,7,1),2)+1+8) | D44: =IF(MONTH(DATE($D$4,7,1)-WEEKDAY(DATE($D$4,7,1),2)+1+9)<>7,"",DATE($D$4,7,1)-WEEKDAY(DATE($D$4,7,1),2)+1+9) | E44: =IF(MONTH(DATE($D$4,7,1)-WEEKDAY(DATE($D$4,7,1),2)+1+10)<>7,"",DATE($D$4,7,1)-WEEKDAY(DATE($D$4,7,1),2)+1+10) | F44: =IF(MONTH(DATE($D$4,7,1)-WEEKDAY(DATE($D$4,7,1),2)+1+11)<>7,"",DATE($D$4,7,1)-WEEKDAY(DATE($D$4,7,1),2)+1+11) | G44: =IF(MONTH(DATE($D$4,7,1)-WEEKDAY(DATE($D$4,7,1),2)+1+12)<>7,"",DATE($D$4,7,1)-WEEKDAY(DATE($D$4,7,1),2)+1+12) | H44: =IF(MONTH(DATE($D$4,7,1)-WEEKDAY(DATE($D$4,7,1),2)+1+13)<>7,"",DATE($D$4,7,1)-WEEKDAY(DATE($D$4,7,1),2)+1+13) | J44: =IF(MONTH(DATE($D$4,8,1)-WEEKDAY(DATE($D$4,8,1),2)+1+7)<>8,"",DATE($D$4,8,1)-WEEKDAY(DATE($D$4,8,1),2)+1+7) | K44: =IF(MONTH(DATE($D$4,8,1)-WEEKDAY(DATE($D$4,8,1),2)+1+8)<>8,"",DATE($D$4,8,1)-WEEKDAY(DATE($D$4,8,1),2)+1+8) | L44: =IF(MONTH(DATE($D$4,8,1)-WEEKDAY(DATE($D$4,8,1),2)+1+9)<>8,"",DATE($D$4,8,1)-WEEKDAY(DATE($D$4,8,1),2)+1+9) | M44: =IF(MONTH(DATE($D$4,8,1)-WEEKDAY(DATE($D$4,8,1),2)+1+10)<>8,"",DATE($D$4,8,1)-WEEKDAY(DATE($D$4,8,1),2)+1+10) | N44: =IF(MONTH(DATE($D$4,8,1)-WEEKDAY(DATE($D$4,8,1),2)+1+11)<>8,"",DATE($D$4,8,1)-WEEKDAY(DATE($D$4,8,1),2)+1+11) | O44: =IF(MONTH(DATE($D$4,8,1)-WEEKDAY(DATE($D$4,8,1),2)+1+12)<>8,"",DATE($D$4,8,1)-WEEKDAY(DATE($D$4,8,1),2)+1+12) | P44: =IF(MONTH(DATE($D$4,8,1)-WEEKDAY(DATE($D$4,8,1),2)+1+13)<>8,"",DATE($D$4,8,1)-WEEKDAY(DATE($D$4,8,1),2)+1+13) | R44: =IF(MONTH(DATE($D$4,9,1)-WEEKDAY(DATE($D$4,9,1),2)+1+7)<>9,"",DATE($D$4,9,1)-WEEKDAY(DATE($D$4,9,1),2)+1+7) | S44: =IF(MONTH(DATE($D$4,9,1)-WEEKDAY(DATE($D$4,9,1),2)+1+8)<>9,"",DATE($D$4,9,1)-WEEKDAY(DATE($D$4,9,1),2)+1+8) | T44: =IF(MONTH(DATE($D$4,9,1)-WEEKDAY(DATE($D$4,9,1),2)+1+9)<>9,"",DATE($D$4,9,1)-WEEKDAY(DATE($D$4,9,1),2)+1+9) | U44: =IF(MONTH(DATE($D$4,9,1)-WEEKDAY(DATE($D$4,9,1),2)+1+10)<>9,"",DATE($D$4,9,1)-WEEKDAY(DATE($D$4,9,1),2)+1+10) | V44: =IF(MONTH(DATE($D$4,9,1)-WEEKDAY(DATE($D$4,9,1),2)+1+11)<>9,"",DATE($D$4,9,1)-WEEKDAY(DATE($D$4,9,1),2)+1+11) | W44: =IF(MONTH(DATE($D$4,9,1)-WEEKDAY(DATE($D$4,9,1),2)+1+12)<>9,"",DATE($D$4,9,1)-WEEKDAY(DATE($D$4,9,1),2)+1+12) | X44: =IF(MONTH(DATE($D$4,9,1)-WEEKDAY(DATE($D$4,9,1),2)+1+13)<>9,"",DATE($D$4,9,1)-WEEKDAY(DATE($D$4,9,1),2)+1+13)
B45: =IF(MONTH(DATE($D$4,7,1)-WEEKDAY(DATE($D$4,7,1),2)+1+14)<>7,"",DATE($D$4,7,1)-WEEKDAY(DATE($D$4,7,1),2)+1+14) | C45: =IF(MONTH(DATE($D$4,7,1)-WEEKDAY(DATE($D$4,7,1),2)+1+15)<>7,"",DATE($D$4,7,1)-WEEKDAY(DATE($D$4,7,1),2)+1+15) | D45: =IF(MONTH(DATE($D$4,7,1)-WEEKDAY(DATE($D$4,7,1),2)+1+16)<>7,"",DATE($D$4,7,1)-WEEKDAY(DATE($D$4,7,1),2)+1+16) | E45: =IF(MONTH(DATE($D$4,7,1)-WEEKDAY(DATE($D$4,7,1),2)+1+17)<>7,"",DATE($D$4,7,1)-WEEKDAY(DATE($D$4,7,1),2)+1+17) | F45: =IF(MONTH(DATE($D$4,7,1)-WEEKDAY(DATE($D$4,7,1),2)+1+18)<>7,"",DATE($D$4,7,1)-WEEKDAY(DATE($D$4,7,1),2)+1+18) | G45: =IF(MONTH(DATE($D$4,7,1)-WEEKDAY(DATE($D$4,7,1),2)+1+19)<>7,"",DATE($D$4,7,1)-WEEKDAY(DATE($D$4,7,1),2)+1+19) | H45: =IF(MONTH(DATE($D$4,7,1)-WEEKDAY(DATE($D$4,7,1),2)+1+20)<>7,"",DATE($D$4,7,1)-WEEKDAY(DATE($D$4,7,1),2)+1+20) | J45: =IF(MONTH(DATE($D$4,8,1)-WEEKDAY(DATE($D$4,8,1),2)+1+14)<>8,"",DATE($D$4,8,1)-WEEKDAY(DATE($D$4,8,1),2)+1+14) | K45: =IF(MONTH(DATE($D$4,8,1)-WEEKDAY(DATE($D$4,8,1),2)+1+15)<>8,"",DATE($D$4,8,1)-WEEKDAY(DATE($D$4,8,1),2)+1+15) | L45: =IF(MONTH(DATE($D$4,8,1)-WEEKDAY(DATE($D$4,8,1),2)+1+16)<>8,"",DATE($D$4,8,1)-WEEKDAY(DATE($D$4,8,1),2)+1+16) | M45: =IF(MONTH(DATE($D$4,8,1)-WEEKDAY(DATE($D$4,8,1),2)+1+17)<>8,"",DATE($D$4,8,1)-WEEKDAY(DATE($D$4,8,1),2)+1+17) | N45: =IF(MONTH(DATE($D$4,8,1)-WEEKDAY(DATE($D$4,8,1),2)+1+18)<>8,"",DATE($D$4,8,1)-WEEKDAY(DATE($D$4,8,1),2)+1+18) | O45: =IF(MONTH(DATE($D$4,8,1)-WEEKDAY(DATE($D$4,8,1),2)+1+19)<>8,"",DATE($D$4,8,1)-WEEKDAY(DATE($D$4,8,1),2)+1+19) | P45: =IF(MONTH(DATE($D$4,8,1)-WEEKDAY(DATE($D$4,8,1),2)+1+20)<>8,"",DATE($D$4,8,1)-WEEKDAY(DATE($D$4,8,1),2)+1+20) | R45: =IF(MONTH(DATE($D$4,9,1)-WEEKDAY(DATE($D$4,9,1),2)+1+14)<>9,"",DATE($D$4,9,1)-WEEKDAY(DATE($D$4,9,1),2)+1+14) | S45: =IF(MONTH(DATE($D$4,9,1)-WEEKDAY(DATE($D$4,9,1),2)+1+15)<>9,"",DATE($D$4,9,1)-WEEKDAY(DATE($D$4,9,1),2)+1+15) | T45: =IF(MONTH(DATE($D$4,9,1)-WEEKDAY(DATE($D$4,9,1),2)+1+16)<>9,"",DATE($D$4,9,1)-WEEKDAY(DATE($D$4,9,1),2)+1+16) | U45: =IF(MONTH(DATE($D$4,9,1)-WEEKDAY(DATE($D$4,9,1),2)+1+17)<>9,"",DATE($D$4,9,1)-WEEKDAY(DATE($D$4,9,1),2)+1+17) | V45: =IF(MONTH(DATE($D$4,9,1)-WEEKDAY(DATE($D$4,9,1),2)+1+18)<>9,"",DATE($D$4,9,1)-WEEKDAY(DATE($D$4,9,1),2)+1+18) | W45: =IF(MONTH(DATE($D$4,9,1)-WEEKDAY(DATE($D$4,9,1),2)+1+19)<>9,"",DATE($D$4,9,1)-WEEKDAY(DATE($D$4,9,1),2)+1+19) | X45: =IF(MONTH(DATE($D$4,9,1)-WEEKDAY(DATE($D$4,9,1),2)+1+20)<>9,"",DATE($D$4,9,1)-WEEKDAY(DATE($D$4,9,1),2)+1+20)
B46: =IF(MONTH(DATE($D$4,7,1)-WEEKDAY(DATE($D$4,7,1),2)+1+21)<>7,"",DATE($D$4,7,1)-WEEKDAY(DATE($D$4,7,1),2)+1+21) | C46: =IF(MONTH(DATE($D$4,7,1)-WEEKDAY(DATE($D$4,7,1),2)+1+22)<>7,"",DATE($D$4,7,1)-WEEKDAY(DATE($D$4,7,1),2)+1+22) | D46: =IF(MONTH(DATE($D$4,7,1)-WEEKDAY(DATE($D$4,7,1),2)+1+23)<>7,"",DATE($D$4,7,1)-WEEKDAY(DATE($D$4,7,1),2)+1+23) | E46: =IF(MONTH(DATE($D$4,7,1)-WEEKDAY(DATE($D$4,7,1),2)+1+24)<>7,"",DATE($D$4,7,1)-WEEKDAY(DATE($D$4,7,1),2)+1+24) | F46: =IF(MONTH(DATE($D$4,7,1)-WEEKDAY(DATE($D$4,7,1),2)+1+25)<>7,"",DATE($D$4,7,1)-WEEKDAY(DATE($D$4,7,1),2)+1+25) | G46: =IF(MONTH(DATE($D$4,7,1)-WEEKDAY(DATE($D$4,7,1),2)+1+26)<>7,"",DATE($D$4,7,1)-WEEKDAY(DATE($D$4,7,1),2)+1+26) | H46: =IF(MONTH(DATE($D$4,7,1)-WEEKDAY(DATE($D$4,7,1),2)+1+27)<>7,"",DATE($D$4,7,1)-WEEKDAY(DATE($D$4,7,1),2)+1+27) | J46: =IF(MONTH(DATE($D$4,8,1)-WEEKDAY(DATE($D$4,8,1),2)+1+21)<>8,"",DATE($D$4,8,1)-WEEKDAY(DATE($D$4,8,1),2)+1+21) | K46: =IF(MONTH(DATE($D$4,8,1)-WEEKDAY(DATE($D$4,8,1),2)+1+22)<>8,"",DATE($D$4,8,1)-WEEKDAY(DATE($D$4,8,1),2)+1+22) | L46: =IF(MONTH(DATE($D$4,8,1)-WEEKDAY(DATE($D$4,8,1),2)+1+23)<>8,"",DATE($D$4,8,1)-WEEKDAY(DATE($D$4,8,1),2)+1+23) | M46: =IF(MONTH(DATE($D$4,8,1)-WEEKDAY(DATE($D$4,8,1),2)+1+24)<>8,"",DATE($D$4,8,1)-WEEKDAY(DATE($D$4,8,1),2)+1+24) | N46: =IF(MONTH(DATE($D$4,8,1)-WEEKDAY(DATE($D$4,8,1),2)+1+25)<>8,"",DATE($D$4,8,1)-WEEKDAY(DATE($D$4,8,1),2)+1+25) | O46: =IF(MONTH(DATE($D$4,8,1)-WEEKDAY(DATE($D$4,8,1),2)+1+26)<>8,"",DATE($D$4,8,1)-WEEKDAY(DATE($D$4,8,1),2)+1+26) | P46: =IF(MONTH(DATE($D$4,8,1)-WEEKDAY(DATE($D$4,8,1),2)+1+27)<>8,"",DATE($D$4,8,1)-WEEKDAY(DATE($D$4,8,1),2)+1+27) | R46: =IF(MONTH(DATE($D$4,9,1)-WEEKDAY(DATE($D$4,9,1),2)+1+21)<>9,"",DATE($D$4,9,1)-WEEKDAY(DATE($D$4,9,1),2)+1+21) | S46: =IF(MONTH(DATE($D$4,9,1)-WEEKDAY(DATE($D$4,9,1),2)+1+22)<>9,"",DATE($D$4,9,1)-WEEKDAY(DATE($D$4,9,1),2)+1+22) | T46: =IF(MONTH(DATE($D$4,9,1)-WEEKDAY(DATE($D$4,9,1),2)+1+23)<>9,"",DATE($D$4,9,1)-WEEKDAY(DATE($D$4,9,1),2)+1+23) | U46: =IF(MONTH(DATE($D$4,9,1)-WEEKDAY(DATE($D$4,9,1),2)+1+24)<>9,"",DATE($D$4,9,1)-WEEKDAY(DATE($D$4,9,1),2)+1+24) | V46: =IF(MONTH(DATE($D$4,9,1)-WEEKDAY(DATE($D$4,9,1),2)+1+25)<>9,"",DATE($D$4,9,1)-WEEKDAY(DATE($D$4,9,1),2)+1+25) | W46: =IF(MONTH(DATE($D$4,9,1)-WEEKDAY(DATE($D$4,9,1),2)+1+26)<>9,"",DATE($D$4,9,1)-WEEKDAY(DATE($D$4,9,1),2)+1+26) | X46: =IF(MONTH(DATE($D$4,9,1)-WEEKDAY(DATE($D$4,9,1),2)+1+27)<>9,"",DATE($D$4,9,1)-WEEKDAY(DATE($D$4,9,1),2)+1+27)
B47: =IF(MONTH(DATE($D$4,7,1)-WEEKDAY(DATE($D$4,7,1),2)+1+28)<>7,"",DATE($D$4,7,1)-WEEKDAY(DATE($D$4,7,1),2)+1+28) | C47: =IF(MONTH(DATE($D$4,7,1)-WEEKDAY(DATE($D$4,7,1),2)+1+29)<>7,"",DATE($D$4,7,1)-WEEKDAY(DATE($D$4,7,1),2)+1+29) | D47: =IF(MONTH(DATE($D$4,7,1)-WEEKDAY(DATE($D$4,7,1),2)+1+30)<>7,"",DATE($D$4,7,1)-WEEKDAY(DATE($D$4,7,1),2)+1+30) | E47: =IF(MONTH(DATE($D$4,7,1)-WEEKDAY(DATE($D$4,7,1),2)+1+31)<>7,"",DATE($D$4,7,1)-WEEKDAY(DATE($D$4,7,1),2)+1+31) | F47: =IF(MONTH(DATE($D$4,7,1)-WEEKDAY(DATE($D$4,7,1),2)+1+32)<>7,"",DATE($D$4,7,1)-WEEKDAY(DATE($D$4,7,1),2)+1+32) | G47: =IF(MONTH(DATE($D$4,7,1)-WEEKDAY(DATE($D$4,7,1),2)+1+33)<>7,"",DATE($D$4,7,1)-WEEKDAY(DATE($D$4,7,1),2)+1+33) | H47: =IF(MONTH(DATE($D$4,7,1)-WEEKDAY(DATE($D$4,7,1),2)+1+34)<>7,"",DATE($D$4,7,1)-WEEKDAY(DATE($D$4,7,1),2)+1+34) | J47: =IF(MONTH(DATE($D$4,8,1)-WEEKDAY(DATE($D$4,8,1),2)+1+28)<>8,"",DATE($D$4,8,1)-WEEKDAY(DATE($D$4,8,1),2)+1+28) | K47: =IF(MONTH(DATE($D$4,8,1)-WEEKDAY(DATE($D$4,8,1),2)+1+29)<>8,"",DATE($D$4,8,1)-WEEKDAY(DATE($D$4,8,1),2)+1+29) | L47: =IF(MONTH(DATE($D$4,8,1)-WEEKDAY(DATE($D$4,8,1),2)+1+30)<>8,"",DATE($D$4,8,1)-WEEKDAY(DATE($D$4,8,1),2)+1+30) | M47: =IF(MONTH(DATE($D$4,8,1)-WEEKDAY(DATE($D$4,8,1),2)+1+31)<>8,"",DATE($D$4,8,1)-WEEKDAY(DATE($D$4,8,1),2)+1+31) | N47: =IF(MONTH(DATE($D$4,8,1)-WEEKDAY(DATE($D$4,8,1),2)+1+32)<>8,"",DATE($D$4,8,1)-WEEKDAY(DATE($D$4,8,1),2)+1+32) | O47: =IF(MONTH(DATE($D$4,8,1)-WEEKDAY(DATE($D$4,8,1),2)+1+33)<>8,"",DATE($D$4,8,1)-WEEKDAY(DATE($D$4,8,1),2)+1+33) | P47: =IF(MONTH(DATE($D$4,8,1)-WEEKDAY(DATE($D$4,8,1),2)+1+34)<>8,"",DATE($D$4,8,1)-WEEKDAY(DATE($D$4,8,1),2)+1+34) | R47: =IF(MONTH(DATE($D$4,9,1)-WEEKDAY(DATE($D$4,9,1),2)+1+28)<>9,"",DATE($D$4,9,1)-WEEKDAY(DATE($D$4,9,1),2)+1+28) | S47: =IF(MONTH(DATE($D$4,9,1)-WEEKDAY(DATE($D$4,9,1),2)+1+29)<>9,"",DATE($D$4,9,1)-WEEKDAY(DATE($D$4,9,1),2)+1+29) | T47: =IF(MONTH(DATE($D$4,9,1)-WEEKDAY(DATE($D$4,9,1),2)+1+30)<>9,"",DATE($D$4,9,1)-WEEKDAY(DATE($D$4,9,1),2)+1+30) | U47: =IF(MONTH(DATE($D$4,9,1)-WEEKDAY(DATE($D$4,9,1),2)+1+31)<>9,"",DATE($D$4,9,1)-WEEKDAY(DATE($D$4,9,1),2)+1+31) | V47: =IF(MONTH(DATE($D$4,9,1)-WEEKDAY(DATE($D$4,9,1),2)+1+32)<>9,"",DATE($D$4,9,1)-WEEKDAY(DATE($D$4,9,1),2)+1+32) | W47: =IF(MONTH(DATE($D$4,9,1)-WEEKDAY(DATE($D$4,9,1),2)+1+33)<>9,"",DATE($D$4,9,1)-WEEKDAY(DATE($D$4,9,1),2)+1+33) | X47: =IF(MONTH(DATE($D$4,9,1)-WEEKDAY(DATE($D$4,9,1),2)+1+34)<>9,"",DATE($D$4,9,1)-WEEKDAY(DATE($D$4,9,1),2)+1+34)
B48: =IF(MONTH(DATE($D$4,7,1)-WEEKDAY(DATE($D$4,7,1),2)+1+35)<>7,"",DATE($D$4,7,1)-WEEKDAY(DATE($D$4,7,1),2)+1+35) | C48: =IF(MONTH(DATE($D$4,7,1)-WEEKDAY(DATE($D$4,7,1),2)+1+36)<>7,"",DATE($D$4,7,1)-WEEKDAY(DATE($D$4,7,1),2)+1+36) | D48: =IF(MONTH(DATE($D$4,7,1)-WEEKDAY(DATE($D$4,7,1),2)+1+37)<>7,"",DATE($D$4,7,1)-WEEKDAY(DATE($D$4,7,1),2)+1+37) | E48: =IF(MONTH(DATE($D$4,7,1)-WEEKDAY(DATE($D$4,7,1),2)+1+38)<>7,"",DATE($D$4,7,1)-WEEKDAY(DATE($D$4,7,1),2)+1+38) | F48: =IF(MONTH(DATE($D$4,7,1)-WEEKDAY(DATE($D$4,7,1),2)+1+39)<>7,"",DATE($D$4,7,1)-WEEKDAY(DATE($D$4,7,1),2)+1+39) | G48: =IF(MONTH(DATE($D$4,7,1)-WEEKDAY(DATE($D$4,7,1),2)+1+40)<>7,"",DATE($D$4,7,1)-WEEKDAY(DATE($D$4,7,1),2)+1+40) | H48: =IF(MONTH(DATE($D$4,7,1)-WEEKDAY(DATE($D$4,7,1),2)+1+41)<>7,"",DATE($D$4,7,1)-WEEKDAY(DATE($D$4,7,1),2)+1+41) | J48: =IF(MONTH(DATE($D$4,8,1)-WEEKDAY(DATE($D$4,8,1),2)+1+35)<>8,"",DATE($D$4,8,1)-WEEKDAY(DATE($D$4,8,1),2)+1+35) | K48: =IF(MONTH(DATE($D$4,8,1)-WEEKDAY(DATE($D$4,8,1),2)+1+36)<>8,"",DATE($D$4,8,1)-WEEKDAY(DATE($D$4,8,1),2)+1+36) | L48: =IF(MONTH(DATE($D$4,8,1)-WEEKDAY(DATE($D$4,8,1),2)+1+37)<>8,"",DATE($D$4,8,1)-WEEKDAY(DATE($D$4,8,1),2)+1+37) | M48: =IF(MONTH(DATE($D$4,8,1)-WEEKDAY(DATE($D$4,8,1),2)+1+38)<>8,"",DATE($D$4,8,1)-WEEKDAY(DATE($D$4,8,1),2)+1+38) | N48: =IF(MONTH(DATE($D$4,8,1)-WEEKDAY(DATE($D$4,8,1),2)+1+39)<>8,"",DATE($D$4,8,1)-WEEKDAY(DATE($D$4,8,1),2)+1+39) | O48: =IF(MONTH(DATE($D$4,8,1)-WEEKDAY(DATE($D$4,8,1),2)+1+40)<>8,"",DATE($D$4,8,1)-WEEKDAY(DATE($D$4,8,1),2)+1+40) | P48: =IF(MONTH(DATE($D$4,8,1)-WEEKDAY(DATE($D$4,8,1),2)+1+41)<>8,"",DATE($D$4,8,1)-WEEKDAY(DATE($D$4,8,1),2)+1+41) | R48: =IF(MONTH(DATE($D$4,9,1)-WEEKDAY(DATE($D$4,9,1),2)+1+35)<>9,"",DATE($D$4,9,1)-WEEKDAY(DATE($D$4,9,1),2)+1+35) | S48: =IF(MONTH(DATE($D$4,9,1)-WEEKDAY(DATE($D$4,9,1),2)+1+36)<>9,"",DATE($D$4,9,1)-WEEKDAY(DATE($D$4,9,1),2)+1+36) | T48: =IF(MONTH(DATE($D$4,9,1)-WEEKDAY(DATE($D$4,9,1),2)+1+37)<>9,"",DATE($D$4,9,1)-WEEKDAY(DATE($D$4,9,1),2)+1+37) | U48: =IF(MONTH(DATE($D$4,9,1)-WEEKDAY(DATE($D$4,9,1),2)+1+38)<>9,"",DATE($D$4,9,1)-WEEKDAY(DATE($D$4,9,1),2)+1+38) | V48: =IF(MONTH(DATE($D$4,9,1)-WEEKDAY(DATE($D$4,9,1),2)+1+39)<>9,"",DATE($D$4,9,1)-WEEKDAY(DATE($D$4,9,1),2)+1+39) | W48: =IF(MONTH(DATE($D$4,9,1)-WEEKDAY(DATE($D$4,9,1),2)+1+40)<>9,"",DATE($D$4,9,1)-WEEKDAY(DATE($D$4,9,1),2)+1+40) | X48: =IF(MONTH(DATE($D$4,9,1)-WEEKDAY(DATE($D$4,9,1),2)+1+41)<>9,"",DATE($D$4,9,1)-WEEKDAY(DATE($D$4,9,1),2)+1+41)
B50: ="OCTUBRE "&$D$4 | G50: =IF(COUNTIFS($B$62:$B$211,">="&DATE($D$4,10,1),$B$62:$B$211,"<="&EOMONTH(DATE($D$4,10,1),0),$V$62:$V$211,"<>4 · Cancelada")=1,"1 cita",COUNTIFS($B$62:$B$211,">="&DATE($D$4,10,1),$B$62:$B$211,"<="&EOMONTH(DATE($D$4,10,1),0),$V$62:$V$211,"<>4 · Cancelada")&" citas") | J50: ="NOVIEMBRE "&$D$4 | O50: =IF(COUNTIFS($B$62:$B$211,">="&DATE($D$4,11,1),$B$62:$B$211,"<="&EOMONTH(DATE($D$4,11,1),0),$V$62:$V$211,"<>4 · Cancelada")=1,"1 cita",COUNTIFS($B$62:$B$211,">="&DATE($D$4,11,1),$B$62:$B$211,"<="&EOMONTH(DATE($D$4,11,1),0),$V$62:$V$211,"<>4 · Cancelada")&" citas") | R50: ="DICIEMBRE "&$D$4 | W50: =IF(COUNTIFS($B$62:$B$211,">="&DATE($D$4,12,1),$B$62:$B$211,"<="&EOMONTH(DATE($D$4,12,1),0),$V$62:$V$211,"<>4 · Cancelada")=1,"1 cita",COUNTIFS($B$62:$B$211,">="&DATE($D$4,12,1),$B$62:$B$211,"<="&EOMONTH(DATE($D$4,12,1),0),$V$62:$V$211,"<>4 · Cancelada")&" citas")
B51: L | C51: M | D51: X | E51: J | F51: V | G51: S | H51: D | J51: L | K51: M | L51: X | M51: J | N51: V | O51: S | P51: D | R51: L | S51: M | T51: X | U51: J | V51: V | W51: S | X51: D
B52: =IF(MONTH(DATE($D$4,10,1)-WEEKDAY(DATE($D$4,10,1),2)+1+0)<>10,"",DATE($D$4,10,1)-WEEKDAY(DATE($D$4,10,1),2)+1+0) | C52: =IF(MONTH(DATE($D$4,10,1)-WEEKDAY(DATE($D$4,10,1),2)+1+1)<>10,"",DATE($D$4,10,1)-WEEKDAY(DATE($D$4,10,1),2)+1+1) | D52: =IF(MONTH(DATE($D$4,10,1)-WEEKDAY(DATE($D$4,10,1),2)+1+2)<>10,"",DATE($D$4,10,1)-WEEKDAY(DATE($D$4,10,1),2)+1+2) | E52: =IF(MONTH(DATE($D$4,10,1)-WEEKDAY(DATE($D$4,10,1),2)+1+3)<>10,"",DATE($D$4,10,1)-WEEKDAY(DATE($D$4,10,1),2)+1+3) | F52: =IF(MONTH(DATE($D$4,10,1)-WEEKDAY(DATE($D$4,10,1),2)+1+4)<>10,"",DATE($D$4,10,1)-WEEKDAY(DATE($D$4,10,1),2)+1+4) | G52: =IF(MONTH(DATE($D$4,10,1)-WEEKDAY(DATE($D$4,10,1),2)+1+5)<>10,"",DATE($D$4,10,1)-WEEKDAY(DATE($D$4,10,1),2)+1+5) | H52: =IF(MONTH(DATE($D$4,10,1)-WEEKDAY(DATE($D$4,10,1),2)+1+6)<>10,"",DATE($D$4,10,1)-WEEKDAY(DATE($D$4,10,1),2)+1+6) | J52: =IF(MONTH(DATE($D$4,11,1)-WEEKDAY(DATE($D$4,11,1),2)+1+0)<>11,"",DATE($D$4,11,1)-WEEKDAY(DATE($D$4,11,1),2)+1+0) | K52: =IF(MONTH(DATE($D$4,11,1)-WEEKDAY(DATE($D$4,11,1),2)+1+1)<>11,"",DATE($D$4,11,1)-WEEKDAY(DATE($D$4,11,1),2)+1+1) | L52: =IF(MONTH(DATE($D$4,11,1)-WEEKDAY(DATE($D$4,11,1),2)+1+2)<>11,"",DATE($D$4,11,1)-WEEKDAY(DATE($D$4,11,1),2)+1+2) | M52: =IF(MONTH(DATE($D$4,11,1)-WEEKDAY(DATE($D$4,11,1),2)+1+3)<>11,"",DATE($D$4,11,1)-WEEKDAY(DATE($D$4,11,1),2)+1+3) | N52: =IF(MONTH(DATE($D$4,11,1)-WEEKDAY(DATE($D$4,11,1),2)+1+4)<>11,"",DATE($D$4,11,1)-WEEKDAY(DATE($D$4,11,1),2)+1+4) | O52: =IF(MONTH(DATE($D$4,11,1)-WEEKDAY(DATE($D$4,11,1),2)+1+5)<>11,"",DATE($D$4,11,1)-WEEKDAY(DATE($D$4,11,1),2)+1+5) | P52: =IF(MONTH(DATE($D$4,11,1)-WEEKDAY(DATE($D$4,11,1),2)+1+6)<>11,"",DATE($D$4,11,1)-WEEKDAY(DATE($D$4,11,1),2)+1+6) | R52: =IF(MONTH(DATE($D$4,12,1)-WEEKDAY(DATE($D$4,12,1),2)+1+0)<>12,"",DATE($D$4,12,1)-WEEKDAY(DATE($D$4,12,1),2)+1+0) | S52: =IF(MONTH(DATE($D$4,12,1)-WEEKDAY(DATE($D$4,12,1),2)+1+1)<>12,"",DATE($D$4,12,1)-WEEKDAY(DATE($D$4,12,1),2)+1+1) | T52: =IF(MONTH(DATE($D$4,12,1)-WEEKDAY(DATE($D$4,12,1),2)+1+2)<>12,"",DATE($D$4,12,1)-WEEKDAY(DATE($D$4,12,1),2)+1+2) | U52: =IF(MONTH(DATE($D$4,12,1)-WEEKDAY(DATE($D$4,12,1),2)+1+3)<>12,"",DATE($D$4,12,1)-WEEKDAY(DATE($D$4,12,1),2)+1+3) | V52: =IF(MONTH(DATE($D$4,12,1)-WEEKDAY(DATE($D$4,12,1),2)+1+4)<>12,"",DATE($D$4,12,1)-WEEKDAY(DATE($D$4,12,1),2)+1+4) | W52: =IF(MONTH(DATE($D$4,12,1)-WEEKDAY(DATE($D$4,12,1),2)+1+5)<>12,"",DATE($D$4,12,1)-WEEKDAY(DATE($D$4,12,1),2)+1+5) | X52: =IF(MONTH(DATE($D$4,12,1)-WEEKDAY(DATE($D$4,12,1),2)+1+6)<>12,"",DATE($D$4,12,1)-WEEKDAY(DATE($D$4,12,1),2)+1+6)
B53: =IF(MONTH(DATE($D$4,10,1)-WEEKDAY(DATE($D$4,10,1),2)+1+7)<>10,"",DATE($D$4,10,1)-WEEKDAY(DATE($D$4,10,1),2)+1+7) | C53: =IF(MONTH(DATE($D$4,10,1)-WEEKDAY(DATE($D$4,10,1),2)+1+8)<>10,"",DATE($D$4,10,1)-WEEKDAY(DATE($D$4,10,1),2)+1+8) | D53: =IF(MONTH(DATE($D$4,10,1)-WEEKDAY(DATE($D$4,10,1),2)+1+9)<>10,"",DATE($D$4,10,1)-WEEKDAY(DATE($D$4,10,1),2)+1+9) | E53: =IF(MONTH(DATE($D$4,10,1)-WEEKDAY(DATE($D$4,10,1),2)+1+10)<>10,"",DATE($D$4,10,1)-WEEKDAY(DATE($D$4,10,1),2)+1+10) | F53: =IF(MONTH(DATE($D$4,10,1)-WEEKDAY(DATE($D$4,10,1),2)+1+11)<>10,"",DATE($D$4,10,1)-WEEKDAY(DATE($D$4,10,1),2)+1+11) | G53: =IF(MONTH(DATE($D$4,10,1)-WEEKDAY(DATE($D$4,10,1),2)+1+12)<>10,"",DATE($D$4,10,1)-WEEKDAY(DATE($D$4,10,1),2)+1+12) | H53: =IF(MONTH(DATE($D$4,10,1)-WEEKDAY(DATE($D$4,10,1),2)+1+13)<>10,"",DATE($D$4,10,1)-WEEKDAY(DATE($D$4,10,1),2)+1+13) | J53: =IF(MONTH(DATE($D$4,11,1)-WEEKDAY(DATE($D$4,11,1),2)+1+7)<>11,"",DATE($D$4,11,1)-WEEKDAY(DATE($D$4,11,1),2)+1+7) | K53: =IF(MONTH(DATE($D$4,11,1)-WEEKDAY(DATE($D$4,11,1),2)+1+8)<>11,"",DATE($D$4,11,1)-WEEKDAY(DATE($D$4,11,1),2)+1+8) | L53: =IF(MONTH(DATE($D$4,11,1)-WEEKDAY(DATE($D$4,11,1),2)+1+9)<>11,"",DATE($D$4,11,1)-WEEKDAY(DATE($D$4,11,1),2)+1+9) | M53: =IF(MONTH(DATE($D$4,11,1)-WEEKDAY(DATE($D$4,11,1),2)+1+10)<>11,"",DATE($D$4,11,1)-WEEKDAY(DATE($D$4,11,1),2)+1+10) | N53: =IF(MONTH(DATE($D$4,11,1)-WEEKDAY(DATE($D$4,11,1),2)+1+11)<>11,"",DATE($D$4,11,1)-WEEKDAY(DATE($D$4,11,1),2)+1+11) | O53: =IF(MONTH(DATE($D$4,11,1)-WEEKDAY(DATE($D$4,11,1),2)+1+12)<>11,"",DATE($D$4,11,1)-WEEKDAY(DATE($D$4,11,1),2)+1+12) | P53: =IF(MONTH(DATE($D$4,11,1)-WEEKDAY(DATE($D$4,11,1),2)+1+13)<>11,"",DATE($D$4,11,1)-WEEKDAY(DATE($D$4,11,1),2)+1+13) | R53: =IF(MONTH(DATE($D$4,12,1)-WEEKDAY(DATE($D$4,12,1),2)+1+7)<>12,"",DATE($D$4,12,1)-WEEKDAY(DATE($D$4,12,1),2)+1+7) | S53: =IF(MONTH(DATE($D$4,12,1)-WEEKDAY(DATE($D$4,12,1),2)+1+8)<>12,"",DATE($D$4,12,1)-WEEKDAY(DATE($D$4,12,1),2)+1+8) | T53: =IF(MONTH(DATE($D$4,12,1)-WEEKDAY(DATE($D$4,12,1),2)+1+9)<>12,"",DATE($D$4,12,1)-WEEKDAY(DATE($D$4,12,1),2)+1+9) | U53: =IF(MONTH(DATE($D$4,12,1)-WEEKDAY(DATE($D$4,12,1),2)+1+10)<>12,"",DATE($D$4,12,1)-WEEKDAY(DATE($D$4,12,1),2)+1+10) | V53: =IF(MONTH(DATE($D$4,12,1)-WEEKDAY(DATE($D$4,12,1),2)+1+11)<>12,"",DATE($D$4,12,1)-WEEKDAY(DATE($D$4,12,1),2)+1+11) | W53: =IF(MONTH(DATE($D$4,12,1)-WEEKDAY(DATE($D$4,12,1),2)+1+12)<>12,"",DATE($D$4,12,1)-WEEKDAY(DATE($D$4,12,1),2)+1+12) | X53: =IF(MONTH(DATE($D$4,12,1)-WEEKDAY(DATE($D$4,12,1),2)+1+13)<>12,"",DATE($D$4,12,1)-WEEKDAY(DATE($D$4,12,1),2)+1+13)
B54: =IF(MONTH(DATE($D$4,10,1)-WEEKDAY(DATE($D$4,10,1),2)+1+14)<>10,"",DATE($D$4,10,1)-WEEKDAY(DATE($D$4,10,1),2)+1+14) | C54: =IF(MONTH(DATE($D$4,10,1)-WEEKDAY(DATE($D$4,10,1),2)+1+15)<>10,"",DATE($D$4,10,1)-WEEKDAY(DATE($D$4,10,1),2)+1+15) | D54: =IF(MONTH(DATE($D$4,10,1)-WEEKDAY(DATE($D$4,10,1),2)+1+16)<>10,"",DATE($D$4,10,1)-WEEKDAY(DATE($D$4,10,1),2)+1+16) | E54: =IF(MONTH(DATE($D$4,10,1)-WEEKDAY(DATE($D$4,10,1),2)+1+17)<>10,"",DATE($D$4,10,1)-WEEKDAY(DATE($D$4,10,1),2)+1+17) | F54: =IF(MONTH(DATE($D$4,10,1)-WEEKDAY(DATE($D$4,10,1),2)+1+18)<>10,"",DATE($D$4,10,1)-WEEKDAY(DATE($D$4,10,1),2)+1+18) | G54: =IF(MONTH(DATE($D$4,10,1)-WEEKDAY(DATE($D$4,10,1),2)+1+19)<>10,"",DATE($D$4,10,1)-WEEKDAY(DATE($D$4,10,1),2)+1+19) | H54: =IF(MONTH(DATE($D$4,10,1)-WEEKDAY(DATE($D$4,10,1),2)+1+20)<>10,"",DATE($D$4,10,1)-WEEKDAY(DATE($D$4,10,1),2)+1+20) | J54: =IF(MONTH(DATE($D$4,11,1)-WEEKDAY(DATE($D$4,11,1),2)+1+14)<>11,"",DATE($D$4,11,1)-WEEKDAY(DATE($D$4,11,1),2)+1+14) | K54: =IF(MONTH(DATE($D$4,11,1)-WEEKDAY(DATE($D$4,11,1),2)+1+15)<>11,"",DATE($D$4,11,1)-WEEKDAY(DATE($D$4,11,1),2)+1+15) | L54: =IF(MONTH(DATE($D$4,11,1)-WEEKDAY(DATE($D$4,11,1),2)+1+16)<>11,"",DATE($D$4,11,1)-WEEKDAY(DATE($D$4,11,1),2)+1+16) | M54: =IF(MONTH(DATE($D$4,11,1)-WEEKDAY(DATE($D$4,11,1),2)+1+17)<>11,"",DATE($D$4,11,1)-WEEKDAY(DATE($D$4,11,1),2)+1+17) | N54: =IF(MONTH(DATE($D$4,11,1)-WEEKDAY(DATE($D$4,11,1),2)+1+18)<>11,"",DATE($D$4,11,1)-WEEKDAY(DATE($D$4,11,1),2)+1+18) | O54: =IF(MONTH(DATE($D$4,11,1)-WEEKDAY(DATE($D$4,11,1),2)+1+19)<>11,"",DATE($D$4,11,1)-WEEKDAY(DATE($D$4,11,1),2)+1+19) | P54: =IF(MONTH(DATE($D$4,11,1)-WEEKDAY(DATE($D$4,11,1),2)+1+20)<>11,"",DATE($D$4,11,1)-WEEKDAY(DATE($D$4,11,1),2)+1+20) | R54: =IF(MONTH(DATE($D$4,12,1)-WEEKDAY(DATE($D$4,12,1),2)+1+14)<>12,"",DATE($D$4,12,1)-WEEKDAY(DATE($D$4,12,1),2)+1+14) | S54: =IF(MONTH(DATE($D$4,12,1)-WEEKDAY(DATE($D$4,12,1),2)+1+15)<>12,"",DATE($D$4,12,1)-WEEKDAY(DATE($D$4,12,1),2)+1+15) | T54: =IF(MONTH(DATE($D$4,12,1)-WEEKDAY(DATE($D$4,12,1),2)+1+16)<>12,"",DATE($D$4,12,1)-WEEKDAY(DATE($D$4,12,1),2)+1+16) | U54: =IF(MONTH(DATE($D$4,12,1)-WEEKDAY(DATE($D$4,12,1),2)+1+17)<>12,"",DATE($D$4,12,1)-WEEKDAY(DATE($D$4,12,1),2)+1+17) | V54: =IF(MONTH(DATE($D$4,12,1)-WEEKDAY(DATE($D$4,12,1),2)+1+18)<>12,"",DATE($D$4,12,1)-WEEKDAY(DATE($D$4,12,1),2)+1+18) | W54: =IF(MONTH(DATE($D$4,12,1)-WEEKDAY(DATE($D$4,12,1),2)+1+19)<>12,"",DATE($D$4,12,1)-WEEKDAY(DATE($D$4,12,1),2)+1+19) | X54: =IF(MONTH(DATE($D$4,12,1)-WEEKDAY(DATE($D$4,12,1),2)+1+20)<>12,"",DATE($D$4,12,1)-WEEKDAY(DATE($D$4,12,1),2)+1+20)
B55: =IF(MONTH(DATE($D$4,10,1)-WEEKDAY(DATE($D$4,10,1),2)+1+21)<>10,"",DATE($D$4,10,1)-WEEKDAY(DATE($D$4,10,1),2)+1+21) | C55: =IF(MONTH(DATE($D$4,10,1)-WEEKDAY(DATE($D$4,10,1),2)+1+22)<>10,"",DATE($D$4,10,1)-WEEKDAY(DATE($D$4,10,1),2)+1+22) | D55: =IF(MONTH(DATE($D$4,10,1)-WEEKDAY(DATE($D$4,10,1),2)+1+23)<>10,"",DATE($D$4,10,1)-WEEKDAY(DATE($D$4,10,1),2)+1+23) | E55: =IF(MONTH(DATE($D$4,10,1)-WEEKDAY(DATE($D$4,10,1),2)+1+24)<>10,"",DATE($D$4,10,1)-WEEKDAY(DATE($D$4,10,1),2)+1+24) | F55: =IF(MONTH(DATE($D$4,10,1)-WEEKDAY(DATE($D$4,10,1),2)+1+25)<>10,"",DATE($D$4,10,1)-WEEKDAY(DATE($D$4,10,1),2)+1+25) | G55: =IF(MONTH(DATE($D$4,10,1)-WEEKDAY(DATE($D$4,10,1),2)+1+26)<>10,"",DATE($D$4,10,1)-WEEKDAY(DATE($D$4,10,1),2)+1+26) | H55: =IF(MONTH(DATE($D$4,10,1)-WEEKDAY(DATE($D$4,10,1),2)+1+27)<>10,"",DATE($D$4,10,1)-WEEKDAY(DATE($D$4,10,1),2)+1+27) | J55: =IF(MONTH(DATE($D$4,11,1)-WEEKDAY(DATE($D$4,11,1),2)+1+21)<>11,"",DATE($D$4,11,1)-WEEKDAY(DATE($D$4,11,1),2)+1+21) | K55: =IF(MONTH(DATE($D$4,11,1)-WEEKDAY(DATE($D$4,11,1),2)+1+22)<>11,"",DATE($D$4,11,1)-WEEKDAY(DATE($D$4,11,1),2)+1+22) | L55: =IF(MONTH(DATE($D$4,11,1)-WEEKDAY(DATE($D$4,11,1),2)+1+23)<>11,"",DATE($D$4,11,1)-WEEKDAY(DATE($D$4,11,1),2)+1+23) | M55: =IF(MONTH(DATE($D$4,11,1)-WEEKDAY(DATE($D$4,11,1),2)+1+24)<>11,"",DATE($D$4,11,1)-WEEKDAY(DATE($D$4,11,1),2)+1+24) | N55: =IF(MONTH(DATE($D$4,11,1)-WEEKDAY(DATE($D$4,11,1),2)+1+25)<>11,"",DATE($D$4,11,1)-WEEKDAY(DATE($D$4,11,1),2)+1+25) | O55: =IF(MONTH(DATE($D$4,11,1)-WEEKDAY(DATE($D$4,11,1),2)+1+26)<>11,"",DATE($D$4,11,1)-WEEKDAY(DATE($D$4,11,1),2)+1+26) | P55: =IF(MONTH(DATE($D$4,11,1)-WEEKDAY(DATE($D$4,11,1),2)+1+27)<>11,"",DATE($D$4,11,1)-WEEKDAY(DATE($D$4,11,1),2)+1+27) | R55: =IF(MONTH(DATE($D$4,12,1)-WEEKDAY(DATE($D$4,12,1),2)+1+21)<>12,"",DATE($D$4,12,1)-WEEKDAY(DATE($D$4,12,1),2)+1+21) | S55: =IF(MONTH(DATE($D$4,12,1)-WEEKDAY(DATE($D$4,12,1),2)+1+22)<>12,"",DATE($D$4,12,1)-WEEKDAY(DATE($D$4,12,1),2)+1+22) | T55: =IF(MONTH(DATE($D$4,12,1)-WEEKDAY(DATE($D$4,12,1),2)+1+23)<>12,"",DATE($D$4,12,1)-WEEKDAY(DATE($D$4,12,1),2)+1+23) | U55: =IF(MONTH(DATE($D$4,12,1)-WEEKDAY(DATE($D$4,12,1),2)+1+24)<>12,"",DATE($D$4,12,1)-WEEKDAY(DATE($D$4,12,1),2)+1+24) | V55: =IF(MONTH(DATE($D$4,12,1)-WEEKDAY(DATE($D$4,12,1),2)+1+25)<>12,"",DATE($D$4,12,1)-WEEKDAY(DATE($D$4,12,1),2)+1+25) | W55: =IF(MONTH(DATE($D$4,12,1)-WEEKDAY(DATE($D$4,12,1),2)+1+26)<>12,"",DATE($D$4,12,1)-WEEKDAY(DATE($D$4,12,1),2)+1+26) | X55: =IF(MONTH(DATE($D$4,12,1)-WEEKDAY(DATE($D$4,12,1),2)+1+27)<>12,"",DATE($D$4,12,1)-WEEKDAY(DATE($D$4,12,1),2)+1+27)
B56: =IF(MONTH(DATE($D$4,10,1)-WEEKDAY(DATE($D$4,10,1),2)+1+28)<>10,"",DATE($D$4,10,1)-WEEKDAY(DATE($D$4,10,1),2)+1+28) | C56: =IF(MONTH(DATE($D$4,10,1)-WEEKDAY(DATE($D$4,10,1),2)+1+29)<>10,"",DATE($D$4,10,1)-WEEKDAY(DATE($D$4,10,1),2)+1+29) | D56: =IF(MONTH(DATE($D$4,10,1)-WEEKDAY(DATE($D$4,10,1),2)+1+30)<>10,"",DATE($D$4,10,1)-WEEKDAY(DATE($D$4,10,1),2)+1+30) | E56: =IF(MONTH(DATE($D$4,10,1)-WEEKDAY(DATE($D$4,10,1),2)+1+31)<>10,"",DATE($D$4,10,1)-WEEKDAY(DATE($D$4,10,1),2)+1+31) | F56: =IF(MONTH(DATE($D$4,10,1)-WEEKDAY(DATE($D$4,10,1),2)+1+32)<>10,"",DATE($D$4,10,1)-WEEKDAY(DATE($D$4,10,1),2)+1+32) | G56: =IF(MONTH(DATE($D$4,10,1)-WEEKDAY(DATE($D$4,10,1),2)+1+33)<>10,"",DATE($D$4,10,1)-WEEKDAY(DATE($D$4,10,1),2)+1+33) | H56: =IF(MONTH(DATE($D$4,10,1)-WEEKDAY(DATE($D$4,10,1),2)+1+34)<>10,"",DATE($D$4,10,1)-WEEKDAY(DATE($D$4,10,1),2)+1+34) | J56: =IF(MONTH(DATE($D$4,11,1)-WEEKDAY(DATE($D$4,11,1),2)+1+28)<>11,"",DATE($D$4,11,1)-WEEKDAY(DATE($D$4,11,1),2)+1+28) | K56: =IF(MONTH(DATE($D$4,11,1)-WEEKDAY(DATE($D$4,11,1),2)+1+29)<>11,"",DATE($D$4,11,1)-WEEKDAY(DATE($D$4,11,1),2)+1+29) | L56: =IF(MONTH(DATE($D$4,11,1)-WEEKDAY(DATE($D$4,11,1),2)+1+30)<>11,"",DATE($D$4,11,1)-WEEKDAY(DATE($D$4,11,1),2)+1+30) | M56: =IF(MONTH(DATE($D$4,11,1)-WEEKDAY(DATE($D$4,11,1),2)+1+31)<>11,"",DATE($D$4,11,1)-WEEKDAY(DATE($D$4,11,1),2)+1+31) | N56: =IF(MONTH(DATE($D$4,11,1)-WEEKDAY(DATE($D$4,11,1),2)+1+32)<>11,"",DATE($D$4,11,1)-WEEKDAY(DATE($D$4,11,1),2)+1+32) | O56: =IF(MONTH(DATE($D$4,11,1)-WEEKDAY(DATE($D$4,11,1),2)+1+33)<>11,"",DATE($D$4,11,1)-WEEKDAY(DATE($D$4,11,1),2)+1+33) | P56: =IF(MONTH(DATE($D$4,11,1)-WEEKDAY(DATE($D$4,11,1),2)+1+34)<>11,"",DATE($D$4,11,1)-WEEKDAY(DATE($D$4,11,1),2)+1+34) | R56: =IF(MONTH(DATE($D$4,12,1)-WEEKDAY(DATE($D$4,12,1),2)+1+28)<>12,"",DATE($D$4,12,1)-WEEKDAY(DATE($D$4,12,1),2)+1+28) | S56: =IF(MONTH(DATE($D$4,12,1)-WEEKDAY(DATE($D$4,12,1),2)+1+29)<>12,"",DATE($D$4,12,1)-WEEKDAY(DATE($D$4,12,1),2)+1+29) | T56: =IF(MONTH(DATE($D$4,12,1)-WEEKDAY(DATE($D$4,12,1),2)+1+30)<>12,"",DATE($D$4,12,1)-WEEKDAY(DATE($D$4,12,1),2)+1+30) | U56: =IF(MONTH(DATE($D$4,12,1)-WEEKDAY(DATE($D$4,12,1),2)+1+31)<>12,"",DATE($D$4,12,1)-WEEKDAY(DATE($D$4,12,1),2)+1+31) | V56: =IF(MONTH(DATE($D$4,12,1)-WEEKDAY(DATE($D$4,12,1),2)+1+32)<>12,"",DATE($D$4,12,1)-WEEKDAY(DATE($D$4,12,1),2)+1+32) | W56: =IF(MONTH(DATE($D$4,12,1)-WEEKDAY(DATE($D$4,12,1),2)+1+33)<>12,"",DATE($D$4,12,1)-WEEKDAY(DATE($D$4,12,1),2)+1+33) | X56: =IF(MONTH(DATE($D$4,12,1)-WEEKDAY(DATE($D$4,12,1),2)+1+34)<>12,"",DATE($D$4,12,1)-WEEKDAY(DATE($D$4,12,1),2)+1+34)
B57: =IF(MONTH(DATE($D$4,10,1)-WEEKDAY(DATE($D$4,10,1),2)+1+35)<>10,"",DATE($D$4,10,1)-WEEKDAY(DATE($D$4,10,1),2)+1+35) | C57: =IF(MONTH(DATE($D$4,10,1)-WEEKDAY(DATE($D$4,10,1),2)+1+36)<>10,"",DATE($D$4,10,1)-WEEKDAY(DATE($D$4,10,1),2)+1+36) | D57: =IF(MONTH(DATE($D$4,10,1)-WEEKDAY(DATE($D$4,10,1),2)+1+37)<>10,"",DATE($D$4,10,1)-WEEKDAY(DATE($D$4,10,1),2)+1+37) | E57: =IF(MONTH(DATE($D$4,10,1)-WEEKDAY(DATE($D$4,10,1),2)+1+38)<>10,"",DATE($D$4,10,1)-WEEKDAY(DATE($D$4,10,1),2)+1+38) | F57: =IF(MONTH(DATE($D$4,10,1)-WEEKDAY(DATE($D$4,10,1),2)+1+39)<>10,"",DATE($D$4,10,1)-WEEKDAY(DATE($D$4,10,1),2)+1+39) | G57: =IF(MONTH(DATE($D$4,10,1)-WEEKDAY(DATE($D$4,10,1),2)+1+40)<>10,"",DATE($D$4,10,1)-WEEKDAY(DATE($D$4,10,1),2)+1+40) | H57: =IF(MONTH(DATE($D$4,10,1)-WEEKDAY(DATE($D$4,10,1),2)+1+41)<>10,"",DATE($D$4,10,1)-WEEKDAY(DATE($D$4,10,1),2)+1+41) | J57: =IF(MONTH(DATE($D$4,11,1)-WEEKDAY(DATE($D$4,11,1),2)+1+35)<>11,"",DATE($D$4,11,1)-WEEKDAY(DATE($D$4,11,1),2)+1+35) | K57: =IF(MONTH(DATE($D$4,11,1)-WEEKDAY(DATE($D$4,11,1),2)+1+36)<>11,"",DATE($D$4,11,1)-WEEKDAY(DATE($D$4,11,1),2)+1+36) | L57: =IF(MONTH(DATE($D$4,11,1)-WEEKDAY(DATE($D$4,11,1),2)+1+37)<>11,"",DATE($D$4,11,1)-WEEKDAY(DATE($D$4,11,1),2)+1+37) | M57: =IF(MONTH(DATE($D$4,11,1)-WEEKDAY(DATE($D$4,11,1),2)+1+38)<>11,"",DATE($D$4,11,1)-WEEKDAY(DATE($D$4,11,1),2)+1+38) | N57: =IF(MONTH(DATE($D$4,11,1)-WEEKDAY(DATE($D$4,11,1),2)+1+39)<>11,"",DATE($D$4,11,1)-WEEKDAY(DATE($D$4,11,1),2)+1+39) | O57: =IF(MONTH(DATE($D$4,11,1)-WEEKDAY(DATE($D$4,11,1),2)+1+40)<>11,"",DATE($D$4,11,1)-WEEKDAY(DATE($D$4,11,1),2)+1+40) | P57: =IF(MONTH(DATE($D$4,11,1)-WEEKDAY(DATE($D$4,11,1),2)+1+41)<>11,"",DATE($D$4,11,1)-WEEKDAY(DATE($D$4,11,1),2)+1+41) | R57: =IF(MONTH(DATE($D$4,12,1)-WEEKDAY(DATE($D$4,12,1),2)+1+35)<>12,"",DATE($D$4,12,1)-WEEKDAY(DATE($D$4,12,1),2)+1+35) | S57: =IF(MONTH(DATE($D$4,12,1)-WEEKDAY(DATE($D$4,12,1),2)+1+36)<>12,"",DATE($D$4,12,1)-WEEKDAY(DATE($D$4,12,1),2)+1+36) | T57: =IF(MONTH(DATE($D$4,12,1)-WEEKDAY(DATE($D$4,12,1),2)+1+37)<>12,"",DATE($D$4,12,1)-WEEKDAY(DATE($D$4,12,1),2)+1+37) | U57: =IF(MONTH(DATE($D$4,12,1)-WEEKDAY(DATE($D$4,12,1),2)+1+38)<>12,"",DATE($D$4,12,1)-WEEKDAY(DATE($D$4,12,1),2)+1+38) | V57: =IF(MONTH(DATE($D$4,12,1)-WEEKDAY(DATE($D$4,12,1),2)+1+39)<>12,"",DATE($D$4,12,1)-WEEKDAY(DATE($D$4,12,1),2)+1+39) | W57: =IF(MONTH(DATE($D$4,12,1)-WEEKDAY(DATE($D$4,12,1),2)+1+40)<>12,"",DATE($D$4,12,1)-WEEKDAY(DATE($D$4,12,1),2)+1+40) | X57: =IF(MONTH(DATE($D$4,12,1)-WEEKDAY(DATE($D$4,12,1),2)+1+41)<>12,"",DATE($D$4,12,1)-WEEKDAY(DATE($D$4,12,1),2)+1+41)
B60: REGISTRO DE CITAS — escribe aquí; los calendarios de arriba se pintan solos
B61: Fecha | D61: Hora | F61: Min. | G61: Cita / asunto | M61: Con quién | P61: Lugar o enlace | S61: Prioridad | V61: Estado | Y61: Google Calendar | Z61: (técnico: próxima cita — no borrar) | AA61: (técnico: ID del evento en Google Calendar — lo escribe el script)
B62: 46247 | D62: 0.4375 | F62: 60 | G62: Reunión con el banco — línea de crédito (ejemplo) | M62: Oficina BBVA | P62: Sucursal Centro | S62: 1 · Urgente | V62: 2 · Confirmada | Y62: =IF(OR($B62="",$G62=""),"",HYPERLINK("https://calendar.google.com/calendar/render?action=TEMPLATE&text="&ENCODEURL($G62)&"&dates="&TEXT($B62,"YYYYMMDD")&"T"&TEXT($D62,"HHMMSS")&"/"&TEXT($B62+($D62+N($F62)/1440),"YYYYMMDD")&"T"&TEXT(MOD($D62+N($F62)/1440,1),"HHMMSS")&"&ctz=Europe/Madrid&location="&ENCODEURL($P62)&"&details="&ENCODEURL("Cita de "&$M62),"➕ Añadir")) | Z62: =IF(OR($B62="",$V62="4 · Cancelada",$V62="3 · Hecha",N($B62)<TODAY()),"",$B62)
B63: 46247 | D63: 0.70833333 | F63: 45 | G63: Llamada con Jose Antonio — acuerdo de devolución (ejemplo) | M63: Jose Antonio Garcia | P63: Teléfono | S63: 2 · Alta | V63: 1 · Pendiente | Y63: =IF(OR($B63="",$G63=""),"",HYPERLINK("https://calendar.google.com/calendar/render?action=TEMPLATE&text="&ENCODEURL($G63)&"&dates="&TEXT($B63,"YYYYMMDD")&"T"&TEXT($D63,"HHMMSS")&"/"&TEXT($B63+($D63+N($F63)/1440),"YYYYMMDD")&"T"&TEXT(MOD($D63+N($F63)/1440,1),"HHMMSS")&"&ctz=Europe/Madrid&location="&ENCODEURL($P63)&"&details="&ENCODEURL("Cita de "&$M63),"➕ Añadir")) | Z63: =IF(OR($B63="",$V63="4 · Cancelada",$V63="3 · Hecha",N($B63)<TODAY()),"",$B63)
B64: 46254 | D64: 0.375 | F64: 90 | G64: Revisión de facturas vencidas (ejemplo) | M64: Tú | P64: Casa | S64: 3 · Media | V64: 1 · Pendiente | Y64: =IF(OR($B64="",$G64=""),"",HYPERLINK("https://calendar.google.com/calendar/render?action=TEMPLATE&text="&ENCODEURL($G64)&"&dates="&TEXT($B64,"YYYYMMDD")&"T"&TEXT($D64,"HHMMSS")&"/"&TEXT($B64+($D64+N($F64)/1440),"YYYYMMDD")&"T"&TEXT(MOD($D64+N($F64)/1440,1),"HHMMSS")&"&ctz=Europe/Madrid&location="&ENCODEURL($P64)&"&details="&ENCODEURL("Cita de "&$M64),"➕ Añadir")) | Z64: =IF(OR($B64="",$V64="4 · Cancelada",$V64="3 · Hecha",N($B64)<TODAY()),"",$B64)
B65: 46262 | D65: 0.5 | F65: 60 | G65: Cierre de mes — actualizar Disponibilidad (ejemplo) | M65: Tú | P65: Casa | S65: 2 · Alta | V65: 1 · Pendiente | Y65: =IF(OR($B65="",$G65=""),"",HYPERLINK("https://calendar.google.com/calendar/render?action=TEMPLATE&text="&ENCODEURL($G65)&"&dates="&TEXT($B65,"YYYYMMDD")&"T"&TEXT($D65,"HHMMSS")&"/"&TEXT($B65+($D65+N($F65)/1440),"YYYYMMDD")&"T"&TEXT(MOD($D65+N($F65)/1440,1),"HHMMSS")&"&ctz=Europe/Madrid&location="&ENCODEURL($P65)&"&details="&ENCODEURL("Cita de "&$M65),"➕ Añadir")) | Z65: =IF(OR($B65="",$V65="4 · Cancelada",$V65="3 · Hecha",N($B65)<TODAY()),"",$B65)
B66: 46268 | D66: 0.6875 | F66: 60 | G66: Gestoría — declaración trimestral (ejemplo) | M66: Gestoría | P66: Videollamada | S66: 1 · Urgente | V66: 2 · Confirmada | Y66: =IF(OR($B66="",$G66=""),"",HYPERLINK("https://calendar.google.com/calendar/render?action=TEMPLATE&text="&ENCODEURL($G66)&"&dates="&TEXT($B66,"YYYYMMDD")&"T"&TEXT($D66,"HHMMSS")&"/"&TEXT($B66+($D66+N($F66)/1440),"YYYYMMDD")&"T"&TEXT(MOD($D66+N($F66)/1440,1),"HHMMSS")&"&ctz=Europe/Madrid&location="&ENCODEURL($P66)&"&details="&ENCODEURL("Cita de "&$M66),"➕ Añadir")) | Z66: =IF(OR($B66="",$V66="4 · Cancelada",$V66="3 · Hecha",N($B66)<TODAY()),"",$B66)
B67: 46280 | D67: 0.45833333 | F67: 30 | G67: Revisión de la cartera de inversiones (ejemplo) | M67: Tú | P67: Casa | S67: 4 · Baja | V67: 1 · Pendiente | Y67: =IF(OR($B67="",$G67=""),"",HYPERLINK("https://calendar.google.com/calendar/render?action=TEMPLATE&text="&ENCODEURL($G67)&"&dates="&TEXT($B67,"YYYYMMDD")&"T"&TEXT($D67,"HHMMSS")&"/"&TEXT($B67+($D67+N($F67)/1440),"YYYYMMDD")&"T"&TEXT(MOD($D67+N($F67)/1440,1),"HHMMSS")&"&ctz=Europe/Madrid&location="&ENCODEURL($P67)&"&details="&ENCODEURL("Cita de "&$M67),"➕ Añadir")) | Z67: =IF(OR($B67="",$V67="4 · Cancelada",$V67="3 · Hecha",N($B67)<TODAY()),"",$B67)
B68: 46296 | D68: 0.75 | F68: 60 | G68: Revisión del plan de salida de deuda (ejemplo) | M68: Tú | P68: Casa | S68: 3 · Media | V68: 1 · Pendiente | Y68: =IF(OR($B68="",$G68=""),"",HYPERLINK("https://calendar.google.com/calendar/render?action=TEMPLATE&text="&ENCODEURL($G68)&"&dates="&TEXT($B68,"YYYYMMDD")&"T"&TEXT($D68,"HHMMSS")&"/"&TEXT($B68+($D68+N($F68)/1440),"YYYYMMDD")&"T"&TEXT(MOD($D68+N($F68)/1440,1),"HHMMSS")&"&ctz=Europe/Madrid&location="&ENCODEURL($P68)&"&details="&ENCODEURL("Cita de "&$M68),"➕ Añadir")) | Z68: =IF(OR($B68="",$V68="4 · Cancelada",$V68="3 · Hecha",N($B68)<TODAY()),"",$B68)
B69: 46338 | D69: 0.41666667 | F69: 120 | G69: Notaría — firma hipoteca (ejemplo) | M69: Notaría | P69: Notaría | S69: 1 · Urgente | V69: 1 · Pendiente | Y69: =IF(OR($B69="",$G69=""),"",HYPERLINK("https://calendar.google.com/calendar/render?action=TEMPLATE&text="&ENCODEURL($G69)&"&dates="&TEXT($B69,"YYYYMMDD")&"T"&TEXT($D69,"HHMMSS")&"/"&TEXT($B69+($D69+N($F69)/1440),"YYYYMMDD")&"T"&TEXT(MOD($D69+N($F69)/1440,1),"HHMMSS")&"&ctz=Europe/Madrid&location="&ENCODEURL($P69)&"&details="&ENCODEURL("Cita de "&$M69),"➕ Añadir")) | Z69: =IF(OR($B69="",$V69="4 · Cancelada",$V69="3 · Hecha",N($B69)<TODAY()),"",$B69)
Y70: =IF(OR($B70="",$G70=""),"",HYPERLINK("https://calendar.google.com/calendar/render?action=TEMPLATE&text="&ENCODEURL($G70)&"&dates="&TEXT($B70,"YYYYMMDD")&"T"&TEXT($D70,"HHMMSS")&"/"&TEXT($B70+($D70+N($F70)/1440),"YYYYMMDD")&"T"&TEXT(MOD($D70+N($F70)/1440,1),"HHMMSS")&"&ctz=Europe/Madrid&location="&ENCODEURL($P70)&"&details="&ENCODEURL("Cita de "&$M70),"➕ Añadir")) | Z70: =IF(OR($B70="",$V70="4 · Cancelada",$V70="3 · Hecha",N($B70)<TODAY()),"",$B70)
Y71: =IF(OR($B71="",$G71=""),"",HYPERLINK("https://calendar.google.com/calendar/render?action=TEMPLATE&text="&ENCODEURL($G71)&"&dates="&TEXT($B71,"YYYYMMDD")&"T"&TEXT($D71,"HHMMSS")&"/"&TEXT($B71+($D71+N($F71)/1440),"YYYYMMDD")&"T"&TEXT(MOD($D71+N($F71)/1440,1),"HHMMSS")&"&ctz=Europe/Madrid&location="&ENCODEURL($P71)&"&details="&ENCODEURL("Cita de "&$M71),"➕ Añadir")) | Z71: =IF(OR($B71="",$V71="4 · Cancelada",$V71="3 · Hecha",N($B71)<TODAY()),"",$B71)
Y72: =IF(OR($B72="",$G72=""),"",HYPERLINK("https://calendar.google.com/calendar/render?action=TEMPLATE&text="&ENCODEURL($G72)&"&dates="&TEXT($B72,"YYYYMMDD")&"T"&TEXT($D72,"HHMMSS")&"/"&TEXT($B72+($D72+N($F72)/1440),"YYYYMMDD")&"T"&TEXT(MOD($D72+N($F72)/1440,1),"HHMMSS")&"&ctz=Europe/Madrid&location="&ENCODEURL($P72)&"&details="&ENCODEURL("Cita de "&$M72),"➕ Añadir")) | Z72: =IF(OR($B72="",$V72="4 · Cancelada",$V72="3 · Hecha",N($B72)<TODAY()),"",$B72)
Y73: =IF(OR($B73="",$G73=""),"",HYPERLINK("https://calendar.google.com/calendar/render?action=TEMPLATE&text="&ENCODEURL($G73)&"&dates="&TEXT($B73,"YYYYMMDD")&"T"&TEXT($D73,"HHMMSS")&"/"&TEXT($B73+($D73+N($F73)/1440),"YYYYMMDD")&"T"&TEXT(MOD($D73+N($F73)/1440,1),"HHMMSS")&"&ctz=Europe/Madrid&location="&ENCODEURL($P73)&"&details="&ENCODEURL("Cita de "&$M73),"➕ Añadir")) | Z73: =IF(OR($B73="",$V73="4 · Cancelada",$V73="3 · Hecha",N($B73)<TODAY()),"",$B73)
Y74: =IF(OR($B74="",$G74=""),"",HYPERLINK("https://calendar.google.com/calendar/render?action=TEMPLATE&text="&ENCODEURL($G74)&"&dates="&TEXT($B74,"YYYYMMDD")&"T"&TEXT($D74,"HHMMSS")&"/"&TEXT($B74+($D74+N($F74)/1440),"YYYYMMDD")&"T"&TEXT(MOD($D74+N($F74)/1440,1),"HHMMSS")&"&ctz=Europe/Madrid&location="&ENCODEURL($P74)&"&details="&ENCODEURL("Cita de "&$M74),"➕ Añadir")) | Z74: =IF(OR($B74="",$V74="4 · Cancelada",$V74="3 · Hecha",N($B74)<TODAY()),"",$B74)
Y75: =IF(OR($B75="",$G75=""),"",HYPERLINK("https://calendar.google.com/calendar/render?action=TEMPLATE&text="&ENCODEURL($G75)&"&dates="&TEXT($B75,"YYYYMMDD")&"T"&TEXT($D75,"HHMMSS")&"/"&TEXT($B75+($D75+N($F75)/1440),"YYYYMMDD")&"T"&TEXT(MOD($D75+N($F75)/1440,1),"HHMMSS")&"&ctz=Europe/Madrid&location="&ENCODEURL($P75)&"&details="&ENCODEURL("Cita de "&$M75),"➕ Añadir")) | Z75: =IF(OR($B75="",$V75="4 · Cancelada",$V75="3 · Hecha",N($B75)<TODAY()),"",$B75)
Y76: =IF(OR($B76="",$G76=""),"",HYPERLINK("https://calendar.google.com/calendar/render?action=TEMPLATE&text="&ENCODEURL($G76)&"&dates="&TEXT($B76,"YYYYMMDD")&"T"&TEXT($D76,"HHMMSS")&"/"&TEXT($B76+($D76+N($F76)/1440),"YYYYMMDD")&"T"&TEXT(MOD($D76+N($F76)/1440,1),"HHMMSS")&"&ctz=Europe/Madrid&location="&ENCODEURL($P76)&"&details="&ENCODEURL("Cita de "&$M76),"➕ Añadir")) | Z76: =IF(OR($B76="",$V76="4 · Cancelada",$V76="3 · Hecha",N($B76)<TODAY()),"",$B76)
Y77: =IF(OR($B77="",$G77=""),"",HYPERLINK("https://calendar.google.com/calendar/render?action=TEMPLATE&text="&ENCODEURL($G77)&"&dates="&TEXT($B77,"YYYYMMDD")&"T"&TEXT($D77,"HHMMSS")&"/"&TEXT($B77+($D77+N($F77)/1440),"YYYYMMDD")&"T"&TEXT(MOD($D77+N($F77)/1440,1),"HHMMSS")&"&ctz=Europe/Madrid&location="&ENCODEURL($P77)&"&details="&ENCODEURL("Cita de "&$M77),"➕ Añadir")) | Z77: =IF(OR($B77="",$V77="4 · Cancelada",$V77="3 · Hecha",N($B77)<TODAY()),"",$B77)
Y78: =IF(OR($B78="",$G78=""),"",HYPERLINK("https://calendar.google.com/calendar/render?action=TEMPLATE&text="&ENCODEURL($G78)&"&dates="&TEXT($B78,"YYYYMMDD")&"T"&TEXT($D78,"HHMMSS")&"/"&TEXT($B78+($D78+N($F78)/1440),"YYYYMMDD")&"T"&TEXT(MOD($D78+N($F78)/1440,1),"HHMMSS")&"&ctz=Europe/Madrid&location="&ENCODEURL($P78)&"&details="&ENCODEURL("Cita de "&$M78),"➕ Añadir")) | Z78: =IF(OR($B78="",$V78="4 · Cancelada",$V78="3 · Hecha",N($B78)<TODAY()),"",$B78)
Y79: =IF(OR($B79="",$G79=""),"",HYPERLINK("https://calendar.google.com/calendar/render?action=TEMPLATE&text="&ENCODEURL($G79)&"&dates="&TEXT($B79,"YYYYMMDD")&"T"&TEXT($D79,"HHMMSS")&"/"&TEXT($B79+($D79+N($F79)/1440),"YYYYMMDD")&"T"&TEXT(MOD($D79+N($F79)/1440,1),"HHMMSS")&"&ctz=Europe/Madrid&location="&ENCODEURL($P79)&"&details="&ENCODEURL("Cita de "&$M79),"➕ Añadir")) | Z79: =IF(OR($B79="",$V79="4 · Cancelada",$V79="3 · Hecha",N($B79)<TODAY()),"",$B79)
Y80: =IF(OR($B80="",$G80=""),"",HYPERLINK("https://calendar.google.com/calendar/render?action=TEMPLATE&text="&ENCODEURL($G80)&"&dates="&TEXT($B80,"YYYYMMDD")&"T"&TEXT($D80,"HHMMSS")&"/"&TEXT($B80+($D80+N($F80)/1440),"YYYYMMDD")&"T"&TEXT(MOD($D80+N($F80)/1440,1),"HHMMSS")&"&ctz=Europe/Madrid&location="&ENCODEURL($P80)&"&details="&ENCODEURL("Cita de "&$M80),"➕ Añadir")) | Z80: =IF(OR($B80="",$V80="4 · Cancelada",$V80="3 · Hecha",N($B80)<TODAY()),"",$B80)
Y81: =IF(OR($B81="",$G81=""),"",HYPERLINK("https://calendar.google.com/calendar/render?action=TEMPLATE&text="&ENCODEURL($G81)&"&dates="&TEXT($B81,"YYYYMMDD")&"T"&TEXT($D81,"HHMMSS")&"/"&TEXT($B81+($D81+N($F81)/1440),"YYYYMMDD")&"T"&TEXT(MOD($D81+N($F81)/1440,1),"HHMMSS")&"&ctz=Europe/Madrid&location="&ENCODEURL($P81)&"&details="&ENCODEURL("Cita de "&$M81),"➕ Añadir")) | Z81: =IF(OR($B81="",$V81="4 · Cancelada",$V81="3 · Hecha",N($B81)<TODAY()),"",$B81)
... Y211: =IF(OR($B211="",$G211=""),"",HYPERLINK("https://calendar.google.com/calendar/render?action=TEMPLATE&text="&ENCODEURL($G211)&"&dates="&TEXT($B211,"YYYYMMDD")&"T"&TEXT($D211,"HHMMSS")&"/"&TEXT($B211+($D211+N($F211)/1440),"YYYYMMDD")&"T"&TEXT(MOD($D211+N($F211)/1440,1),"HHMMSS")&"&ctz=Europe/Madrid&location="&ENCODEURL($P211)&"&details="&ENCODEURL("Cita de "&$M211),"➕ Añadir")) | Z211: =IF(OR($B211="",$V211="4 · Cancelada",$V211="3 · Hecha",N($B211)<TODAY()),"",$B211)
B214: CÓMO CONECTARLO CON GOOGLE CALENDAR
B216: OPCIÓN A · un clic por cita (no necesita instalar nada)
B217: Rellena la fila y pulsa "➕ Añadir" en la última columna: se abre Google Calendar con el título, la fecha, la hora, la duración y el lugar ya puestos. Solo tienes que darle a Guardar. Funciona igual en Excel y en Google Sheets.
B219: OPCIÓN B · sincronización automática (Google Sheets + Apps Script)
B220: Sube este libro a Google Sheets. Menú Extensiones → Apps Script → pega el archivo "citas-google-calendar.gs" que te he dejado en la carpeta → Guardar → Ejecutar "crearCitasEnCalendar" y autoriza. Se crearán en tu calendario todas las citas que no estén canceladas y se marcará la columna Estado. Puedes programarlo cada hora con Activadores.
B222: OPCIÓN C · al revés, traer las citas del calendario a esta hoja
B223: El mismo archivo .gs incluye la función "importarDesdeCalendar": lee tu Google Calendar del año elegido en D4 y rellena el registro. Útil la primera vez, para no teclear lo que ya tienes.
B225: REGLA DE COLORES
B226: Cada día se pinta con la prioridad MÁS ALTA de ese día: rojo 1 Urgente, naranja 2 Alta, azul 3 Media, verde 4 Baja, gris si la cita no tiene prioridad. Las canceladas no pintan ni cuentan. El día de hoy sale con borde grueso y subrayado. El calendario grande de arriba muestra el mes elegido en el desplegable MES (o el actual, por defecto).

Sheet Balance
B1: BALANCE GENERAL
B2: Foto de hoy: lo que tienes menos lo que debes. Los saldos y las líneas de crédito se reparten entre tu economía y la del hogar según la columna Ámbito de la hoja Disponibilidad; las facturas heredan el ámbito de la cuenta desde la que se pagan.
B4: Balance a fin del periodo seleccionado | C4: =EOMONTH(Panel!$H$5,0) | D4: =Panel!$I$4 | E4: Los pasivos por facturas se filtran a esa fecha. Los saldos bancarios usan el histórico de cierres si lo has rellenado; si no, los de hoy.
B6: Concepto | C6: Tú (€) | D6: Hogar (€) | E6: CONSOLIDADO (€) | F6: % s/activo | G6: Notas | I6: Datos para los gráficos
B7: ACTIVO | I7: Concepto | J7: €
B8: Activo corriente (lo que es dinero o se convierte en dinero en menos de un año) | I8: Activo corriente | J8: =$E$13
B9: Efectivo y saldos bancarios disponibles | C9: {=IFERROR(INDEX($C$58:$C$72,MATCH(Panel!$I$4,$B$58:$B$72,0)),SUMIFS(Disponibilidad!$J$6:$J$18,Disponibilidad!$O$6:$O$18,"Tú"))} | D9: {=IFERROR(INDEX($D$58:$D$72,MATCH(Panel!$I$4,$B$58:$B$72,0)),SUMIFS(Disponibilidad!$J$6:$J$18,Disponibilidad!$O$6:$O$18,"Hogar"))} | E9: =N($C9)+N($D9) | F9: =IFERROR($E9/$E$22,"") | I9: Activo no corriente | J9: =$E$20
B10: Saldos retenidos o bloqueados | C10: =SUMIFS(Disponibilidad!$I$6:$I$18,Disponibilidad!$O$6:$O$18,"Tú") | D10: =SUMIFS(Disponibilidad!$I$6:$I$18,Disponibilidad!$O$6:$O$18,"Hogar") | E10: =N($C10)+N($D10) | F10: =IFERROR($E10/$E$22,"") | I10: Pasivo corriente | J10: =$E$32
B11: Fondos comprometidos (no disponibles) | C11: =SUMIFS(Disponibilidad!$G$6:$G$18,Disponibilidad!$H$6:$H$18,"No",Disponibilidad!$O$6:$O$18,"Tú") | D11: =SUMIFS(Disponibilidad!$G$6:$G$18,Disponibilidad!$H$6:$H$18,"No",Disponibilidad!$O$6:$O$18,"Hogar") | E11: =N($C11)+N($D11) | F11: =IFERROR($E11/$E$22,"") | G11: Sobre todo ABANCA: es tuyo y suma patrimonio, pero no lo puedes usar para pagar facturas. | I11: Pasivo no corriente | J11: =$E$37
B12: Facturas por cobrar / dinero que te deben | C12: 0 | D12: 0 | E12: =N($C12)+N($D12) | F12: =IFERROR($E12/$E$22,"") | I12: Patrimonio neto | J12: =$E$41
B13: Total activo corriente | C13: =SUM(C9:C12) | D13: =SUM(D9:D12) | E13: =SUM(E9:E12) | F13: =IFERROR($E13/$E$22,"")
B15: Activo no corriente (lo que no piensas convertir en dinero este año)
B16: Cartera de inversión | C16: =SUMIFS(Inversiones!$L$7:$L$47,Inversiones!$X$7:$X$47,"Sí") | E16: =N($C16)+N($D16) | F16: =IFERROR($E16/$E$22,"") | G16: Valor actual total de la hoja Inversiones. Toda la cartera se imputa a la columna "Tú": la hoja Inversiones no tiene columna de Ámbito.
B17: Inmuebles (viviendas) | C17: =SUMIFS($E$80:$E$88,$G$80:$G$88,"Inmueble",$H$80:$H$88,"Tú") | D17: =SUMIFS($E$80:$E$88,$G$80:$G$88,"Inmueble",$H$80:$H$88,"Hogar") | E17: =N($C17)+N($D17) | F17: =IFERROR($E17/$E$22,"") | G17: Suma de la tabla de detalle de abajo. España 117.000 € + República Dominicana 85.250 € (5.500.000 DOP).
B18: Bienes duraderos (vehículo, informática, mobiliario, oro) | C18: =SUMIFS($E$80:$E$88,$G$80:$G$88,"Bien duradero",$H$80:$H$88,"Tú") | D18: =SUMIFS($E$80:$E$88,$G$80:$G$88,"Bien duradero",$H$80:$H$88,"Hogar") | E18: =N($C18)+N($D18) | F18: =IFERROR($E18/$E$22,"") | G18: Vehículo 1.000 € + equipos informáticos 950 € + muebles y electrodomésticos 1.500 €.
B19: Otros activos | C19: =SUMIFS($E$80:$E$88,$G$80:$G$88,"Otro activo",$H$80:$H$88,"Tú") | D19: =SUMIFS($E$80:$E$88,$G$80:$G$88,"Otro activo",$H$80:$H$88,"Hogar") | E19: =N($C19)+N($D19) | F19: =IFERROR($E19/$E$22,"") | G19: Detállalos en la tabla de abajo cuando puedas.
B20: Total activo no corriente | C20: =SUM(C16:C19) | D20: =SUM(D16:D19) | E20: =SUM(E16:E19) | F20: =IFERROR($E20/$E$22,"")
B22: TOTAL ACTIVO | C22: =C13+C20 | D22: =D13+D20 | E22: =E13+E20 | F22: =IF($E$22=0,"",1)
B24: PASIVO
B25: Pasivo corriente (lo que debes pagar en menos de un año)
B26: Facturas pendientes (excluida la deuda financiera) | C26: =SUMIFS(Facturas!$K$6:$K$205,Facturas!$AC$6:$AC$205,"Tú",Facturas!$AE$6:$AE$205,"<="&$C$4)-SUMIFS(Facturas!$K$6:$K$205,Facturas!$AC$6:$AC$205,"Tú",Facturas!$D$6:$D$205,"Tarjeta de crédito",Facturas!$AE$6:$AE$205,"<="&$C$4)-SUMIFS(Facturas!$K$6:$K$205,Facturas!$AC$6:$AC$205,"Tú",Facturas!$D$6:$D$205,"Empeño",Facturas!$AE$6:$AE$205,"<="&$C$4)-SUMIFS(Facturas!$K$6:$K$205,Facturas!$AC$6:$AC$205,"Tú",Facturas!$D$6:$D$205,"Préstamo particular",Facturas!$AE$6:$AE$205,"<="&$C$4)-SUMIFS(Facturas!$K$6:$K$205,Facturas!$AC$6:$AC$205,"Tú",Facturas!$D$6:$D$205,"Crédito comercial",Facturas!$AE$6:$AE$205,"<="&$C$4) | D26: =SUMIFS(Facturas!$K$6:$K$205,Facturas!$AC$6:$AC$205,"Hogar",Facturas!$AE$6:$AE$205,"<="&$C$4)-SUMIFS(Facturas!$K$6:$K$205,Facturas!$AC$6:$AC$205,"Hogar",Facturas!$D$6:$D$205,"Tarjeta de crédito",Facturas!$AE$6:$AE$205,"<="&$C$4)-SUMIFS(Facturas!$K$6:$K$205,Facturas!$AC$6:$AC$205,"Hogar",Facturas!$D$6:$D$205,"Empeño",Facturas!$AE$6:$AE$205,"<="&$C$4)-SUMIFS(Facturas!$K$6:$K$205,Facturas!$AC$6:$AC$205,"Hogar",Facturas!$D$6:$D$205,"Préstamo particular",Facturas!$AE$6:$AE$205,"<="&$C$4)-SUMIFS(Facturas!$K$6:$K$205,Facturas!$AC$6:$AC$205,"Hogar",Facturas!$D$6:$D$205,"Crédito comercial",Facturas!$AE$6:$AE$205,"<="&$C$4) | E26: =N($C26)+N($D26) | F26: =IFERROR($E26/$E$22,"") | G26: Saldo vivo de la hoja Facturas a la fecha del balance, usando el VENCIMIENTO EFECTIVO (si aplazas una factura, cuenta la fecha nueva). Se descuentan "Tarjeta de crédito", "Empeño", "Préstamo particular" y "Crédito comercial" porque cada una tiene su propia fila más abajo. Los "Intereses de empeño" sí se quedan aquí: son una obligación adicional al capital.
B27: Saldo dispuesto en tarjetas y líneas de crédito | C27: =SUMIFS(Disponibilidad!$G$23:$G$26,Disponibilidad!$O$23:$O$26,"Tú") | D27: =SUMIFS(Disponibilidad!$G$23:$G$26,Disponibilidad!$O$23:$O$26,"Hogar") | E27: =N($C27)+N($D27) | F27: =IFERROR($E27/$E$22,"") | G27: Lo dispuesto, no el límite. Un límite sin usar no es deuda.
B28: Empeños — capital pendiente de las prendas | C28: =SUMIFS($D$105:$D$114,$H$105:$H$114,"Tú") | D28: =SUMIFS($D$105:$D$114,$H$105:$H$114,"Hogar") | E28: =N($C28)+N($D28) | F28: =IFERROR($E28/$E$22,"") | G28: Suma del detalle de PRENDAS de abajo (bloque A). Solo empeños: los préstamos de particulares tienen ahora su propia fila. | I28: Composición del activo | J28: €
B29: Parte de la hipoteca a pagar en 12 meses | C29: 0 | D29: =$C$96 | E29: =N($C29)+N($D29) | F29: =IFERROR($E29/$E$22,"") | G29: La hipoteca es del ámbito Hogar: por eso la columna "Tú" va a cero. | I29: Efectivo disponible | J29: =$E$9
B30: Préstamos de particulares (Jose Antonio, Fulgencia, …) | C30: =SUMIFS(Facturas!$K$6:$K$205,Facturas!$AC$6:$AC$205,"Tú",Facturas!$D$6:$D$205,"Préstamo particular",Facturas!$AE$6:$AE$205,"<="&$C$4) | D30: =SUMIFS(Facturas!$K$6:$K$205,Facturas!$AC$6:$AC$205,"Hogar",Facturas!$D$6:$D$205,"Préstamo particular",Facturas!$AE$6:$AE$205,"<="&$C$4) | E30: =N($C30)+N($D30) | F30: =IFERROR($E30/$E$22,"") | G30: Se alimenta SOLA de la hoja Facturas: todas las facturas con categoría "Préstamo particular". Cuando registres un pago en Caja enlazado a esa factura, baja aquí y baja la caja. El desglose por prestamista está en el bloque B del final de esta hoja.
B31: Crédito comercial y otras deudas a corto plazo | C31: =SUMIFS(Facturas!$K$6:$K$205,Facturas!$AC$6:$AC$205,"Tú",Facturas!$D$6:$D$205,"Crédito comercial")+N($C$143) | D31: =SUMIFS(Facturas!$K$6:$K$205,Facturas!$AC$6:$AC$205,"Hogar",Facturas!$D$6:$D$205,"Crédito comercial")+N($D$143) | E31: =N($C31)+N($D31) | F31: =IFERROR($E31/$E$22,"") | G31: Compras aplazadas a proveedores y microcréditos: todas las facturas con categoría "Crédito comercial" (Karma Market, Vivus, Imagin…). Se toma el saldo vivo COMPLETO, sin filtrar por fecha de vencimiento: la deuda existe hoy aunque la cuota venza el mes que viene. El desglose por proveedor está en la sección C). En la fila 143 puedes añadir a mano cualquier otra deuda a corto plazo que no esté en Facturas. | I31: Retenido o comprometido | J31: =$E$10+$E$11
B32: Total pasivo corriente | C32: =SUM(C26:C31) | D32: =SUM(D26:D31) | E32: =SUM(E26:E31) | F32: =IFERROR($E32/$E$22,"") | I32: Cartera de inversión | J32: =$E$16
I33: Vivienda | J33: =$E$17
B34: Pasivo no corriente | I34: Otros bienes | J34: =$E$18+$E$19
B35: Hipoteca pendiente (más allá de 12 meses) | D35: =$C$97 | E35: =N($C35)+N($D35) | F35: =IFERROR($E35/$E$22,"") | G35: El resto del capital vivo.
B36: Otras deudas a largo plazo | C36: 0 | D36: 0 | E36: =N($C36)+N($D36) | F36: =IFERROR($E36/$E$22,"")
B37: Total pasivo no corriente | C37: =SUM(C35:C36) | D37: =SUM(D35:D36) | E37: =SUM(E35:E36) | F37: =IFERROR($E37/$E$22,"")
B39: TOTAL PASIVO | C39: =C32+C37 | D39: =D32+D37 | E39: =E32+E37 | F39: =IFERROR($E$39/$E$22,"")
B41: TOTAL PATRIMONIO NETO (Activo − Pasivo) | C41: =C22-C39 | D41: =D22-D39 | E41: =E22-E39 | F41: =IFERROR($E$41/$E$22,"") | G41: No es una lista de cosas: es una resta. Es el único número que resume si vas hacia arriba o hacia abajo.
B42: TOTAL PASIVO + PATRIMONIO NETO | C42: =C39+C41 | D42: =D39+D41 | E42: =E39+E41 | F42: =IF($E$22=0,"",1) | G42: Debe dar exactamente el mismo número que TOTAL ACTIVO (fila 22). Es la ecuación contable básica.
B43: ✔️ COMPROBACIÓN DEL BALANCE (Activo − Pasivo − Patrimonio = 0) | C43: =ROUND(C22-C42,2) | D43: =ROUND(D22-D42,2) | E43: =ROUND(E22-E42,2) | G43: =IF(ROUND($E$43,2)=0,"✅ CUADRA: el activo es igual al pasivo más el patrimonio","🔴 NO CUADRA: faltan "&TEXT(ABS($E$43),"#,##0.00")&" € por explicar")
B44: Estado de los datos | C44: =IF(AND($E$17=0,$C$92=0),"⚠️ Balance incompleto: falta el valor de la vivienda y el capital vivo de la hipoteca","✅ Datos principales cargados")
B45: RATIOS DEL BALANCE
B46: Ratio | C46: Valor | D46: Referencia | E46: Estado | G46: Qué significa
B47: Fondo de maniobra (activo corriente − pasivo corriente) | C47: =$E$13-$E$32 | D47: > 0 | E47: =IF($C47>0,"✅","🔴") | G47: Si es negativo, tus deudas a corto superan lo que puedes convertir en dinero: es la definición de tensión de tesorería.
B48: Ratio de liquidez (activo corriente / pasivo corriente) | C48: =IFERROR($E$13/$E$32,"") | D48: entre 1,2 y 2 | E48: =IF(N($C48)=0,"—",IF($C48>=1.2,"✅",IF($C48>=1,"🟡","🔴"))) | G48: Cuántas veces cubres con dinero disponible lo que debes pagar este año.
B49: Endeudamiento (pasivo / activo) | C49: =IFERROR($E$39/$E$22,"") | D49: < 50% | E49: =IF(N($C49)=0,"—",IF($C49<0.5,"✅",IF($C49<0.7,"🟡","🔴"))) | G49: Qué parte de lo que posees es en realidad de otros.
B50: Deuda financiera / patrimonio neto | C50: =IFERROR(($E$27+$E$28+$E$29+$E$30+$E$35)/$E$41,"") | D50: < 1 | E50: =IF(N($C50)=0,"—",IF(AND($C50>0,$C50<1),"✅","🔴")) | G50: Euros de deuda con interés por cada euro de patrimonio propio.
B51: Deuda vencida sobre el total de facturas | C51: =IFERROR(Facturas!$AG$24/Facturas!$AG$20,"") | D51: 0% | E51: =IF(N($C51)=0,"✅",IF($C51<0.1,"🟡","🔴")) | G51: Parte de lo que debes que ya está fuera de plazo. Cualquier cifra distinta de cero encarece la deuda con recargos.
B52: Crédito disponible | C52: =Disponibilidad!$I$27 | D52: > 1 mes de gastos | E52: =IF($C52>Resultados!$F$41,"✅","🔴") | G52: Margen que te queda en las líneas de crédito. Es tu única red si algo se tuerce.
B55: HISTÓRICO DE SALDOS AL CIERRE DE CADA MES
B56: Rellena el disponible real al último día de cada mes. El balance lo usará automáticamente para el periodo que elijas; si el mes no está, usa los saldos de hoy.
B57: Mes | C57: Disponible tú (€) | D57: Disponible hogar (€) | E57: Total (€) | G57: Notas
E58: =IF($B58="","",N($C58)+N($D58))
E59: =IF($B59="","",N($C59)+N($D59))
E60: =IF($B60="","",N($C60)+N($D60))
E61: =IF($B61="","",N($C61)+N($D61))
E62: =IF($B62="","",N($C62)+N($D62))
E63: =IF($B63="","",N($C63)+N($D63))
E64: =IF($B64="","",N($C64)+N($D64))
E65: =IF($B65="","",N($C65)+N($D65))
E66: =IF($B66="","",N($C66)+N($D66))
E67: =IF($B67="","",N($C67)+N($D67))
E68: =IF($B68="","",N($C68)+N($D68))
E69: =IF($B69="","",N($C69)+N($D69))
... E72: =IF($B72="","",N($C72)+N($D72))
B74: Origen de los saldos de este balance | C74: =IF(ISNUMBER(MATCH(Panel!$I$4,$B$58:$B$72,0)),"📌 Cierre histórico de "&Panel!$I$4,"🕐 Saldos de hoy (no hay cierre cargado para "&Panel!$I$4&")")
B77: DETALLE DE INMUEBLES, BIENES Y DEUDA HIPOTECARIA
B78: Escribe aquí cada bien con su moneda. Lo que esté en divisa se convierte solo con la tabla de tipos de cambio de la hoja Disponibilidad. Las tres filas de "Activo no corriente" del balance se alimentan de esta tabla.
B79: Concepto | C79: Importe en su moneda | D79: Moneda | E79: VALOR (€) | F79: T.C. | G79: Grupo | H79: Ámbito | I79: Notas
B80: Vivienda en España | C80: 117000 | D80: EUR | E80: =IF($B80="","",N($C80)*$F80) | F80: {=IF($D80="","",IFERROR(INDEX(Disponibilidad!$N$6:$N$9,MATCH($D80,Disponibilidad!$M$6:$M$9,0)),1))} | G80: Inmueble | H80: Hogar | I80: Valor estimado de mercado. Sobre esta vivienda pesa la hipoteca del bloque de abajo.
B81: Vivienda en República Dominicana | C81: 5500000 | D81: DOP | E81: =IF($B81="","",N($C81)*$F81) | F81: {=IF($D81="","",IFERROR(INDEX(Disponibilidad!$N$6:$N$9,MATCH($D81,Disponibilidad!$M$6:$M$9,0)),1))} | G81: Inmueble | H81: Hogar | I81: ⚠️ Libre de cargas. Se convierte con el tipo DOP de la hoja Disponibilidad (0,0155 €/DOP). Verifica ese tipo: mueve 85.250 € de tu patrimonio, así que un error del 5% son más de 4.000 €.
B82: Relojes de gama media | C82: 1840 | D82: EUR | E82: =IF($B82="","",N($C82)*$F82) | F82: {=IF($D82="","",IFERROR(INDEX(Disponibilidad!$N$6:$N$9,MATCH($D82,Disponibilidad!$M$6:$M$9,0)),1))} | G82: Bien duradero | H82: Hogar | I82: Valóralos a precio de venta realista (lo que te pagaría hoy un comprador), no a precio de compra. Salvo piezas muy concretas, un reloj de gama media pierde bastante valor y no es fácil de vender rápido.
B83: Vehículo | C83: 1000 | D83: EUR | E83: =IF($B83="","",N($C83)*$F83) | F83: {=IF($D83="","",IFERROR(INDEX(Disponibilidad!$N$6:$N$9,MATCH($D83,Disponibilidad!$M$6:$M$9,0)),1))} | G83: Bien duradero | H83: Hogar | I83: Se deprecia: revísalo a la baja una vez al año.
B84: Equipos informáticos | C84: 950 | D84: EUR | E84: =IF($B84="","",N($C84)*$F84) | F84: {=IF($D84="","",IFERROR(INDEX(Disponibilidad!$N$6:$N$9,MATCH($D84,Disponibilidad!$M$6:$M$9,0)),1))} | G84: Bien duradero | H84: Hogar | I84: Se deprecian rápido, entre un 25% y un 33% al año.
B85: Muebles y electrodomésticos | C85: 1500 | D85: EUR | E85: =IF($B85="","",N($C85)*$F85) | F85: {=IF($D85="","",IFERROR(INDEX(Disponibilidad!$N$6:$N$9,MATCH($D85,Disponibilidad!$M$6:$M$9,0)),1))} | G85: Bien duradero | H85: Hogar
B86: Oro empeñado (prendas en garantía) | C86: =$E$115 | D86: EUR | E86: =IF($B86="","",N($C86)*$F86) | F86: {=IF($D86="","",IFERROR(INDEX(Disponibilidad!$N$6:$N$9,MATCH($D86,Disponibilidad!$M$6:$M$9,0)),1))} | G86: Bien duradero | H86: Hogar | I86: Valor de mercado de las prendas empeñadas, calculado abajo. Siguen siendo tuyas mientras puedas rescatarlas, así que suman al activo; la deuda correspondiente está en el pasivo.
B87: Otros activos | C87: 2000 | D87: EUR | E87: =IF($B87="","",N($C87)*$F87) | F87: {=IF($D87="","",IFERROR(INDEX(Disponibilidad!$N$6:$N$9,MATCH($D87,Disponibilidad!$M$6:$M$9,0)),1))} | G87: Otro activo | H87: Hogar | I87: Detállalo cuando puedas: un "otros" de 2.000 € es difícil de verificar y de vender si lo necesitas.
D88: EUR | E88: =IF($B88="","",N($C88)*$F88) | F88: {=IF($D88="","",IFERROR(INDEX(Disponibilidad!$N$6:$N$9,MATCH($D88,Disponibilidad!$M$6:$M$9,0)),1))} | G88: Otro activo | H88: Hogar
B89: TOTAL BIENES E INMUEBLES | E89: =SUM($E$80:$E$88)
B91: DEUDA HIPOTECARIA
B92: Capital vivo pendiente de la hipoteca | C92: 71500 | I92: Lo que aún debes al banco hoy. Es el dato que hacía falta para que el balance dejara de estar incompleto.
B93: Cuota mensual | C93: 431 | I93: Coincide con el gasto de hipoteca de tu presupuesto.
B94: Tipo de interés anual | C94: =Resultados!$H$33 | I94: Se lee de la hoja Resultados. Cámbialo allí si no es el tuyo.
B95: Intereses estimados del próximo año | C95: =$C$92*$C$94 | I95: Capital vivo × tipo. Es una aproximación: el interés real baja cada mes según amortizas.
B96: Amortización estimada en los próximos 12 meses | C96: =MIN($C$92,MAX(0,$C$93*12-$C$95)) | I96: Lo que pagas en un año menos lo que se lleva el banco en intereses.
B97: Resto de capital a más de 12 meses | C97: =MAX(0,$C$92-$C$96)
B98: Años estimados hasta liquidarla | C98: =IFERROR(NPER($C$94/12,-$C$93,$C$92)/12,"") | I98: Al ritmo de cuota actual.
B99: Ratio préstamo/valor de la vivienda (LTV) | C99: =IFERROR($C$92/$E$80,"") | D99: =IF($C$99="","",IF($C$99<0.6,"✅",IF($C$99<0.8,"🟡","🔴"))) | I99: Por debajo del 80% es zona cómoda: si tuvieras que vender, el precio cubriría la deuda con margen.
B101: A) EMPEÑOS — detalle de las prendas de oro en garantía
B102: Las prendas empeñadas siguen siendo TUYAS: puedes recuperarlas pagando. Por eso el oro es un activo y la deuda un pasivo, cada uno en su sitio. La columna "Margen" te dice si compensa rescatar la prenda o dejarla perder. AQUÍ SOLO VAN EMPEÑOS: los préstamos de particulares están en el bloque B, justo debajo.
B103: Precio del oro de 18 quilates (€/gramo) | C103: 78 | I103: Referencia de preciodelorohoy.es a 24/07/2026: 86,13 €/g para oro de 18 k (750 milésimas), el estándar de la joyería española. Si tus piezas son de 14 k o 24 k, cambia este precio. Ojo: una casa de empeño nunca paga el precio de mercado, suele tasar bastante por debajo.
B104: Prenda empeñada | C104: Gramos | D104: Deuda pendiente (€) | E104: Valor estimado (€) | F104: Margen (€) | G104: Acreedor | H104: Ámbito | I104: Notas
B105: Anillo de 2,10 g | C105: 2.1 | D105: 199.79 | E105: =IF($C105="","",$C105*$C$103) | F105: =IF($B105="","",N($E105)-N($D105)) | G105: Quick Gold | H105: Hogar | I105: ⚠️ COMPROBAR: aquí figuran 2.004,42 € de capital y en Facturas hay 580,90 € de intereses de Quick Gold. Si las cifras de "se debe" que me diste ya incluían los intereses acumulados, estarías contando esa parte dos veces. Si son solo capital, está bien como está.
B106: Anillo de 2,45 g | C106: 2.45 | D106: 187 | E106: =IF($C106="","",$C106*$C$103) | F106: =IF($B106="","",N($E106)-N($D106)) | G106: CloverIntergold | H106: Hogar | I106: Coincide con la factura de CloverIntergold de 187,00 € que ya tienes registrada.
B107: Anillo de 3,50 g | C107: 3.5 | D107: 318.41 | E107: =IF($C107="","",$C107*$C$103) | F107: =IF($B107="","",N($E107)-N($D107)) | G107: Quick Gold | H107: Hogar
B108: Cadena de 11,56 g | C108: 11.56 | D108: 931.98 | E108: =IF($C108="","",$C108*$C$103) | F108: =IF($B108="","",N($E108)-N($D108)) | G108: Quick Gold | H108: Hogar | I108: La prenda de más peso y la que más debe: casi la mitad del total empeñado.
B109: Anillo de 6,04 g | C109: 6.04 | D109: 367.24 | E109: =IF($C109="","",$C109*$C$103) | F109: =IF($B109="","",N($E109)-N($D109)) | G109: Quick Gold | H109: Hogar
E110: =IF($C110="","",$C110*$C$103) | F110: =IF($B110="","",N($E110)-N($D110)) | H110: Hogar | I110: Fila libre para otra prenda. Si lo que quieres anotar es un préstamo de una persona, NO va aquí: créalo como factura con categoría "Préstamo particular".
E111: =IF($C111="","",$C111*$C$103) | F111: =IF($B111="","",N($E111)-N($D111)) | H111: Hogar
E112: =IF($C112="","",$C112*$C$103) | F112: =IF($B112="","",N($E112)-N($D112)) | H112: Hogar
E113: =IF($C113="","",$C113*$C$103) | F113: =IF($B113="","",N($E113)-N($D113)) | H113: Hogar
E114: =IF($C114="","",$C114*$C$103) | F114: =IF($B114="","",N($E114)-N($D114)) | H114: Hogar
B115: TOTAL EMPEÑADO (solo prendas en garantía) | C115: =SUM(C$105:C$114) | D115: =SUM(D$105:D$114) | E115: =SUM(E$105:E$114) | F115: =SUM(F$105:F$114)
B117: Deuda sobre el valor del oro | C117: =IFERROR($D$115/$E$115,"") | D117: =IF($C$117="","",IF($C$117<0.6,"✅",IF($C$117<0.85,"🟡","🔴"))) | I117: Cuánto debes por cada euro de oro que tienes empeñado. Cuanto más alto, menos sentido tiene rescatar la prenda.
...

Sheet PresupuestoReal
B1: PRESUPUESTO CONTRA REALIDAD
B2: Hasta ahora el presupuesto vivía en la hoja Escenarios y el gasto real en la hoja Caja, sin que nadie los enfrentara. Aquí se ven juntos: lo que dijiste que ibas a gastar y lo que gastaste de verdad, categoría a categoría. El mes se elige en el Panel. La columna "Real" se llena sola con los apuntes de Caja, así que solo funciona si registras los movimientos.
B4: Mes analizado | C4: =Panel!$I$4 | D4: Apuntes registrados ese mes | F4: =COUNTIFS(Caja!$K$6:$K$505,$C$4) | G4: =IF($F$4=0,"🔴 No hay ningún apunte de este mes en la hoja Caja: la columna Real saldrá a cero.",IF($F$4<10,"🟡 Solo "&$F$4&" apuntes: el mes está a medio registrar y la comparación engaña.","✅ Mes con datos suficientes para comparar."))
B6: A. INGRESOS
B7: Categoría | C7: Presupuesto (€/mes) | D7: REAL del mes (€) | E7: Desviación (€) | F7: % s/ppto | G7: Estado | H7: Nº de apuntes | I7: Acumulado del año (€) | J7: Notas
B8: Nómina y salarios | C8: 852.5 | D8: =SUMIFS(Caja!$H$6:$H$505,Caja!$K$6:$K$505,$C$4,Caja!$C$6:$C$505,"Cobro",Caja!$E$6:$E$505,$B8) | E8: =N($D8)-N($C8) | F8: =IFERROR($D8/$C8,"") | G8: =IF(N($C8)=0,IF(N($D8)=0,"—","✅ Extra"),IF($D8>=$C8,"✅ Cumplido",IF($D8>=$C8*0.9,"🟡 Casi","🔴 Por debajo"))) | H8: =COUNTIFS(Caja!$K$6:$K$505,$C$4,Caja!$C$6:$C$505,"Cobro",Caja!$E$6:$E$505,$B8) | I8: =SUMPRODUCT((LEFT(Caja!$K$6:$K$505,4)=TEXT(YEAR(TODAY()),"0"))*(Caja!$C$6:$C$505="Cobro")*(Caja!$E$6:$E$505=$B8)*Caja!$H$6:$H$505)
B9: Otros ingresos | C9: 339 | D9: =SUMIFS(Caja!$H$6:$H$505,Caja!$K$6:$K$505,$C$4,Caja!$C$6:$C$505,"Cobro",Caja!$E$6:$E$505,$B9) | E9: =N($D9)-N($C9) | F9: =IFERROR($D9/$C9,"") | G9: =IF(N($C9)=0,IF(N($D9)=0,"—","✅ Extra"),IF($D9>=$C9,"✅ Cumplido",IF($D9>=$C9*0.9,"🟡 Casi","🔴 Por debajo"))) | H9: =COUNTIFS(Caja!$K$6:$K$505,$C$4,Caja!$C$6:$C$505,"Cobro",Caja!$E$6:$E$505,$B9) | I9: =SUMPRODUCT((LEFT(Caja!$K$6:$K$505,4)=TEXT(YEAR(TODAY()),"0"))*(Caja!$C$6:$C$505="Cobro")*(Caja!$E$6:$E$505=$B9)*Caja!$H$6:$H$505)
B10: Intereses y dividendos | C10: 0 | D10: =SUMIFS(Caja!$H$6:$H$505,Caja!$K$6:$K$505,$C$4,Caja!$C$6:$C$505,"Cobro",Caja!$E$6:$E$505,$B10) | E10: =N($D10)-N($C10) | F10: =IFERROR($D10/$C10,"") | G10: =IF(N($C10)=0,IF(N($D10)=0,"—","✅ Extra"),IF($D10>=$C10,"✅ Cumplido",IF($D10>=$C10*0.9,"🟡 Casi","🔴 Por debajo"))) | H10: =COUNTIFS(Caja!$K$6:$K$505,$C$4,Caja!$C$6:$C$505,"Cobro",Caja!$E$6:$E$505,$B10) | I10: =SUMPRODUCT((LEFT(Caja!$K$6:$K$505,4)=TEXT(YEAR(TODAY()),"0"))*(Caja!$C$6:$C$505="Cobro")*(Caja!$E$6:$E$505=$B10)*Caja!$H$6:$H$505)
B11: Devoluciones y reembolsos | C11: 0 | D11: =SUMIFS(Caja!$H$6:$H$505,Caja!$K$6:$K$505,$C$4,Caja!$C$6:$C$505,"Cobro",Caja!$E$6:$E$505,$B11) | E11: =N($D11)-N($C11) | F11: =IFERROR($D11/$C11,"") | G11: =IF(N($C11)=0,IF(N($D11)=0,"—","✅ Extra"),IF($D11>=$C11,"✅ Cumplido",IF($D11>=$C11*0.9,"🟡 Casi","🔴 Por debajo"))) | H11: =COUNTIFS(Caja!$K$6:$K$505,$C$4,Caja!$C$6:$C$505,"Cobro",Caja!$E$6:$E$505,$B11) | I11: =SUMPRODUCT((LEFT(Caja!$K$6:$K$505,4)=TEXT(YEAR(TODAY()),"0"))*(Caja!$C$6:$C$505="Cobro")*(Caja!$E$6:$E$505=$B11)*Caja!$H$6:$H$505)
B12: Regalos recibidos | C12: 0 | D12: =SUMIFS(Caja!$H$6:$H$505,Caja!$K$6:$K$505,$C$4,Caja!$C$6:$C$505,"Cobro",Caja!$E$6:$E$505,$B12) | E12: =N($D12)-N($C12) | F12: =IFERROR($D12/$C12,"") | G12: =IF(N($C12)=0,IF(N($D12)=0,"—","✅ Extra"),IF($D12>=$C12,"✅ Cumplido",IF($D12>=$C12*0.9,"🟡 Casi","🔴 Por debajo"))) | H12: =COUNTIFS(Caja!$K$6:$K$505,$C$4,Caja!$C$6:$C$505,"Cobro",Caja!$E$6:$E$505,$B12) | I12: =SUMPRODUCT((LEFT(Caja!$K$6:$K$505,4)=TEXT(YEAR(TODAY()),"0"))*(Caja!$C$6:$C$505="Cobro")*(Caja!$E$6:$E$505=$B12)*Caja!$H$6:$H$505)
B13: TOTAL | C13: =SUM(C$8:C$12) | D13: =SUM(D$8:D$12) | E13: =SUM(E$8:E$12) | F13: =IFERROR($D13/$C13,"") | H13: =SUM($H$8:$H$12) | I13: =SUM(I$8:I$12)
B15: B. GASTOS
B16: Categoría | C16: Presupuesto (€/mes) | D16: REAL del mes (€) | E16: Desviación (€) | F16: % s/ppto | G16: Estado | H16: Nº de apuntes | I16: Acumulado del año (€) | J16: Notas
B17: Hipoteca | C17: 431 | D17: =SUMIFS(Caja!$H$6:$H$505,Caja!$K$6:$K$505,$C$4,Caja!$C$6:$C$505,"Pago",Caja!$E$6:$E$505,$B17) | E17: =N($D17)-N($C17) | F17: =IFERROR($D17/$C17,"") | G17: =IF(N($C17)=0,IF(N($D17)=0,"—","🟠 Sin presupuesto"),IF($D17<=$C17,"✅ Dentro",IF($D17<=$C17*1.1,"🟡 Ajustado","🔴 Pasado"))) | H17: =COUNTIFS(Caja!$K$6:$K$505,$C$4,Caja!$C$6:$C$505,"Pago",Caja!$E$6:$E$505,$B17) | I17: =SUMPRODUCT((LEFT(Caja!$K$6:$K$505,4)=TEXT(YEAR(TODAY()),"0"))*(Caja!$C$6:$C$505="Pago")*(Caja!$E$6:$E$505=$B17)*Caja!$H$6:$H$505)
B18: Alquiler / habitación | C18: 0 | D18: =SUMIFS(Caja!$H$6:$H$505,Caja!$K$6:$K$505,$C$4,Caja!$C$6:$C$505,"Pago",Caja!$E$6:$E$505,$B18) | E18: =N($D18)-N($C18) | F18: =IFERROR($D18/$C18,"") | G18: =IF(N($C18)=0,IF(N($D18)=0,"—","🟠 Sin presupuesto"),IF($D18<=$C18,"✅ Dentro",IF($D18<=$C18*1.1,"🟡 Ajustado","🔴 Pasado"))) | H18: =COUNTIFS(Caja!$K$6:$K$505,$C$4,Caja!$C$6:$C$505,"Pago",Caja!$E$6:$E$505,$B18) | I18: =SUMPRODUCT((LEFT(Caja!$K$6:$K$505,4)=TEXT(YEAR(TODAY()),"0"))*(Caja!$C$6:$C$505="Pago")*(Caja!$E$6:$E$505=$B18)*Caja!$H$6:$H$505)
B19: Agua | C19: 45 | D19: =SUMIFS(Caja!$H$6:$H$505,Caja!$K$6:$K$505,$C$4,Caja!$C$6:$C$505,"Pago",Caja!$E$6:$E$505,$B19) | E19: =N($D19)-N($C19) | F19: =IFERROR($D19/$C19,"") | G19: =IF(N($C19)=0,IF(N($D19)=0,"—","🟠 Sin presupuesto"),IF($D19<=$C19,"✅ Dentro",IF($D19<=$C19*1.1,"🟡 Ajustado","🔴 Pasado"))) | H19: =COUNTIFS(Caja!$K$6:$K$505,$C$4,Caja!$C$6:$C$505,"Pago",Caja!$E$6:$E$505,$B19) | I19: =SUMPRODUCT((LEFT(Caja!$K$6:$K$505,4)=TEXT(YEAR(TODAY()),"0"))*(Caja!$C$6:$C$505="Pago")*(Caja!$E$6:$E$505=$B19)*Caja!$H$6:$H$505)
B20: Luz | C20: 42 | D20: =SUMIFS(Caja!$H$6:$H$505,Caja!$K$6:$K$505,$C$4,Caja!$C$6:$C$505,"Pago",Caja!$E$6:$E$505,$B20) | E20: =N($D20)-N($C20) | F20: =IFERROR($D20/$C20,"") | G20: =IF(N($C20)=0,IF(N($D20)=0,"—","🟠 Sin presupuesto"),IF($D20<=$C20,"✅ Dentro",IF($D20<=$C20*1.1,"🟡 Ajustado","🔴 Pasado"))) | H20: =COUNTIFS(Caja!$K$6:$K$505,$C$4,Caja!$C$6:$C$505,"Pago",Caja!$E$6:$E$505,$B20) | I20: =SUMPRODUCT((LEFT(Caja!$K$6:$K$505,4)=TEXT(YEAR(TODAY()),"0"))*(Caja!$C$6:$C$505="Pago")*(Caja!$E$6:$E$505=$B20)*Caja!$H$6:$H$505)
B21: Gas | C21: 0 | D21: =SUMIFS(Caja!$H$6:$H$505,Caja!$K$6:$K$505,$C$4,Caja!$C$6:$C$505,"Pago",Caja!$E$6:$E$505,$B21) | E21: =N($D21)-N($C21) | F21: =IFERROR($D21/$C21,"") | G21: =IF(N($C21)=0,IF(N($D21)=0,"—","🟠 Sin presupuesto"),IF($D21<=$C21,"✅ Dentro",IF($D21<=$C21*1.1,"🟡 Ajustado","🔴 Pasado"))) | H21: =COUNTIFS(Caja!$K$6:$K$505,$C$4,Caja!$C$6:$C$505,"Pago",Caja!$E$6:$E$505,$B21) | I21: =SUMPRODUCT((LEFT(Caja!$K$6:$K$505,4)=TEXT(YEAR(TODAY()),"0"))*(Caja!$C$6:$C$505="Pago")*(Caja!$E$6:$E$505=$B21)*Caja!$H$6:$H$505)
B22: Comunidad | C22: 30 | D22: =SUMIFS(Caja!$H$6:$H$505,Caja!$K$6:$K$505,$C$4,Caja!$C$6:$C$505,"Pago",Caja!$E$6:$E$505,$B22) | E22: =N($D22)-N($C22) | F22: =IFERROR($D22/$C22,"") | G22: =IF(N($C22)=0,IF(N($D22)=0,"—","🟠 Sin presupuesto"),IF($D22<=$C22,"✅ Dentro",IF($D22<=$C22*1.1,"🟡 Ajustado","🔴 Pasado"))) | H22: =COUNTIFS(Caja!$K$6:$K$505,$C$4,Caja!$C$6:$C$505,"Pago",Caja!$E$6:$E$505,$B22) | I22: =SUMPRODUCT((LEFT(Caja!$K$6:$K$505,4)=TEXT(YEAR(TODAY()),"0"))*(Caja!$C$6:$C$505="Pago")*(Caja!$E$6:$E$505=$B22)*Caja!$H$6:$H$505)
B23: Telefonía y datos | C23: 90 | D23: =SUMIFS(Caja!$H$6:$H$505,Caja!$K$6:$K$505,$C$4,Caja!$C$6:$C$505,"Pago",Caja!$E$6:$E$505,$B23) | E23: =N($D23)-N($C23) | F23: =IFERROR($D23/$C23,"") | G23: =IF(N($C23)=0,IF(N($D23)=0,"—","🟠 Sin presupuesto"),IF($D23<=$C23,"✅ Dentro",IF($D23<=$C23*1.1,"🟡 Ajustado","🔴 Pasado"))) | H23: =COUNTIFS(Caja!$K$6:$K$505,$C$4,Caja!$C$6:$C$505,"Pago",Caja!$E$6:$E$505,$B23) | I23: =SUMPRODUCT((LEFT(Caja!$K$6:$K$505,4)=TEXT(YEAR(TODAY()),"0"))*(Caja!$C$6:$C$505="Pago")*(Caja!$E$6:$E$505=$B23)*Caja!$H$6:$H$505)
B24: Alimentación | C24: 345 | D24: =SUMIFS(Caja!$H$6:$H$505,Caja!$K$6:$K$505,$C$4,Caja!$C$6:$C$505,"Pago",Caja!$E$6:$E$505,$B24) | E24: =N($D24)-N($C24) | F24: =IFERROR($D24/$C24,"") | G24: =IF(N($C24)=0,IF(N($D24)=0,"—","🟠 Sin presupuesto"),IF($D24<=$C24,"✅ Dentro",IF($D24<=$C24*1.1,"🟡 Ajustado","🔴 Pasado"))) | H24: =COUNTIFS(Caja!$K$6:$K$505,$C$4,Caja!$C$6:$C$505,"Pago",Caja!$E$6:$E$505,$B24) | I24: =SUMPRODUCT((LEFT(Caja!$K$6:$K$505,4)=TEXT(YEAR(TODAY()),"0"))*(Caja!$C$6:$C$505="Pago")*(Caja!$E$6:$E$505=$B24)*Caja!$H$6:$H$505)
B25: Transporte | C25: 0 | D25: =SUMIFS(Caja!$H$6:$H$505,Caja!$K$6:$K$505,$C$4,Caja!$C$6:$C$505,"Pago",Caja!$E$6:$E$505,$B25) | E25: =N($D25)-N($C25) | F25: =IFERROR($D25/$C25,"") | G25: =IF(N($C25)=0,IF(N($D25)=0,"—","🟠 Sin presupuesto"),IF($D25<=$C25,"✅ Dentro",IF($D25<=$C25*1.1,"🟡 Ajustado","🔴 Pasado"))) | H25: =COUNTIFS(Caja!$K$6:$K$505,$C$4,Caja!$C$6:$C$505,"Pago",Caja!$E$6:$E$505,$B25) | I25: =SUMPRODUCT((LEFT(Caja!$K$6:$K$505,4)=TEXT(YEAR(TODAY()),"0"))*(Caja!$C$6:$C$505="Pago")*(Caja!$E$6:$E$505=$B25)*Caja!$H$6:$H$505)
B26: Taxi | C26: 0 | D26: =SUMIFS(Caja!$H$6:$H$505,Caja!$K$6:$K$505,$C$4,Caja!$C$6:$C$505,"Pago",Caja!$E$6:$E$505,$B26) | E26: =N($D26)-N($C26) | F26: =IFERROR($D26/$C26,"") | G26: =IF(N($C26)=0,IF(N($D26)=0,"—","🟠 Sin presupuesto"),IF($D26<=$C26,"✅ Dentro",IF($D26<=$C26*1.1,"🟡 Ajustado","🔴 Pasado"))) | H26: =COUNTIFS(Caja!$K$6:$K$505,$C$4,Caja!$C$6:$C$505,"Pago",Caja!$E$6:$E$505,$B26) | I26: =SUMPRODUCT((LEFT(Caja!$K$6:$K$505,4)=TEXT(YEAR(TODAY()),"0"))*(Caja!$C$6:$C$505="Pago")*(Caja!$E$6:$E$505=$B26)*Caja!$H$6:$H$505)
B27: Salud | C27: 0 | D27: =SUMIFS(Caja!$H$6:$H$505,Caja!$K$6:$K$505,$C$4,Caja!$C$6:$C$505,"Pago",Caja!$E$6:$E$505,$B27) | E27: =N($D27)-N($C27) | F27: =IFERROR($D27/$C27,"") | G27: =IF(N($C27)=0,IF(N($D27)=0,"—","🟠 Sin presupuesto"),IF($D27<=$C27,"✅ Dentro",IF($D27<=$C27*1.1,"🟡 Ajustado","🔴 Pasado"))) | H27: =COUNTIFS(Caja!$K$6:$K$505,$C$4,Caja!$C$6:$C$505,"Pago",Caja!$E$6:$E$505,$B27) | I27: =SUMPRODUCT((LEFT(Caja!$K$6:$K$505,4)=TEXT(YEAR(TODAY()),"0"))*(Caja!$C$6:$C$505="Pago")*(Caja!$E$6:$E$505=$B27)*Caja!$H$6:$H$505)
B28: Ropa | C28: 0 | D28: =SUMIFS(Caja!$H$6:$H$505,Caja!$K$6:$K$505,$C$4,Caja!$C$6:$C$505,"Pago",Caja!$E$6:$E$505,$B28) | E28: =N($D28)-N($C28) | F28: =IFERROR($D28/$C28,"") | G28: =IF(N($C28)=0,IF(N($D28)=0,"—","🟠 Sin presupuesto"),IF($D28<=$C28,"✅ Dentro",IF($D28<=$C28*1.1,"🟡 Ajustado","🔴 Pasado"))) | H28: =COUNTIFS(Caja!$K$6:$K$505,$C$4,Caja!$C$6:$C$505,"Pago",Caja!$E$6:$E$505,$B28) | I28: =SUMPRODUCT((LEFT(Caja!$K$6:$K$505,4)=TEXT(YEAR(TODAY()),"0"))*(Caja!$C$6:$C$505="Pago")*(Caja!$E$6:$E$505=$B28)*Caja!$H$6:$H$505)
... B41: Amortización de deuda | C41: 0 | D41: =SUMIFS(Caja!$H$6:$H$505,Caja!$K$6:$K$505,$C$4,Caja!$C$6:$C$505,"Pago",Caja!$E$6:$E$505,$B41) | E41: =N($D41)-N($C41) | F41: =IFERROR($D41/$C41,"") | G41: =IF(N($C41)=0,IF(N($D41)=0,"—","🟠 Sin presupuesto"),IF($D41<=$C41,"✅ Dentro",IF($D41<=$C41*1.1,"🟡 Ajustado","🔴 Pasado"))) | H41: =COUNTIFS(Caja!$K$6:$K$505,$C$4,Caja!$C$6:$C$505,"Pago",Caja!$E$6:$E$505,$B41) | I41: =SUMPRODUCT((LEFT(Caja!$K$6:$K$505,4)=TEXT(YEAR(TODAY()),"0"))*(Caja!$C$6:$C$505="Pago")*(Caja!$E$6:$E$505=$B41)*Caja!$H$6:$H$505)
B42: TOTAL | C42: =SUM(C$17:C$41) | D42: =SUM(D$17:D$41) | E42: =SUM(E$17:E$41) | F42: =IFERROR($D42/$C42,"") | H42: =SUM($H$17:$H$41) | I42: =SUM(I$17:I$41)
B44: C. LECTURA DEL MES
B45: =IF($F$4=0,"🕐 Aún no hay apuntes de este mes en la hoja Caja. Registra los cobros y pagos y esta hoja se llenará sola.","Presupuestaste "&TEXT($C$42,"#,##0.00")&" € de gasto y llevas "&TEXT($D$42,"#,##0.00")&" € registrados ("&TEXT($D$42/$C$42,"0%")&"). "&IF($E$42>0,"Vas "&TEXT($E$42,"#,##0.00")&" € POR ENCIMA del presupuesto.","Vas "&TEXT(ABS($E$42),"#,##0.00")&" € por debajo, aunque puede que el mes no esté completo todavía."))
B47: {=IF(COUNTIF($G$15:$G$41,"🔴 Pasado")=0,"✅ Ninguna categoría se ha pasado del presupuesto.","🔴 "&COUNTIF($G$15:$G$41,"🔴 Pasado")&" categorías se han pasado. La que más se desvía es "&INDEX($B$15:$B$41,MATCH(MAX($E$15:$E$41),$E$15:$E$41,0))&" con "&TEXT(MAX($E$15:$E$41),"#,##0.00")&" € de más.")}
B49: UN AVISO HONESTO: esta hoja solo vale lo que valga tu registro en Caja. Si apuntas la mitad de los gastos, te dirá que vas de maravilla. Coge la costumbre de anotar en cuanto pagas, aunque sea con el importe redondeado: un registro imperfecto pero constante vale mucho más que uno exacto que abandonas en tres semanas.

Sheet Facturas
B1: FACTURAS — pendientes, abonos y saldos
B2: Cada factura lleva su importe, lo que ya has abonado (pagos a cuenta, notas de abono o descuentos) y el SALDO que queda vivo. Todo el libro trabaja con el saldo, no con el importe original: así un pago parcial se refleja al instante en la tesorería y en el disponible.
P3: Marca aquí las facturas que quieres pagar primero. Aparecerán solas en la hoja Prioridad, ordenadas, y desaparecerán en cuanto su saldo llegue a cero.
A4: 1. REGISTRO — clasificado por categoría y fecha | J4: ← también puedes anotar el abono aquí a mano | R4: APLAZAMIENTOS — escribe la nueva fecha pactada en la columna R y, si el acreedor cobra recargo, anótalo en T. Todo el libro pasará a usar esa fecha. | AB4: Auxiliar | AF4: 2. SALDO PENDIENTE POR CATEGORÍA
A5: # | B5: Estado | C5: Proveedor / Emisor | D5: Categoría | E5: Concepto | F5: Nº de factura | G5: Fecha de emisión | H5: Fecha de vencimiento | I5: Importe de la factura (€) | J5: Abonado / pagado a cuenta (€) | K5: SALDO PENDIENTE (€) | L5: Cuenta de pago | M5: Días | N5: Urgencia | O5: Mes | P5: PRIORIDAD DE PAGO | Q5: Notas | R5: APLAZADA HASTA (nueva fecha) | S5: Motivo / acuerdo del aplazamiento | T5: Recargo por aplazar (€) | AA5: Clave de prioridad | AB5: Clave de orden | AC5: Ámbito | AD5: Pagado en Caja | AE5: Vencimiento efectivo | AF5: Categoría | AG5: Saldo pendiente (€) | AH5: Nº | AI5: % | AJ5: Visual
A6: =IF($C6="","",ROW()-5) | B6: Pagada | C6: Veolia | D6: Agua | E6: Factura del agua | F6: 981 215 990 | G6: 46205 | H6: 46219 | I6: 98.2 | J6: 98.2 | K6: =IF($C6="","",IF($B6="Pagada",0,ROUND(MAX(0,N($I6)+N($T6)-N($J6)-N($AD6)),2))) | L6: Revolut (corriente) | M6: =IF(OR($C6="",$AE6="",$K6=0),"",$AE6-TODAY()) | N6: =IF($C6="","",IF($K6=0,"✅ Saldada",IF($M6="","",IF($M6<0,IF(N($R6)>0,"🔴 APLAZADA VENCIDA","🔴 VENCIDA"),IF(N($R6)>0,"🕓 Aplazada",IF($M6<=3,"🟠 ≤3 días",IF($M6<=7,"🟡 ≤7 días",IF($M6<=30,"🔵 ≤30 días","⚪ >30 días")))))))) | O6: =IF($AE6="","",TEXT($AE6,"YYYY-MM")) | P6: 1 · Urgente | Q6: Ya la tenías: la he actualizado con los datos reales de la captura (nº 981 215 990, factura 02072026AN00029464, vencimiento 16/07/2026). NO la he duplicado. | AA6: =IF(OR($C6="",$K6=0,$P6=""),"",VALUE(LEFT($P6,1))*100000+N($M6)+ROW()/100000) | AB6: =IF(OR($C6="",$K6=0,$AE6=""),"",$M6+ROW()/100000) | AC6: {=IF($C6="","",IFERROR(INDEX(Disponibilidad!$O$6:$O$18,MATCH($L6,Disponibilidad!$B$6:$B$18,0)),"Hogar"))} | AD6: =IF($C6="","",SUMIFS(Caja!$H$6:$H$505,Caja!$J$6:$J$505,$A6,Caja!$C$6:$C$505,"Pago")) | AE6: =IF($C6="","",IF(N($R6)>0,$R6,$H6)) | AF6: Hipoteca | AG6: =SUMIFS($K$6:$K$205,$D$6:$D$205,$AF6) | AH6: =COUNTIFS($D$6:$D$205,$AF6,$K$6:$K$205,">0") | AI6: =IFERROR($AG6/$AG$20,"") | AJ6: =IF($AG6=0,"",REPT("█",MAX(1,ROUND($AG6/MAX($AG$6:$AG$19)*18,0))))
A7: =IF($C7="","",ROW()-5) | B7: Pendiente | C7: CaixaBank | D7: Tarjeta de crédito | E7: Cuota de la tarjeta | G7: 46223 | H7: 46234 | I7: 50 | J7: 50 | K7: =IF($C7="","",IF($B7="Pagada",0,ROUND(MAX(0,N($I7)+N($T7)-N($J7)-N($AD7)),2))) | L7: CaixaBank (corriente 9914) | M7: =IF(OR($C7="",$AE7="",$K7=0),"",$AE7-TODAY()) | N7: =IF($C7="","",IF($K7=0,"✅ Saldada",IF($M7="","",IF($M7<0,IF(N($R7)>0,"🔴 APLAZADA VENCIDA","🔴 VENCIDA"),IF(N($R7)>0,"🕓 Aplazada",IF($M7<=3,"🟠 ≤3 días",IF($M7<=7,"🟡 ≤7 días",IF($M7<=30,"🔵 ≤30 días","⚪ >30 días")))))))) | O7: =IF($AE7="","",TEXT($AE7,"YYYY-MM")) | P7: 1 · Urgente | Q7: MIGRADA de tu hoja "tesoreria". | AA7: =IF(OR($C7="",$K7=0,$P7=""),"",VALUE(LEFT($P7,1))*100000+N($M7)+ROW()/100000) | AB7: =IF(OR($C7="",$K7=0,$AE7=""),"",$M7+ROW()/100000) | AC7: {=IF($C7="","",IFERROR(INDEX(Disponibilidad!$O$6:$O$18,MATCH($L7,Disponibilidad!$B$6:$B$18,0)),"Hogar"))} | AD7: =IF($C7="","",SUMIFS(Caja!$H$6:$H$505,Caja!$J$6:$J$505,$A7,Caja!$C$6:$C$505,"Pago")) | AE7: =IF($C7="","",IF(N($R7)>0,$R7,$H7)) | AF7: Agua | AG7: =SUMIFS($K$6:$K$205,$D$6:$D$205,$AF7) | AH7: =COUNTIFS($D$6:$D$205,$AF7,$K$6:$K$205,">0") | AI7: =IFERROR($AG7/$AG$20,"") | AJ7: =IF($AG7=0,"",REPT("█",MAX(1,ROUND($AG7/MAX($AG$6:$AG$19)*18,0))))
A8: =IF($C8="","",ROW()-5) | B8: Pagada | C8: Agencia Tributaria | D8: Impuestos y hacienda | E8: Deuda de Hacienda | F8: A1585426100091075 | G8: 46213 | H8: 46239 | I8: 72.9 | J8: 72.9 | K8: =IF($C8="","",IF($B8="Pagada",0,ROUND(MAX(0,N($I8)+N($T8)-N($J8)-N($AD8)),2))) | L8: Revolut (corriente) | M8: =IF(OR($C8="",$AE8="",$K8=0),"",$AE8-TODAY()) | N8: =IF($C8="","",IF($K8=0,"✅ Saldada",IF($M8="","",IF($M8<0,IF(N($R8)>0,"🔴 APLAZADA VENCIDA","🔴 VENCIDA"),IF(N($R8)>0,"🕓 Aplazada",IF($M8<=3,"🟠 ≤3 días",IF($M8<=7,"🟡 ≤7 días",IF($M8<=30,"🔵 ≤30 días","⚪ >30 días")))))))) | O8: =IF($AE8="","",TEXT($AE8,"YYYY-MM")) | P8: 1 · Urgente | Q8: Ya la tenías: es la cuota de 08/2026 del fraccionamiento, expediente 152640329330L. NO la he duplicado; las siete cuotas siguientes están más abajo. | AA8: =IF(OR($C8="",$K8=0,$P8=""),"",VALUE(LEFT($P8,1))*100000+N($M8)+ROW()/100000) | AB8: =IF(OR($C8="",$K8=0,$AE8=""),"",$M8+ROW()/100000) | AC8: {=IF($C8="","",IFERROR(INDEX(Disponibilidad!$O$6:$O$18,MATCH($L8,Disponibilidad!$B$6:$B$18,0)),"Hogar"))} | AD8: =IF($C8="","",SUMIFS(Caja!$H$6:$H$505,Caja!$J$6:$J$505,$A8,Caja!$C$6:$C$505,"Pago")) | AE8: =IF($C8="","",IF(N($R8)>0,$R8,$H8)) | AF8: Luz | AG8: =SUMIFS($K$6:$K$205,$D$6:$D$205,$AF8) | AH8: =COUNTIFS($D$6:$D$205,$AF8,$K$6:$K$205,">0") | AI8: =IFERROR($AG8/$AG$20,"") | AJ8: =IF($AG8=0,"",REPT("█",MAX(1,ROUND($AG8/MAX($AG$6:$AG$19)*18,0))))
A9: =IF($C9="","",ROW()-5) | B9: Domiciliada | C9: Banco (hipoteca) | D9: Hipoteca | E9: Cuota mensual de la hipoteca | G9: 46235 | H9: 46235 | I9: 431 | J9: 0 | K9: =IF($C9="","",IF($B9="Pagada",0,ROUND(MAX(0,N($I9)+N($T9)-N($J9)-N($AD9)),2))) | L9: CaixaBank (corriente 9914) | M9: =IF(OR($C9="",$AE9="",$K9=0),"",$AE9-TODAY()) | N9: =IF($C9="","",IF($K9=0,"✅ Saldada",IF($M9="","",IF($M9<0,IF(N($R9)>0,"🔴 APLAZADA VENCIDA","🔴 VENCIDA"),IF(N($R9)>0,"🕓 Aplazada",IF($M9<=3,"🟠 ≤3 días",IF($M9<=7,"🟡 ≤7 días",IF($M9<=30,"🔵 ≤30 días","⚪ >30 días")))))))) | O9: =IF($AE9="","",TEXT($AE9,"YYYY-MM")) | Q9: SUPUESTO a partir del gasto de 431 € de tu presupuesto del hogar. Ajusta la fecha real de cargo. | AA9: =IF(OR($C9="",$K9=0,$P9=""),"",VALUE(LEFT($P9,1))*100000+N($M9)+ROW()/100000) | AB9: =IF(OR($C9="",$K9=0,$AE9=""),"",$M9+ROW()/100000) | AC9: {=IF($C9="","",IFERROR(INDEX(Disponibilidad!$O$6:$O$18,MATCH($L9,Disponibilidad!$B$6:$B$18,0)),"Hogar"))} | AD9: =IF($C9="","",SUMIFS(Caja!$H$6:$H$505,Caja!$J$6:$J$505,$A9,Caja!$C$6:$C$505,"Pago")) | AE9: =IF($C9="","",IF(N($R9)>0,$R9,$H9)) | AF9: Gas | AG9: =SUMIFS($K$6:$K$205,$D$6:$D$205,$AF9) | AH9: =COUNTIFS($D$6:$D$205,$AF9,$K$6:$K$205,">0") | AI9: =IFERROR($AG9/$AG$20,"") | AJ9: =IF($AG9=0,"",REPT("█",MAX(1,ROUND($AG9/MAX($AG$6:$AG$19)*18,0))))
A10: =IF($C10="","",ROW()-5) | B10: Pagada | C10: Supermercado | D10: Alimentación | E10: Compra del mes | G10: 46235 | H10: 46244 | I10: 345 | J10: 0 | K10: =IF($C10="","",IF($B10="Pagada",0,ROUND(MAX(0,N($I10)+N($T10)-N($J10)-N($AD10)),2))) | L10: CaixaBank (corriente 9914) | M10: =IF(OR($C10="",$AE10="",$K10=0),"",$AE10-TODAY()) | N10: =IF($C10="","",IF($K10=0,"✅ Saldada",IF($M10="","",IF($M10<0,IF(N($R10)>0,"🔴 APLAZADA VENCIDA","🔴 VENCIDA"),IF(N($R10)>0,"🕓 Aplazada",IF($M10<=3,"🟠 ≤3 días",IF($M10<=7,"🟡 ≤7 días",IF($M10<=30,"🔵 ≤30 días","⚪ >30 días")))))))) | O10: =IF($AE10="","",TEXT($AE10,"YYYY-MM")) | Q10: SUPUESTO: los 345 € de alimentación de tu presupuesto. | AA10: =IF(OR($C10="",$K10=0,$P10=""),"",VALUE(LEFT($P10,1))*100000+N($M10)+ROW()/100000) | AB10: =IF(OR($C10="",$K10=0,$AE10=""),"",$M10+ROW()/100000) | AC10: {=IF($C10="","",IFERROR(INDEX(Disponibilidad!$O$6:$O$18,MATCH($L10,Disponibilidad!$B$6:$B$18,0)),"Hogar"))} | AD10: =IF($C10="","",SUMIFS(Caja!$H$6:$H$505,Caja!$J$6:$J$505,$A10,Caja!$C$6:$C$505,"Pago")) | AE10: =IF($C10="","",IF(N($R10)>0,$R10,$H10)) | AF10: Comunidad | AG10: =SUMIFS($K$6:$K$205,$D$6:$D$205,$AF10) | AH10: =COUNTIFS($D$6:$D$205,$AF10,$K$6:$K$205,">0") | AI10: =IFERROR($AG10/$AG$20,"") | AJ10: =IF($AG10=0,"",REPT("█",MAX(1,ROUND($AG10/MAX($AG$6:$AG$19)*18,0))))
A11: =IF($C11="","",ROW()-5) | B11: Domiciliada | C11: Operadora | D11: Telefonía y datos | E11: Datos móviles e iPhone | G11: 46235 | H11: 46246 | I11: 90 | J11: 0 | K11: =IF($C11="","",IF($B11="Pagada",0,ROUND(MAX(0,N($I11)+N($T11)-N($J11)-N($AD11)),2))) | L11: CaixaBank (corriente 9914) | M11: =IF(OR($C11="",$AE11="",$K11=0),"",$AE11-TODAY()) | N11: =IF($C11="","",IF($K11=0,"✅ Saldada",IF($M11="","",IF($M11<0,IF(N($R11)>0,"🔴 APLAZADA VENCIDA","🔴 VENCIDA"),IF(N($R11)>0,"🕓 Aplazada",IF($M11<=3,"🟠 ≤3 días",IF($M11<=7,"🟡 ≤7 días",IF($M11<=30,"🔵 ≤30 días","⚪ >30 días")))))))) | O11: =IF($AE11="","",TEXT($AE11,"YYYY-MM")) | Q11: SUPUESTO: los 90 € de tu presupuesto. | AA11: =IF(OR($C11="",$K11=0,$P11=""),"",VALUE(LEFT($P11,1))*100000+N($M11)+ROW()/100000) | AB11: =IF(OR($C11="",$K11=0,$AE11=""),"",$M11+ROW()/100000) | AC11: {=IF($C11="","",IFERROR(INDEX(Disponibilidad!$O$6:$O$18,MATCH($L11,Disponibilidad!$B$6:$B$18,0)),"Hogar"))} | AD11: =IF($C11="","",SUMIFS(Caja!$H$6:$H$505,Caja!$J$6:$J$505,$A11,Caja!$C$6:$C$505,"Pago")) | AE11: =IF($C11="","",IF(N($R11)>0,$R11,$H11)) | AF11: Telefonía y datos | AG11: =SUMIFS($K$6:$K$205,$D$6:$D$205,$AF11) | AH11: =COUNTIFS($D$6:$D$205,$AF11,$K$6:$K$205,">0") | AI11: =IFERROR($AG11/$AG$20,"") | AJ11: =IF($AG11=0,"",REPT("█",MAX(1,ROUND($AG11/MAX($AG$6:$AG$19)*18,0))))
A12: =IF($C12="","",ROW()-5) | B12: Pendiente | C12: Compañía eléctrica | D12: Luz | E12: Factura de la luz | G12: 46239 | H12: 46252 | I12: 112.76 | J12: 0 | K12: =IF($C12="","",IF($B12="Pagada",0,ROUND(MAX(0,N($I12)+N($T12)-N($J12)-N($AD12)),2))) | L12: CaixaBank (corriente 9914) | M12: =IF(OR($C12="",$AE12="",$K12=0),"",$AE12-TODAY()) | N12: =IF($C12="","",IF($K12=0,"✅ Saldada",IF($M12="","",IF($M12<0,IF(N($R12)>0,"🔴 APLAZADA VENCIDA","🔴 VENCIDA"),IF(N($R12)>0,"🕓 Aplazada",IF($M12<=3,"🟠 ≤3 días",IF($M12<=7,"🟡 ≤7 días",IF($M12<=30,"🔵 ≤30 días","⚪ >30 días")))))))) | O12: =IF($AE12="","",TEXT($AE12,"YYYY-MM")) | Q12: ⚠️ Esta la inventé yo como supuesto. Ahora tienes las facturas REALES de Iberdrola (90,97 · 74,58 · 41,79 de gas). Bórrala para no contar la luz dos veces. | AA12: =IF(OR($C12="",$K12=0,$P12=""),"",VALUE(LEFT($P12,1))*100000+N($M12)+ROW()/100000) | AB12: =IF(OR($C12="",$K12=0,$AE12=""),"",$M12+ROW()/100000) | AC12: {=IF($C12="","",IFERROR(INDEX(Disponibilidad!$O$6:$O$18,MATCH($L12,Disponibilidad!$B$6:$B$18,0)),"Hogar"))} | AD12: =IF($C12="","",SUMIFS(Caja!$H$6:$H$505,Caja!$J$6:$J$505,$A12,Caja!$C$6:$C$505,"Pago")) | AE12: =IF($C12="","",IF(N($R12)>0,$R12,$H12)) | AF12: Alimentación | AG12: =SUMIFS($K$6:$K$205,$D$6:$D$205,$AF12) | AH12: =COUNTIFS($D$6:$D$205,$AF12,$K$6:$K$205,">0") | AI12: =IFERROR($AG12/$AG$20,"") | AJ12: =IF($AG12=0,"",REPT("█",MAX(1,ROUND($AG12/MAX($AG$6:$AG$19)*18,0))))
A13: =IF($C13="","",ROW()-5) | B13: Domiciliada | C13: Comunidad de propietarios | D13: Comunidad | E13: Cuota de comunidad | G13: 46235 | H13: 46254 | I13: 30 | J13: 0 | K13: =IF($C13="","",IF($B13="Pagada",0,ROUND(MAX(0,N($I13)+N($T13)-N($J13)-N($AD13)),2))) | L13: CaixaBank (corriente 9914) | M13: =IF(OR($C13="",$AE13="",$K13=0),"",$AE13-TODAY()) | N13: =IF($C13="","",IF($K13=0,"✅ Saldada",IF($M13="","",IF($M13<0,IF(N($R13)>0,"🔴 APLAZADA VENCIDA","🔴 VENCIDA"),IF(N($R13)>0,"🕓 Aplazada",IF($M13<=3,"🟠 ≤3 días",IF($M13<=7,"🟡 ≤7 días",IF($M13<=30,"🔵 ≤30 días","⚪ >30 días")))))))) | O13: =IF($AE13="","",TEXT($AE13,"YYYY-MM")) | Q13: ⚠️ Supuesto mío. Ahora tienes las nueve facturas REALES de Comunidad Capitol de 30 € cada una. Bórrala. | AA13: =IF(OR($C13="",$K13=0,$P13=""),"",VALUE(LEFT($P13,1))*100000+N($M13)+ROW()/100000) | AB13: =IF(OR($C13="",$K13=0,$AE13=""),"",$M13+ROW()/100000) | AC13: {=IF($C13="","",IFERROR(INDEX(Disponibilidad!$O$6:$O$18,MATCH($L13,Disponibilidad!$B$6:$B$18,0)),"Hogar"))} | AD13: =IF($C13="","",SUMIFS(Caja!$H$6:$H$505,Caja!$J$6:$J$505,$A13,Caja!$C$6:$C$505,"Pago")) | AE13: =IF($C13="","",IF(N($R13)>0,$R13,$H13)) | AF13: Tarjeta de crédito | AG13: =SUMIFS($K$6:$K$205,$D$6:$D$205,$AF13) | AH13: =COUNTIFS($D$6:$D$205,$AF13,$K$6:$K$205,">0") | AI13: =IFERROR($AG13/$AG$20,"") | AJ13: =IF($AG13=0,"",REPT("█",MAX(1,ROUND($AG13/MAX($AG$6:$AG$19)*18,0))))
A14: =IF($C14="","",ROW()-5) | B14: Pagada | C14: Bank of Ireland | D14: Tarjeta de crédito | E14: Pago mínimo Mastercard | G14: 46235 | H14: 46254 | I14: 150 | J14: 0 | K14: =IF($C14="","",IF($B14="Pagada",0,ROUND(MAX(0,N($I14)+N($T14)-N($J14)-N($AD14)),2))) | L14: Bank of Ireland (nómina) | M14: =IF(OR($C14="",$AE14="",$K14=0),"",$AE14-TODAY()) | N14: =IF($C14="","",IF($K14=0,"✅ Saldada",IF($M14="","",IF($M14<0,IF(N($R14)>0,"🔴 APLAZADA VENCIDA","🔴 VENCIDA"),IF(N($R14)>0,"🕓 Aplazada",IF($M14<=3,"🟠 ≤3 días",IF($M14<=7,"🟡 ≤7 días",IF($M14<=30,"🔵 ≤30 días","⚪ >30 días")))))))) | O14: =IF($AE14="","",TEXT($AE14,"YYYY-MM")) | Q14: SUPUESTO. Saldo de 4.990,64 € al 22,8% según tu libro de finanzas personales. | AA14: =IF(OR($C14="",$K14=0,$P14=""),"",VALUE(LEFT($P14,1))*100000+N($M14)+ROW()/100000) | AB14: =IF(OR($C14="",$K14=0,$AE14=""),"",$M14+ROW()/100000) | AC14: {=IF($C14="","",IFERROR(INDEX(Disponibilidad!$O$6:$O$18,MATCH($L14,Disponibilidad!$B$6:$B$18,0)),"Hogar"))} | AD14: =IF($C14="","",SUMIFS(Caja!$H$6:$H$505,Caja!$J$6:$J$505,$A14,Caja!$C$6:$C$505,"Pago")) | AE14: =IF($C14="","",IF(N($R14)>0,$R14,$H14)) | AF14: Impuestos y hacienda | AG14: =SUMIFS($K$6:$K$205,$D$6:$D$205,$AF14) | AH14: =COUNTIFS($D$6:$D$205,$AF14,$K$6:$K$205,">0") | AI14: =IFERROR($AG14/$AG$20,"") | AJ14: =IF($AG14=0,"",REPT("█",MAX(1,ROUND($AG14/MAX($AG$6:$AG$19)*18,0))))
A15: =IF($C15="","",ROW()-5) | B15: Pendiente | C15: Quick Gold | D15: Intereses de empeño | E15: Intereses del empeño — lote 5658R | F15: 5658R | H15: 46230 | I15: 357.7 | J15: 0 | K15: =IF($C15="","",IF($B15="Pagada",0,ROUND(MAX(0,N($I15)+N($T15)-N($J15)-N($AD15)),2))) | L15: CaixaBank (corriente 9914) | M15: =IF(OR($C15="",$AE15="",$K15=0),"",$AE15-TODAY()) | N15: =IF($C15="","",IF($K15=0,"✅ Saldada",IF($M15="","",IF($M15<0,IF(N($R15)>0,"🔴 APLAZADA VENCIDA","🔴 VENCIDA"),IF(N($R15)>0,"🕓 Aplazada",IF($M15<=3,"🟠 ≤3 días",IF($M15<=7,"🟡 ≤7 días",IF($M15<=30,"🔵 ≤30 días","⚪ >30 días")))))))) | O15: =IF($AE15="","",TEXT($AE15,"YYYY-MM")) | Q15: Intereses por el empeño, no devolución de capital: por eso van a gastos financieros del Estado de Resultados y NO se descuentan del pasivo por facturas del Balance. Transcrita de la captura de HomeBank del 30/07/2026. Notas del origen: "intereses…" (texto cortado en la captura). | AA15: =IF(OR($C15="",$K15=0,$P15=""),"",VALUE(LEFT($P15,1))*100000+N($M15)+ROW()/100000) | AB15: =IF(OR($C15="",$K15=0,$AE15=""),"",$M15+ROW()/100000) | AC15: {=IF($C15="","",IFERROR(INDEX(Disponibilidad!$O$6:$O$18,MATCH($L15,Disponibilidad!$B$6:$B$18,0)),"Hogar"))} | AD15: =IF($C15="","",SUMIFS(Caja!$H$6:$H$505,Caja!$J$6:$J$505,$A15,Caja!$C$6:$C$505,"Pago")) | AE15: =IF($C15="","",IF(N($R15)>0,$R15,$H15)) | AF15: Empeño | AG15: =SUMIFS($K$6:$K$205,$D$6:$D$205,$AF15) | AH15: =COUNTIFS($D$6:$D$205,$AF15,$K$6:$K$205,">0") | AI15: =IFERROR($AG15/$AG$20,"") | AJ15: =IF($AG15=0,"",REPT("█",MAX(1,ROUND($AG15/MAX($AG$6:$AG$19)*18,0))))
A16: =IF($C16="","",ROW()-5) | B16: Pendiente | C16: CloverIntergold | D16: Empeño | E16: Pago del préstamo — LOTE R855 | F16: LOTE R855 | H16: 46245 | I16: 187 | J16: 0 | K16: =IF($C16="","",IF($B16="Pagada",0,ROUND(MAX(0,N($I16)+N($T16)-N($J16)-N($AD16)),2))) | L16: CaixaBank (corriente 9914) | M16: =IF(OR($C16="",$AE16="",$K16=0),"",$AE16-TODAY()) | N16: =IF($C16="","",IF($K16=0,"✅ Saldada",IF($M16="","",IF($M16<0,IF(N($R16)>0,"🔴 APLAZADA VENCIDA","🔴 VENCIDA"),IF(N($R16)>0,"🕓 Aplazada",IF($M16<=3,"🟠 ≤3 días",IF($M16<=7,"🟡 ≤7 días",IF($M16<=30,"🔵 ≤30 días","⚪ >30 días")))))))) | O16: =IF($AE16="","",TEXT($AE16,"YYYY-MM")) | P16: 3 · Media | Q16: Transcrita de la captura de HomeBank del 30/07/2026. Notas del origen: "Monto tot…". | AA16: =IF(OR($C16="",$K16=0,$P16=""),"",VALUE(LEFT($P16,1))*100000+N($M16)+ROW()/100000) | AB16: =IF(OR($C16="",$K16=0,$AE16=""),"",$M16+ROW()/100000) | AC16: {=IF($C16="","",IFERROR(INDEX(Disponibilidad!$O$6:$O$18,MATCH($L16,Disponibilidad!$B$6:$B$18,0)),"Hogar"))} | AD16: =IF($C16="","",SUMIFS(Caja!$H$6:$H$505,Caja!$J$6:$J$505,$A16,Caja!$C$6:$C$505,"Pago")) | AE16: =IF($C16="","",IF(N($R16)>0,$R16,$H16)) | AF16: Préstamo particular | AG16: =SUMIFS($K$6:$K$205,$D$6:$D$205,$AF16) | AH16: =COUNTIFS($D$6:$D$205,$AF16,$K$6:$K$205,">0") | AI16: =IFERROR($AG16/$AG$20,"") | AJ16: =IF($AG16=0,"",REPT("█",MAX(1,ROUND($AG16/MAX($AG$6:$AG$19)*18,0))))
A17: =IF($C17="","",ROW()-5) | B17: Pendiente | C17: Quick Gold | D17: Intereses de empeño | E17: Intereses del empeño — lote 005659 | F17: lote 005659 | H17: 46275 | I17: 114.45 | J17: 0 | K17: =IF($C17="","",IF($B17="Pagada",0,ROUND(MAX(0,N($I17)+N($T17)-N($J17)-N($AD17)),2))) | L17: CaixaBank (corriente 9914) | M17: =IF(OR($C17="",$AE17="",$K17=0),"",$AE17-TODAY()) | N17: =IF($C17="","",IF($K17=0,"✅ Saldada",IF($M17="","",IF($M17<0,IF(N($R17)>0,"🔴 APLAZADA VENCIDA","🔴 VENCIDA"),IF(N($R17)>0,"🕓 Aplazada",IF($M17<=3,"🟠 ≤3 días",IF($M17<=7,"🟡 ≤7 días",IF($M17<=30,"🔵 ≤30 días","⚪ >30 días")))))))) | O17: =IF($AE17="","",TEXT($AE17,"YYYY-MM")) | Q17: Intereses por el empeño, no devolución de capital: por eso van a gastos financieros del Estado de Resultados y NO se descuentan del pasivo por facturas del Balance. Transcrita de la captura de HomeBank del 30/07/2026. | AA17: =IF(OR($C17="",$K17=0,$P17=""),"",VALUE(LEFT($P17,1))*100000+N($M17)+ROW()/100000) | AB17: =IF(OR($C17="",$K17=0,$AE17=""),"",$M17+ROW()/100000) | AC17: {=IF($C17="","",IFERROR(INDEX(Disponibilidad!$O$6:$O$18,MATCH($L17,Disponibilidad!$B$6:$B$18,0)),"Hogar"))} | AD17: =IF($C17="","",SUMIFS(Caja!$H$6:$H$505,Caja!$J$6:$J$505,$A17,Caja!$C$6:$C$505,"Pago")) | AE17: =IF($C17="","",IF(N($R17)>0,$R17,$H17)) | AF17: Crédito comercial | AG17: =SUMIFS($K$6:$K$205,$D$6:$D$205,$AF17) | AH17: =COUNTIFS($D$6:$D$205,$AF17,$K$6:$K$205,">0") | AI17: =IFERROR($AG17/$AG$20,"") | AJ17: =IF($AG17=0,"",REPT("█",MAX(1,ROUND($AG17/MAX($AG$6:$AG$19)*18,0))))
A18: =IF($C18="","",ROW()-5) | B18: Pendiente | C18: Iberdrola | D18: Luz | E18: Factura de electricidad | F18: 212042201000008197 | H18: 46197 | I18: 90.97 | J18: 0 | K18: =IF($C18="","",IF($B18="Pagada",0,ROUND(MAX(0,N($I18)+N($T18)-N($J18)-N($AD18)),2))) | L18: CaixaBank (corriente 9914) | M18: =IF(OR($C18="",$AE18="",$K18=0),"",$AE18-TODAY()) | N18: =IF($C18="","",IF($K18=0,"✅ Saldada",IF($M18="","",IF($M18<0,IF(N($R18)>0,"🔴 APLAZADA VENCIDA","🔴 VENCIDA"),IF(N($R18)>0,"🕓 Aplazada",IF($M18<=3,"🟠 ≤3 días",IF($M18<=7,"🟡 ≤7 días",IF($M18<=30,"🔵 ≤30 días","⚪ >30 días")))))))) | O18: =IF($AE18="","",TEXT($AE18,"YYYY-MM")) | Q18: Transcrita de la captura de HomeBank del 30/07/2026. Contrato 316970245. | AA18: =IF(OR($C18="",$K18=0,$P18=""),"",VALUE(LEFT($P18,1))*100000+N($M18)+ROW()/100000) | AB18: =IF(OR($C18="",$K18=0,$AE18=""),"",$M18+ROW()/100000) | AC18: {=IF($C18="","",IFERROR(INDEX(Disponibilidad!$O$6:$O$18,MATCH($L18,Disponibilidad!$B$6:$B$18,0)),"Hogar"))} | AD18: =IF($C18="","",SUMIFS(Caja!$H$6:$H$505,Caja!$J$6:$J$505,$A18,Caja!$C$6:$C$505,"Pago")) | AE18: =IF($C18="","",IF(N($R18)>0,$R18,$H18)) | AF18: Intereses de empeño | AG18: =SUMIFS($K$6:$K$205,$D$6:$D$205,$AF18) | AH18: =COUNTIFS($D$6:$D$205,$AF18,$K$6:$K$205,">0") | AI18: =IFERROR($AG18/$AG$20,"") | AJ18: =IF($AG18=0,"",REPT("█",MAX(1,ROUND($AG18/MAX($AG$6:$AG$19)*18,0))))
A19: =IF($C19="","",ROW()-5) | B19: Pagada | C19: Lowie | D19: Otros | E19: Servicio (categoría de origen: "Billetes:Servicio de…") | F19: julio 2026 | H19: 46230 | I19: 85.26 | J19: 85.26 | K19: =IF($C19="","",IF($B19="Pagada",0,ROUND(MAX(0,N($I19)+N($T19)-N($J19)-N($AD19)),2))) | L19: CaixaBank (corriente 9914) | M19: =IF(OR($C19="",$AE19="",$K19=0),"",$AE19-TODAY()) | N19: =IF($C19="","",IF($K19=0,"✅ Saldada",IF($M19="","",IF($M19<0,IF(N($R19)>0,"🔴 APLAZADA VENCIDA","🔴 VENCIDA"),IF(N($R19)>0,"🕓 Aplazada",IF($M19<=3,"🟠 ≤3 días",IF($M19<=7,"🟡 ≤7 días",IF($M19<=30,"🔵 ≤30 días","⚪ >30 días")))))))) | O19: =IF($AE19="","",TEXT($AE19,"YYYY-MM")) | Q19: ⚠️ En la captura esta línea lleva la marca de CONCILIADA, por eso la he puesto como Pagada y no suma al pendiente. Si aún la debes, cámbiala a Pendiente. Notas del origen: "Promesa…". | AA19: =IF(OR($C19="",$K19=0,$P19=""),"",VALUE(LEFT($P19,1))*100000+N($M19)+ROW()/100000) | AB19: =IF(OR($C19="",$K19=0,$AE19=""),"",$M19+ROW()/100000) | AC19: {=IF($C19="","",IFERROR(INDEX(Disponibilidad!$O$6:$O$18,MATCH($L19,Disponibilidad!$B$6:$B$18,0)),"Hogar"))} | AD19: =IF($C19="","",SUMIFS(Caja!$H$6:$H$505,Caja!$J$6:$J$505,$A19,Caja!$C$6:$C$505,"Pago")) | AE19: =IF($C19="","",IF(N($R19)>0,$R19,$H19)) | AF19: Otros | AG19: =SUMIFS($K$6:$K$205,$D$6:$D$205,$AF19) | AH19: =COUNTIFS($D$6:$D$205,$AF19,$K$6:$K$205,">0") | AI19: =IFERROR($AG19/$AG$20,"") | AJ19: =IF($AG19=0,"",REPT("█",MAX(1,ROUND($AG19/MAX($AG$6:$AG$19)*18,0))))
A20: =IF($C20="","",ROW()-5) | B20: Pendiente | C20: Veolia (Viaqua) | D20: Agua | E20: Factura de agua y alcantarillado | F20: 2-2026 | H20: 46158 | I20: 84.14 | J20: 0 | K20: =IF($C20="","",IF($B20="Pagada",0,ROUND(MAX(0,N($I20)+N($T20)-N($J20)-N($AD20)),2))) | L20: CaixaBank (corriente 9914) | M20: =IF(OR($C20="",$AE20="",$K20=0),"",$AE20-TODAY()) | N20: =IF($C20="","",IF($K20=0,"✅ Saldada",IF($M20="","",IF($M20<0,IF(N($R20)>0,"🔴 APLAZADA VENCIDA","🔴 VENCIDA"),IF(N($R20)>0,"🕓 Aplazada",IF($M20<=3,"🟠 ≤3 días",IF($M20<=7,"🟡 ≤7 días",IF($M20<=30,"🔵 ≤30 días","⚪ >30 días")))))))) | O20: =IF($AE20="","",TEXT($AE20,"YYYY-MM")) | Q20: Transcrita de la captura de HomeBank del 30/07/2026. Notas del origen: "factura co…". | AA20: =IF(OR($C20="",$K20=0,$P20=""),"",VALUE(LEFT($P20,1))*100000+N($M20)+ROW()/100000) | AB20: =IF(OR($C20="",$K20=0,$AE20=""),"",$M20+ROW()/100000) | AC20: {=IF($C20="","",IFERROR(INDEX(Disponibilidad!$O$6:$O$18,MATCH($L20,Disponibilidad!$B$6:$B$18,0)),"Hogar"))} | AD20: =IF($C20="","",SUMIFS(Caja!$H$6:$H$505,Caja!$J$6:$J$505,$A20,Caja!$C$6:$C$505,"Pago")) | AE20: =IF($C20="","",IF(N($R20)>0,$R20,$H20)) | AF20: SALDO PENDIENTE TOTAL | AG20: =SUM($AG$6:$AG$19) | AH20: =SUM($AH$6:$AH$19) | AI20: =IF($AG$20=0,"",1)
A21: =IF($C21="","",ROW()-5) | B21: Pendiente | C21: Agencia Tributaria | D21: Impuestos y hacienda | E21: Fraccionamiento — cuota 09/2026 | F21: A1585426100091075 | H21: 46272 | I21: 76.48 | J21: 0 | K21: =IF($C21="","",IF($B21="Pagada",0,ROUND(MAX(0,N($I21)+N($T21)-N($J21)-N($AD21)),2))) | L21: CaixaBank (corriente 9914) | M21: =IF(OR($C21="",$AE21="",$K21=0),"",$AE21-TODAY()) | N21: =IF($C21="","",IF($K21=0,"✅ Saldada",IF($M21="","",IF($M21<0,IF(N($R21)>0,"🔴 APLAZADA VENCIDA","🔴 VENCIDA"),IF(N($R21)>0,"🕓 Aplazada",IF($M21<=3,"🟠 ≤3 días",IF($M21<=7,"🟡 ≤7 días",IF($M21<=30,"🔵 ≤30 días","⚪ >30 días")))))))) | O21: =IF($AE21="","",TEXT($AE21,"YYYY-MM")) | Q21: Expediente 152640329330L. Transcrita de la captura de HomeBank del 30/07/2026. | AA21: =IF(OR($C21="",$K21=0,$P21=""),"",VALUE(LEFT($P21,1))*100000+N($M21)+ROW()/100000) | AB21: =IF(OR($C21="",$K21=0,$AE21=""),"",$M21+ROW()/100000) | AC21: {=IF($C21="","",IFERROR(INDEX(Disponibilidad!$O$6:$O$18,MATCH($L21,Disponibilidad!$B$6:$B$18,0)),"Hogar"))} | AD21: =IF($C21="","",SUMIFS(Caja!$H$6:$H$505,Caja!$J$6:$J$505,$A21,Caja!$C$6:$C$505,"Pago")) | AE21: =IF($C21="","",IF(N($R21)>0,$R21,$H21)) | AF21: ⚠️ Facturas con una categoría que NO está en esta lista (no suman arriba) | AG21: =ROUND(SUM($K$6:$K$205)-$AG$20,2) | AH21: =IF(ROUND($AG$21,2)=0,"✅ Todas clasificadas","🔴 Revisa la columna Categoría") | AK21: Son 14 categorías fijas. "Préstamos y empeños" se ha partido en "Empeño" (prendas de oro) y "Préstamo particular" (dinero que te han prestado personas). "Seguros" y "Transporte", que no usabas, se han reutilizado. Si necesitas otra, renombra una que no uses y las fórmulas la siguen solas.
A22: =IF($C22="","",ROW()-5) | B22: Pendiente | C22: Agencia Tributaria | D22: Impuestos y hacienda | E22: Fraccionamiento — cuota 10/2026 | F22: A1585426100091075 | H22: 46300 | I22: 76.48 | J22: 0 | K22: =IF($C22="","",IF($B22="Pagada",0,ROUND(MAX(0,N($I22)+N($T22)-N($J22)-N($AD22)),2))) | L22: CaixaBank (corriente 9914) | M22: =IF(OR($C22="",$AE22="",$K22=0),"",$AE22-TODAY()) | N22: =IF($C22="","",IF($K22=0,"✅ Saldada",IF($M22="","",IF($M22<0,IF(N($R22)>0,"🔴 APLAZADA VENCIDA","🔴 VENCIDA"),IF(N($R22)>0,"🕓 Aplazada",IF($M22<=3,"🟠 ≤3 días",IF($M22<=7,"🟡 ≤7 días",IF($M22<=30,"🔵 ≤30 días","⚪ >30 días")))))))) | O22: =IF($AE22="","",TEXT($AE22,"YYYY-MM")) | Q22: Expediente 152640329330L. | AA22: =IF(OR($C22="",$K22=0,$P22=""),"",VALUE(LEFT($P22,1))*100000+N($M22)+ROW()/100000) | AB22: =IF(OR($C22="",$K22=0,$AE22=""),"",$M22+ROW()/100000) | AC22: {=IF($C22="","",IFERROR(INDEX(Disponibilidad!$O$6:$O$18,MATCH($L22,Disponibilidad!$B$6:$B$18,0)),"Hogar"))} | AD22: =IF($C22="","",SUMIFS(Caja!$H$6:$H$505,Caja!$J$6:$J$505,$A22,Caja!$C$6:$C$505,"Pago")) | AE22: =IF($C22="","",IF(N($R22)>0,$R22,$H22)) | AF22: 3. URGENCIA DEL SALDO
A23: =IF($C23="","",ROW()-5) | B23: Pendiente | C23: Agencia Tributaria | D23: Impuestos y hacienda | E23: Fraccionamiento — cuota 11/2026 | F23: A1585426100091075 | H23: 46331 | I23: 76.48 | J23: 0 | K23: =IF($C23="","",IF($B23="Pagada",0,ROUND(MAX(0,N($I23)+N($T23)-N($J23)-N($AD23)),2))) | L23: CaixaBank (corriente 9914) | M23: =IF(OR($C23="",$AE23="",$K23=0),"",$AE23-TODAY()) | N23: =IF($C23="","",IF($K23=0,"✅ Saldada",IF($M23="","",IF($M23<0,IF(N($R23)>0,"🔴 APLAZADA VENCIDA","🔴 VENCIDA"),IF(N($R23)>0,"🕓 Aplazada",IF($M23<=3,"🟠 ≤3 días",IF($M23<=7,"🟡 ≤7 días",IF($M23<=30,"🔵 ≤30 días","⚪ >30 días")))))))) | O23: =IF($AE23="","",TEXT($AE23,"YYYY-MM")) | Q23: Expediente 152640329330L. | AA23: =IF(OR($C23="",$K23=0,$P23=""),"",VALUE(LEFT($P23,1))*100000+N($M23)+ROW()/100000) | AB23: =IF(OR($C23="",$K23=0,$AE23=""),"",$M23+ROW()/100000) | AC23: {=IF($C23="","",IFERROR(INDEX(Disponibilidad!$O$6:$O$18,MATCH($L23,Disponibilidad!$B$6:$B$18,0)),"Hogar"))} | AD23: =IF($C23="","",SUMIFS(Caja!$H$6:$H$505,Caja!$J$6:$J$505,$A23,Caja!$C$6:$C$505,"Pago")) | AE23: =IF($C23="","",IF(N($R23)>0,$R23,$H23)) | AF23: Tramo | AG23: Saldo (€) | AH23: Nº | AI23: % | AJ23: Visual
A24: =IF($C24="","",ROW()-5) | B24: Pendiente | C24: Agencia Tributaria | D24: Impuestos y hacienda | E24: Fraccionamiento — cuota 12/2026 | F24: A1585426100091075 | H24: 46363 | I24: 76.48 | J24: 0 | K24: =IF($C24="","",IF($B24="Pagada",0,ROUND(MAX(0,N($I24)+N($T24)-N($J24)-N($AD24)),2))) | L24: CaixaBank (corriente 9914) | M24: =IF(OR($C24="",$AE24="",$K24=0),"",$AE24-TODAY()) | N24: =IF($C24="","",IF($K24=0,"✅ Saldada",IF($M24="","",IF($M24<0,IF(N($R24)>0,"🔴 APLAZADA VENCIDA","🔴 VENCIDA"),IF(N($R24)>0,"🕓 Aplazada",IF($M24<=3,"🟠 ≤3 días",IF($M24<=7,"🟡 ≤7 días",IF($M24<=30,"🔵 ≤30 días","⚪ >30 días")))))))) | O24: =IF($AE24="","",TEXT($AE24,"YYYY-MM")) | Q24: Expediente 152640329330L. | AA24: =IF(OR($C24="",$K24=0,$P24=""),"",VALUE(LEFT($P24,1))*100000+N($M24)+ROW()/100000) | AB24: =IF(OR($C24="",$K24=0,$AE24=""),"",$M24+ROW()/100000) | AC24: {=IF($C24="","",IFERROR(INDEX(Disponibilidad!$O$6:$O$18,MATCH($L24,Disponibilidad!$B$6:$B$18,0)),"Hogar"))} | AD24: =IF($C24="","",SUMIFS(Caja!$H$6:$H$505,Caja!$J$6:$J$505,$A24,Caja!$C$6:$C$505,"Pago")) | AE24: =IF($C24="","",IF(N($R24)>0,$R24,$H24)) | AF24: 🔴 Vencidas | AG24: =SUMIFS($K$6:$K$205,$M$6:$M$205,"<0") | AH24: =COUNTIFS($M$6:$M$205,"<0",$K$6:$K$205,">0") | AI24: =IFERROR($AG24/$AG$20,"") | AJ24: =IF($AG24=0,"",REPT("█",MAX(1,ROUND($AG24/MAX($AG$24:$AG$27)*18,0))))
A25: =IF($C25="","",ROW()-5) | B25: Pendiente | C25: Agencia Tributaria | D25: Impuestos y hacienda | E25: Fraccionamiento — cuota 01/2027 | F25: A1585426100091075 | H25: 46392 | I25: 76.48 | J25: 0 | K25: =IF($C25="","",IF($B25="Pagada",0,ROUND(MAX(0,N($I25)+N($T25)-N($J25)-N($AD25)),2))) | L25: CaixaBank (corriente 9914) | M25: =IF(OR($C25="",$AE25="",$K25=0),"",$AE25-TODAY()) | N25: =IF($C25="","",IF($K25=0,"✅ Saldada",IF($M25="","",IF($M25<0,IF(N($R25)>0,"🔴 APLAZADA VENCIDA","🔴 VENCIDA"),IF(N($R25)>0,"🕓 Aplazada",IF($M25<=3,"🟠 ≤3 días",IF($M25<=7,"🟡 ≤7 días",IF($M25<=30,"🔵 ≤30 días","⚪ >30 días")))))))) | O25: =IF($AE25="","",TEXT($AE25,"YYYY-MM")) | Q25: Expediente 152640329330L. | AA25: =IF(OR($C25="",$K25=0,$P25=""),"",VALUE(LEFT($P25,1))*100000+N($M25)+ROW()/100000) | AB25: =IF(OR($C25="",$K25=0,$AE25=""),"",$M25+ROW()/100000) | AC25: {=IF($C25="","",IFERROR(INDEX(Disponibilidad!$O$6:$O$18,MATCH($L25,Disponibilidad!$B$6:$B$18,0)),"Hogar"))} | AD25: =IF($C25="","",SUMIFS(Caja!$H$6:$H$505,Caja!$J$6:$J$505,$A25,Caja!$C$6:$C$505,"Pago")) | AE25: =IF($C25="","",IF(N($R25)>0,$R25,$H25)) | AF25: 🟠 Vencen en 7 días o menos | AG25: =SUMIFS($K$6:$K$205,$M$6:$M$205,">=0",$M$6:$M$205,"<=7") | AH25: =COUNTIFS($M$6:$M$205,">=0",$M$6:$M$205,"<=7",$K$6:$K$205,">0") | AI25: =IFERROR($AG25/$AG$20,"") | AJ25: =IF($AG25=0,"",REPT("█",MAX(1,ROUND($AG25/MAX($AG$24:$AG$27)*18,0))))
A26: =IF($C26="","",ROW()-5) | B26: Pendiente | C26: Agencia Tributaria | D26: Impuestos y hacienda | E26: Fraccionamiento — cuota 02/2027 | F26: A1585426100091075 | H26: 46423 | I26: 76.48 | J26: 0 | K26: =IF($C26="","",IF($B26="Pagada",0,ROUND(MAX(0,N($I26)+N($T26)-N($J26)-N($AD26)),2))) | L26: CaixaBank (corriente 9914) | M26: =IF(OR($C26="",$AE26="",$K26=0),"",$AE26-TODAY()) | N26: =IF($C26="","",IF($K26=0,"✅ Saldada",IF($M26="","",IF($M26<0,IF(N($R26)>0,"🔴 APLAZADA VENCIDA","🔴 VENCIDA"),IF(N($R26)>0,"🕓 Aplazada",IF($M26<=3,"🟠 ≤3 días",IF($M26<=7,"🟡 ≤7 días",IF($M26<=30,"🔵 ≤30 días","⚪ >30 días")))))))) | O26: =IF($AE26="","",TEXT($AE26,"YYYY-MM")) | Q26: Expediente 152640329330L. | AA26: =IF(OR($C26="",$K26=0,$P26=""),"",VALUE(LEFT($P26,1))*100000+N($M26)+ROW()/100000) | AB26: =IF(OR($C26="",$K26=0,$AE26=""),"",$M26+ROW()/100000) | AC26: {=IF($C26="","",IFERROR(INDEX(Disponibilidad!$O$6:$O$18,MATCH($L26,Disponibilidad!$B$6:$B$18,0)),"Hogar"))} | AD26: =IF($C26="","",SUMIFS(Caja!$H$6:$H$505,Caja!$J$6:$J$505,$A26,Caja!$C$6:$C$505,"Pago")) | AE26: =IF($C26="","",IF(N($R26)>0,$R26,$H26)) | AF26: 🔵 Entre 8 y 30 días | AG26: =SUMIFS($K$6:$K$205,$M$6:$M$205,">=8",$M$6:$M$205,"<=30") | AH26: =COUNTIFS($M$6:$M$205,">=8",$M$6:$M$205,"<=30",$K$6:$K$205,">0") | AI26: =IFERROR($AG26/$AG$20,"") | AJ26: =IF($AG26=0,"",REPT("█",MAX(1,ROUND($AG26/MAX($AG$24:$AG$27)*18,0))))
A27: =IF($C27="","",ROW()-5) | B27: Pendiente | C27: Agencia Tributaria | D27: Impuestos y hacienda | E27: Fraccionamiento — cuota 03/2027 | F27: A1585426100091075 | H27: 46451 | I27: 76.48 | J27: 0 | K27: =IF($C27="","",IF($B27="Pagada",0,ROUND(MAX(0,N($I27)+N($T27)-N($J27)-N($AD27)),2))) | L27: CaixaBank (corriente 9914) | M27: =IF(OR($C27="",$AE27="",$K27=0),"",$AE27-TODAY()) | N27: =IF($C27="","",IF($K27=0,"✅ Saldada",IF($M27="","",IF($M27<0,IF(N($R27)>0,"🔴 APLAZADA VENCIDA","🔴 VENCIDA"),IF(N($R27)>0,"🕓 Aplazada",IF($M27<=3,"🟠 ≤3 días",IF($M27<=7,"🟡 ≤7 días",IF($M27<=30,"🔵 ≤30 días","⚪ >30 días")))))))) | O27: =IF($AE27="","",TEXT($AE27,"YYYY-MM")) | Q27: Expediente 152640329330L. | AA27: =IF(OR($C27="",$K27=0,$P27=""),"",VALUE(LEFT($P27,1))*100000+N($M27)+ROW()/100000) | AB27: =IF(OR($C27="",$K27=0,$AE27=""),"",$M27+ROW()/100000) | AC27: {=IF($C27="","",IFERROR(INDEX(Disponibilidad!$O$6:$O$18,MATCH($L27,Disponibilidad!$B$6:$B$18,0)),"Hogar"))} | AD27: =IF($C27="","",SUMIFS(Caja!$H$6:$H$505,Caja!$J$6:$J$505,$A27,Caja!$C$6:$C$505,"Pago")) | AE27: =IF($C27="","",IF(N($R27)>0,$R27,$H27)) | AF27: ⚪ En más de 30 días | AG27: =SUMIFS($K$6:$K$205,$M$6:$M$205,">30") | AH27: =COUNTIFS($M$6:$M$205,">30",$K$6:$K$205,">0") | AI27: =IFERROR($AG27/$AG$20,"") | AJ27: =IF($AG27=0,"",REPT("█",MAX(1,ROUND($AG27/MAX($AG$24:$AG$27)*18,0))))
A28: =IF($C28="","",ROW()-5) | B28: Pagada | C28: Iberdrola | D28: Luz | E28: Factura de electricidad — 357 kWh | F28: 21260525010009364 | H28: 46220 | I28: 74.58 | J28: 74.58 | K28: =IF($C28="","",IF($B28="Pagada",0,ROUND(MAX(0,N($I28)+N($T28)-N($J28)-N($AD28)),2))) | L28: CaixaBank (corriente 9914) | M28: =IF(OR($C28="",$AE28="",$K28=0),"",$AE28-TODAY()) | N28: =IF($C28="","",IF($K28=0,"✅ Saldada",IF($M28="","",IF($M28<0,IF(N($R28)>0,"🔴 APLAZADA VENCIDA","🔴 VENCIDA"),IF(N($R28)>0,"🕓 Aplazada",IF($M28<=3,"🟠 ≤3 días",IF($M28<=7,"🟡 ≤7 días",IF($M28<=30,"🔵 ≤30 días","⚪ >30 días")))))))) | O28: =IF($AE28="","",TEXT($AE28,"YYYY-MM")) | Q28: ⚠️ En la captura lleva la marca de CONCILIADA, por eso va como Pagada. Contrato 316970245. 357 kWh. | AA28: =IF(OR($C28="",$K28=0,$P28=""),"",VALUE(LEFT($P28,1))*100000+N($M28)+ROW()/100000) | AB28: =IF(OR($C28="",$K28=0,$AE28=""),"",$M28+ROW()/100000) | AC28: {=IF($C28="","",IFERROR(INDEX(Disponibilidad!$O$6:$O$18,MATCH($L28,Disponibilidad!$B$6:$B$18,0)),"Hogar"))} | AD28: =IF($C28="","",SUMIFS(Caja!$H$6:$H$505,Caja!$J$6:$J$505,$A28,Caja!$C$6:$C$505,"Pago")) | AE28: =IF($C28="","",IF(N($R28)>0,$R28,$H28))
A29: =IF($C29="","",ROW()-5) | B29: Pendiente | C29: Imagin Crédito (CaixaBank) | D29: Crédito comercial | E29: Pago mensual del crédito | F29: Recurrente | H29: 46204 | I29: 50 | J29: 0 | K29: =IF($C29="","",IF($B29="Pagada",0,ROUND(MAX(0,N($I29)+N($T29)-N($J29)-N($AD29)),2))) | L29: CaixaBank (corriente 9914) | M29: =IF(OR($C29="",$AE29="",$K29=0),"",$AE29-TODAY()) | N29: =IF($C29="","",IF($K29=0,"✅ Saldada",IF($M29="","",IF($M29<0,IF(N($R29)>0,"🔴 APLAZADA VENCIDA","🔴 VENCIDA"),IF(N($R29)>0,"🕓 Aplazada",IF($M29<=3,"🟠 ≤3 días",IF($M29<=7,"🟡 ≤7 días",IF($M29<=30,"🔵 ≤30 días","⚪ >30 días")))))))) | O29: =IF($AE29="","",TEXT($AE29,"YYYY-MM")) | Q29: ⚠️ Revisa si se solapa con la fila "CaixaBank · Cuota de la tarjeta · 60,00 €" que ya tenías: podrían ser el mismo recibo con distinto importe. Transcrita de la captura de HomeBank del 30/07/2026. | AA29: =IF(OR($C29="",$K29=0,$P29=""),"",VALUE(LEFT($P29,1))*100000+N($M29)+ROW()/100000) | AB29: =IF(OR($C29="",$K29=0,$AE29=""),"",$M29+ROW()/100000) | AC29: {=IF($C29="","",IFERROR(INDEX(Disponibilidad!$O$6:$O$18,MATCH($L29,Disponibilidad!$B$6:$B$18,0)),"Hogar"))} | AD29: =IF($C29="","",SUMIFS(Caja!$H$6:$H$505,Caja!$J$6:$J$505,$A29,Caja!$C$6:$C$505,"Pago")) | AE29: =IF($C29="","",IF(N($R29)>0,$R29,$H29)) | AF29: 4. ABONOS Y SALDOS
A30: =IF($C30="","",ROW()-5) | B30: Pendiente | C30: Quick Gold | D30: Intereses de empeño | E30: Intereses del empeño — lote 004503 | F30: lote 004503 | H30: 46275 | I30: 45.1 | J30: 0 | K30: =IF($C30="","",IF($B30="Pagada",0,ROUND(MAX(0,N($I30)+N($T30)-N($J30)-N($AD30)),2))) | L30: CaixaBank (corriente 9914) | M30: =IF(OR($C30="",$AE30="",$K30=0),"",$AE30-TODAY()) | N30: =IF($C30="","",IF($K30=0,"✅ Saldada",IF($M30="","",IF($M30<0,IF(N($R30)>0,"🔴 APLAZADA VENCIDA","🔴 VENCIDA"),IF(N($R30)>0,"🕓 Aplazada",IF($M30<=3,"🟠 ≤3 días",IF($M30<=7,"🟡 ≤7 días",IF($M30<=30,"🔵 ≤30 días","⚪ >30 días")))))))) | O30: =IF($AE30="","",TEXT($AE30,"YYYY-MM")) | Q30: Intereses por el empeño, no devolución de capital: por eso van a gastos financieros del Estado de Resultados y NO se descuentan del pasivo por facturas del Balance. Transcrita de la captura de HomeBank del 30/07/2026. | AA30: =IF(OR($C30="",$K30=0,$P30=""),"",VALUE(LEFT($P30,1))*100000+N($M30)+ROW()/100000) | AB30: =IF(OR($C30="",$K30=0,$AE30=""),"",$M30+ROW()/100000) | AC30: {=IF($C30="","",IFERROR(INDEX(Disponibilidad!$O$6:$O$18,MATCH($L30,Disponibilidad!$B$6:$B$18,0)),"Hogar"))} | AD30: =IF($C30="","",SUMIFS(Caja!$H$6:$H$505,Caja!$J$6:$J$505,$A30,Caja!$C$6:$C$505,"Pago")) | AE30: =IF($C30="","",IF(N($R30)>0,$R30,$H30)) | AF30: Concepto | AG30: Importe (€) | AH30: Nº | AI30: % | AJ30: Visual
A31: =IF($C31="","",ROW()-5) | B31: Pendiente | C31: Iberdrola | D31: Gas | E31: Factura de gas natural | F31: 21260710010269250 | H31: 46164 | I31: 41.79 | J31: 0 | K31: =IF($C31="","",IF($B31="Pagada",0,ROUND(MAX(0,N($I31)+N($T31)-N($J31)-N($AD31)),2))) | L31: CaixaBank (corriente 9914) | M31: =IF(OR($C31="",$AE31="",$K31=0),"",$AE31-TODAY()) | N31: =IF($C31="","",IF($K31=0,"✅ Saldada",IF($M31="","",IF($M31<0,IF(N($R31)>0,"🔴 APLAZADA VENCIDA","🔴 VENCIDA"),IF(N($R31)>0,"🕓 Aplazada",IF($M31<=3,"🟠 ≤3 días",IF($M31<=7,"🟡 ≤7 días",IF($M31<=30,"🔵 ≤30 días","⚪ >30 días")))))))) | O31: =IF($AE31="","",TEXT($AE31,"YYYY-MM")) | Q31: Nº de contrato 1062486277. Transcrita de la captura de HomeBank del 30/07/2026. | AA31: =IF(OR($C31="",$K31=0,$P31=""),"",VALUE(LEFT($P31,1))*100000+N($M31)+ROW()/100000) | AB31: =IF(OR($C31="",$K31=0,$AE31=""),"",$M31+ROW()/100000) | AC31: {=IF($C31="","",IFERROR(INDEX(Disponibilidad!$O$6:$O$18,MATCH($L31,Disponibilidad!$B$6:$B$18,0)),"Hogar"))} | AD31: =IF($C31="","",SUMIFS(Caja!$H$6:$H$505,Caja!$J$6:$J$505,$A31,Caja!$C$6:$C$505,"Pago")) | AE31: =IF($C31="","",IF(N($R31)>0,$R31,$H31)) | AF31: Total facturado | AG31: =SUM($I$6:$I$205) | AH31: =COUNTIFS($I$6:$I$205,">0")
A32: =IF($C32="","",ROW()-5) | B32: Pendiente | C32: Quick Gold | D32: Intereses de empeño | E32: Intereses del empeño — lote 006258 | F32: lote 006258 | H32: 46290 | I32: 39.11 | J32: 0 | K32: =IF($C32="","",IF($B32="Pagada",0,ROUND(MAX(0,N($I32)+N($T32)-N($J32)-N($AD32)),2))) | L32: CaixaBank (corriente 9914) | M32: =IF(OR($C32="",$AE32="",$K32=0),"",$AE32-TODAY()) | N32: =IF($C32="","",IF($K32=0,"✅ Saldada",IF($M32="","",IF($M32<0,IF(N($R32)>0,"🔴 APLAZADA VENCIDA","🔴 VENCIDA"),IF(N($R32)>0,"🕓 Aplazada",IF($M32<=3,"🟠 ≤3 días",IF($M32<=7,"🟡 ≤7 días",IF($M32<=30,"🔵 ≤30 días","⚪ >30 días")))))))) | O32: =IF($AE32="","",TEXT($AE32,"YYYY-MM")) | Q32: Intereses por el empeño, no devolución de capital: por eso van a gastos financieros del Estado de Resultados y NO se descuentan del pasivo por facturas del Balance. Transcrita de la captura de HomeBank del 30/07/2026. | AA32: =IF(OR($C32="",$K32=0,$P32=""),"",VALUE(LEFT($P32,1))*100000+N($M32)+ROW()/100000) | AB32: =IF(OR($C32="",$K32=0,$AE32=""),"",$M32+ROW()/100000) | AC32: {=IF($C32="","",IFERROR(INDEX(Disponibilidad!$O$6:$O$18,MATCH($L32,Disponibilidad!$B$6:$B$18,0)),"Hogar"))} | AD32: =IF($C32="","",SUMIFS(Caja!$H$6:$H$505,Caja!$J$6:$J$505,$A32,Caja!$C$6:$C$505,"Pago")) | AE32: =IF($C32="","",IF(N($R32)>0,$R32,$H32)) | AF32: Total ya abonado | AG32: =SUM($I$6:$I$205)-SUM($K$6:$K$205) | AH32: =COUNTIFS($J$6:$J$205,">0")
A33: =IF($C33="","",ROW()-5) | B33: Pendiente | C33: Comunidad Capitol | D33: Comunidad | E33: Limpieza de comunidad — factura 001 | F33: 001 | H33: 45991 | I33: 30 | J33: 0 | K33: =IF($C33="","",IF($B33="Pagada",0,ROUND(MAX(0,N($I33)+N($T33)-N($J33)-N($AD33)),2))) | L33: CaixaBank (corriente 9914) | M33: =IF(OR($C33="",$AE33="",$K33=0),"",$AE33-TODAY()) | N33: =IF($C33="","",IF($K33=0,"✅ Saldada",IF($M33="","",IF($M33<0,IF(N($R33)>0,"🔴 APLAZADA VENCIDA","🔴 VENCIDA"),IF(N($R33)>0,"🕓 Aplazada",IF($M33<=3,"🟠 ≤3 días",IF($M33<=7,"🟡 ≤7 días",IF($M33<=30,"🔵 ≤30 días","⚪ >30 días")))))))) | O33: =IF($AE33="","",TEXT($AE33,"YYYY-MM")) | P33: 1 · Urgente | Q33: Transcrita de la captura de HomeBank del 30/07/2026. | AA33: =IF(OR($C33="",$K33=0,$P33=""),"",VALUE(LEFT($P33,1))*100000+N($M33)+ROW()/100000) | AB33: =IF(OR($C33="",$K33=0,$AE33=""),"",$M33+ROW()/100000) | AC33: {=IF($C33="","",IFERROR(INDEX(Disponibilidad!$O$6:$O$18,MATCH($L33,Disponibilidad!$B$6:$B$18,0)),"Hogar"))} | AD33: =IF($C33="","",SUMIFS(Caja!$H$6:$H$505,Caja!$J$6:$J$505,$A33,Caja!$C$6:$C$505,"Pago")) | AE33: =IF($C33="","",IF(N($R33)>0,$R33,$H33)) | AF33: SALDO PENDIENTE | AG33: =$AG$20 | AH33: =COUNTIFS($K$6:$K$205,">0")
A34: =IF($C34="","",ROW()-5) | B34: Pendiente | C34: Comunidad Capitol | D34: Comunidad | E34: Limpieza de comunidad — factura 002 | F34: 002 | H34: 46022 | I34: 30 | J34: 0 | K34: =IF($C34="","",IF($B34="Pagada",0,ROUND(MAX(0,N($I34)+N($T34)-N($J34)-N($AD34)),2))) | L34: CaixaBank (corriente 9914) | M34: =IF(OR($C34="",$AE34="",$K34=0),"",$AE34-TODAY()) | N34: =IF($C34="","",IF($K34=0,"✅ Saldada",IF($M34="","",IF($M34<0,IF(N($R34)>0,"🔴 APLAZADA VENCIDA","🔴 VENCIDA"),IF(N($R34)>0,"🕓 Aplazada",IF($M34<=3,"🟠 ≤3 días",IF($M34<=7,"🟡 ≤7 días",IF($M34<=30,"🔵 ≤30 días","⚪ >30 días")))))))) | O34: =IF($AE34="","",TEXT($AE34,"YYYY-MM")) | P34: 1 · Urgente | Q34: Transcrita de la captura de HomeBank del 30/07/2026. | AA34: =IF(OR($C34="",$K34=0,$P34=""),"",VALUE(LEFT($P34,1))*100000+N($M34)+ROW()/100000) | AB34: =IF(OR($C34="",$K34=0,$AE34=""),"",$M34+ROW()/100000) | AC34: {=IF($C34="","",IFERROR(INDEX(Disponibilidad!$O$6:$O$18,MATCH($L34,Disponibilidad!$B$6:$B$18,0)),"Hogar"))} | AD34: =IF($C34="","",SUMIFS(Caja!$H$6:$H$505,Caja!$J$6:$J$505,$A34,Caja!$C$6:$C$505,"Pago")) | AE34: =IF($C34="","",IF(N($R34)>0,$R34,$H34)) | AF34: Facturas con abono parcial | AH34: =SUMPRODUCT(($J$6:$J$205>0)*($K$6:$K$205>0))
A35: =IF($C35="","",ROW()-5) | B35: Pendiente | C35: Comunidad Capitol | D35: Comunidad | E35: Limpieza de comunidad — factura 003 | F35: 003 | H35: 46053 | I35: 30 | J35: 0 | K35: =IF($C35="","",IF($B35="Pagada",0,ROUND(MAX(0,N($I35)+N($T35)-N($J35)-N($AD35)),2))) | L35: CaixaBank (corriente 9914) | M35: =IF(OR($C35="",$AE35="",$K35=0),"",$AE35-TODAY()) | N35: =IF($C35="","",IF($K35=0,"✅ Saldada",IF($M35="","",IF($M35<0,IF(N($R35)>0,"🔴 APLAZADA VENCIDA","🔴 VENCIDA"),IF(N($R35)>0,"🕓 Aplazada",IF($M35<=3,"🟠 ≤3 días",IF($M35<=7,"🟡 ≤7 días",IF($M35<=30,"🔵 ≤30 días","⚪ >30 días")))))))) | O35: =IF($AE35="","",TEXT($AE35,"YYYY-MM")) | P35: 1 · Urgente | Q35: Transcrita de la captura de HomeBank del 30/07/2026. | AA35: =IF(OR($C35="",$K35=0,$P35=""),"",VALUE(LEFT($P35,1))*100000+N($M35)+ROW()/100000) | AB35: =IF(OR($C35="",$K35=0,$AE35=""),"",$M35+ROW()/100000) | AC35: {=IF($C35="","",IFERROR(INDEX(Disponibilidad!$O$6:$O$18,MATCH($L35,Disponibilidad!$B$6:$B$18,0)),"Hogar"))} | AD35: =IF($C35="","",SUMIFS(Caja!$H$6:$H$505,Caja!$J$6:$J$505,$A35,Caja!$C$6:$C$505,"Pago")) | AE35: =IF($C35="","",IF(N($R35)>0,$R35,$H35)) | AF35: Facturas totalmente saldadas | AH35: =SUMPRODUCT(($C$6:$C$205<>"")*($K$6:$K$205=0))
A36: =IF($C36="","",ROW()-5) | B36: Pendiente | C36: Comunidad Capitol | D36: Comunidad | E36: Limpieza de comunidad — factura 005 | F36: 005 | H36: 46112 | I36: 30 | J36: 0 | K36: =IF($C36="","",IF($B36="Pagada",0,ROUND(MAX(0,N($I36)+N($T36)-N($J36)-N($AD36)),2))) | L36: CaixaBank (corriente 9914) | M36: =IF(OR($C36="",$AE36="",$K36=0),"",$AE36-TODAY()) | N36: =IF($C36="","",IF($K36=0,"✅ Saldada",IF($M36="","",IF($M36<0,IF(N($R36)>0,"🔴 APLAZADA VENCIDA","🔴 VENCIDA"),IF(N($R36)>0,"🕓 Aplazada",IF($M36<=3,"🟠 ≤3 días",IF($M36<=7,"🟡 ≤7 días",IF($M36<=30,"🔵 ≤30 días","⚪ >30 días")))))))) | O36: =IF($AE36="","",TEXT($AE36,"YYYY-MM")) | P36: 1 · Urgente | Q36: Transcrita de la captura de HomeBank del 30/07/2026. | AA36: =IF(OR($C36="",$K36=0,$P36=""),"",VALUE(LEFT($P36,1))*100000+N($M36)+ROW()/100000) | AB36: =IF(OR($C36="",$K36=0,$AE36=""),"",$M36+ROW()/100000) | AC36: {=IF($C36="","",IFERROR(INDEX(Disponibilidad!$O$6:$O$18,MATCH($L36,Disponibilidad!$B$6:$B$18,0)),"Hogar"))} | AD36: =IF($C36="","",SUMIFS(Caja!$H$6:$H$505,Caja!$J$6:$J$505,$A36,Caja!$C$6:$C$505,"Pago")) | AE36: =IF($C36="","",IF(N($R36)>0,$R36,$H36)) | AF36: % abonado sobre el total facturado | AG36: =IFERROR($AG$32/$AG$31,"") | AJ36: =IF($AG$36="","",REPT("█",MAX(0,ROUND($AG$36*18,0)))&REPT("░",18-MAX(0,ROUND($AG$36*18,0))))
A37: =IF($C37="","",ROW()-5) | B37: Pendiente | C37: Comunidad Capitol | D37: Comunidad | E37: Limpieza de comunidad — factura 006 | F37: 006 | H37: 46142 | I37: 30 | J37: 0 | K37: =IF($C37="","",IF($B37="Pagada",0,ROUND(MAX(0,N($I37)+N($T37)-N($J37)-N($AD37)),2))) | L37: CaixaBank (corriente 9914) | M37: =IF(OR($C37="",$AE37="",$K37=0),"",$AE37-TODAY()) | N37: =IF($C37="","",IF($K37=0,"✅ Saldada",IF($M37="","",IF($M37<0,IF(N($R37)>0,"🔴 APLAZADA VENCIDA","🔴 VENCIDA"),IF(N($R37)>0,"🕓 Aplazada",IF($M37<=3,"🟠 ≤3 días",IF($M37<=7,"🟡 ≤7 días",IF($M37<=30,"🔵 ≤30 días","⚪ >30 días")))))))) | O37: =IF($AE37="","",TEXT($AE37,"YYYY-MM")) | P37: 1 · Urgente | Q37: Transcrita de la captura de HomeBank del 30/07/2026. | AA37: =IF(OR($C37="",$K37=0,$P37=""),"",VALUE(LEFT($P37,1))*100000+N($M37)+ROW()/100000) | AB37: =IF(OR($C37="",$K37=0,$AE37=""),"",$M37+ROW()/100000) | AC37: {=IF($C37="","",IFERROR(INDEX(Disponibilidad!$O$6:$O$18,MATCH($L37,Disponibilidad!$B$6:$B$18,0)),"Hogar"))} | AD37: =IF($C37="","",SUMIFS(Caja!$H$6:$H$505,Caja!$J$6:$J$505,$A37,Caja!$C$6:$C$505,"Pago")) | AE37: =IF($C37="","",IF(N($R37)>0,$R37,$H37))
A38: =IF($C38="","",ROW()-5) | B38: Pendiente | C38: Comunidad Capitol | D38: Comunidad | E38: Limpieza de comunidad — factura 007 | F38: 007 | H38: 46172 | I38: 30 | J38: 0 | K38: =IF($C38="","",IF($B38="Pagada",0,ROUND(MAX(0,N($I38)+N($T38)-N($J38)-N($AD38)),2))) | L38: CaixaBank (corriente 9914) | M38: =IF(OR($C38="",$AE38="",$K38=0),"",$AE38-TODAY()) | N38: =IF($C38="","",IF($K38=0,"✅ Saldada",IF($M38="","",IF($M38<0,IF(N($R38)>0,"🔴 APLAZADA VENCIDA","🔴 VENCIDA"),IF(N($R38)>0,"🕓 Aplazada",IF($M38<=3,"🟠 ≤3 días",IF($M38<=7,"🟡 ≤7 días",IF($M38<=30,"🔵 ≤30 días","⚪ >30 días")))))))) | O38: =IF($AE38="","",TEXT($AE38,"YYYY-MM")) | Q38: Transcrita de la captura de HomeBank del 30/07/2026. | AA38: =IF(OR($C38="",$K38=0,$P38=""),"",VALUE(LEFT($P38,1))*100000+N($M38)+ROW()/100000) | AB38: =IF(OR($C38="",$K38=0,$AE38=""),"",$M38+ROW()/100000) | AC38: {=IF($C38="","",IFERROR(INDEX(Disponibilidad!$O$6:$O$18,MATCH($L38,Disponibilidad!$B$6:$B$18,0)),"Hogar"))} | AD38: =IF($C38="","",SUMIFS(Caja!$H$6:$H$505,Caja!$J$6:$J$505,$A38,Caja!$C$6:$C$505,"Pago")) | AE38: =IF($C38="","",IF(N($R38)>0,$R38,$H38)) | AF38: 5. SALDO POR MES DE VENCIMIENTO
A39: =IF($C39="","",ROW()-5) | B39: Pendiente | C39: Comunidad Capitol | D39: Comunidad | E39: Limpieza de comunidad — factura 008 | F39: 008 | H39: 46203 | I39: 30 | J39: 0 | K39: =IF($C39="","",IF($B39="Pagada",0,ROUND(MAX(0,N($I39)+N($T39)-N($J39)-N($AD39)),2))) | L39: CaixaBank (corriente 9914) | M39: =IF(OR($C39="",$AE39="",$K39=0),"",$AE39-TODAY()) | N39: =IF($C39="","",IF($K39=0,"✅ Saldada",IF($M39="","",IF($M39<0,IF(N($R39)>0,"🔴 APLAZADA VENCIDA","🔴 VENCIDA"),IF(N($R39)>0,"🕓 Aplazada",IF($M39<=3,"🟠 ≤3 días",IF($M39<=7,"🟡 ≤7 días",IF($M39<=30,"🔵 ≤30 días","⚪ >30 días")))))))) | O39: =IF($AE39="","",TEXT($AE39,"YYYY-MM")) | Q39: Transcrita de la captura de HomeBank del 30/07/2026. | AA39: =IF(OR($C39="",$K39=0,$P39=""),"",VALUE(LEFT($P39,1))*100000+N($M39)+ROW()/100000) | AB39: =IF(OR($C39="",$K39=0,$AE39=""),"",$M39+ROW()/100000) | AC39: {=IF($C39="","",IFERROR(INDEX(Disponibilidad!$O$6:$O$18,MATCH($L39,Disponibilidad!$B$6:$B$18,0)),"Hogar"))} | AD39: =IF($C39="","",SUMIFS(Caja!$H$6:$H$505,Caja!$J$6:$J$505,$A39,Caja!$C$6:$C$505,"Pago")) | AE39: =IF($C39="","",IF(N($R39)>0,$R39,$H39)) | AF39: Mes | AG39: Saldo pendiente (€) | AH39: Nº | AI39: Ya abonado (€) | AJ39: Visual
A40: =IF($C40="","",ROW()-5) | B40: Pendiente | C40: Comunidad Capitol | D40: Comunidad | E40: Limpieza de comunidad — factura 004 | F40: 004 | H40: 46225 | I40: 30 | J40: 0 | K40: =IF($C40="","",IF($B40="Pagada",0,ROUND(MAX(0,N($I40)+N($T40)-N($J40)-N($AD40)),2))) | L40: CaixaBank (corriente 9914) | M40: =IF(OR($C40="",$AE40="",$K40=0),"",$AE40-TODAY()) | N40: =IF($C40="","",IF($K40=0,"✅ Saldada",IF($M40="","",IF($M40<0,IF(N($R40)>0,"🔴 APLAZADA VENCIDA","🔴 VENCIDA"),IF(N($R40)>0,"🕓 Aplazada",IF($M40<=3,"🟠 ≤3 días",IF($M40<=7,"🟡 ≤7 días",IF($M40<=30,"🔵 ≤30 días","⚪ >30 días")))))))) | O40: =IF($AE40="","",TEXT($AE40,"YYYY-MM")) | Q40: En la captura la 004 aparece fechada después de la 008: revisa si es correcto. Transcrita de la captura de HomeBank del 30/07/2026. | AA40: =IF(OR($C40="",$K40=0,$P40=""),"",VALUE(LEFT($P40,1))*100000+N($M40)+ROW()/100000) | AB40: =IF(OR($C40="",$K40=0,$AE40=""),"",$M40+ROW()/100000) | AC40: {=IF($C40="","",IFERROR(INDEX(Disponibilidad!$O$6:$O$18,MATCH($L40,Disponibilidad!$B$6:$B$18,0)),"Hogar"))} | AD40: =IF($C40="","",SUMIFS(Caja!$H$6:$H$505,Caja!$J$6:$J$505,$A40,Caja!$C$6:$C$505,"Pago")) | AE40: =IF($C40="","",IF(N($R40)>0,$R40,$H40)) | AF40: Anteriores (atrasos) | AG40: =MAX(0,$AG$20-SUM($AG$41:$AG$51)) | AH40: =COUNTIFS($M$6:$M$205,"<0",$K$6:$K$205,">0")-COUNTIFS($O$6:$O$205,">="&$AF$41,$M$6:$M$205,"<0",$K$6:$K$205,">0") | AJ40: =IF($AG$40=0,"",REPT("█",MAX(1,ROUND($AG$40/MAX($AG$40:$AG$51)*18,0))))
A41: =IF($C41="","",ROW()-5) | B41: Pendiente | C41: Comunidad Capitol | D41: Comunidad | E41: Limpieza de comunidad — factura 009 | F41: 009 | H41: 46234 | I41: 30 | J41: 0 | K41: =IF($C41="","",IF($B41="Pagada",0,ROUND(MAX(0,N($I41)+N($T41)-N($J41)-N($AD41)),2))) | L41: CaixaBank (corriente 9914) | M41: =IF(OR($C41="",$AE41="",$K41=0),"",$AE41-TODAY()) | N41: =IF($C41="","",IF($K41=0,"✅ Saldada",IF($M41="","",IF($M41<0,IF(N($R41)>0,"🔴 APLAZADA VENCIDA","🔴 VENCIDA"),IF(N($R41)>0,"🕓 Aplazada",IF($M41<=3,"🟠 ≤3 días",IF($M41<=7,"🟡 ≤7 días",IF($M41<=30,"🔵 ≤30 días","⚪ >30 días")))))))) | O41: =IF($AE41="","",TEXT($AE41,"YYYY-MM")) | Q41: Transcrita de la captura de HomeBank del 30/07/2026. | AA41: =IF(OR($C41="",$K41=0,$P41=""),"",VALUE(LEFT($P41,1))*100000+N($M41)+ROW()/100000) | AB41: =IF(OR($C41="",$K41=0,$AE41=""),"",$M41+ROW()/100000) | AC41: {=IF($C41="","",IFERROR(INDEX(Disponibilidad!$O$6:$O$18,MATCH($L41,Disponibilidad!$B$6:$B$18,0)),"Hogar"))} | AD41: =IF($C41="","",SUMIFS(Caja!$H$6:$H$505,Caja!$J$6:$J$505,$A41,Caja!$C$6:$C$505,"Pago")) | AE41: =IF($C41="","",IF(N($R41)>0,$R41,$H41)) | AF41: =TEXT(EDATE(TODAY(),0),"YYYY-MM") | AG41: =SUMIFS($K$6:$K$205,$O$6:$O$205,$AF41) | AH41: =COUNTIFS($O$6:$O$205,$AF41,$K$6:$K$205,">0") | AI41: =SUMIFS($I$6:$I$205,$O$6:$O$205,$AF41)-SUMIFS($K$6:$K$205,$O$6:$O$205,$AF41) | AJ41: =IF($AG41=0,"",REPT("█",MAX(1,ROUND($AG41/MAX($AG$40:$AG$51)*18,0))))
A42: =IF($C42="","",ROW()-5) | B42: Pagada | C42: Quick Gold | D42: Intereses de empeño | E42: Intereses del empeño — lote 006548 | F42: lote 006548 | H42: 46248 | I42: 24.54 | J42: 0 | K42: =IF($C42="","",IF($B42="Pagada",0,ROUND(MAX(0,N($I42)+N($T42)-N($J42)-N($AD42)),2))) | L42: CaixaBank (corriente 9914) | M42: =IF(OR($C42="",$AE42="",$K42=0),"",$AE42-TODAY()) | N42: =IF($C42="","",IF($K42=0,"✅ Saldada",IF($M42="","",IF($M42<0,IF(N($R42)>0,"🔴 APLAZADA VENCIDA","🔴 VENCIDA"),IF(N($R42)>0,"🕓 Aplazada",IF($M42<=3,"🟠 ≤3 días",IF($M42<=7,"🟡 ≤7 días",IF($M42<=30,"🔵 ≤30 días","⚪ >30 días")))))))) | O42: =IF($AE42="","",TEXT($AE42,"YYYY-MM")) | Q42: Intereses por el empeño, no devolución de capital: por eso van a gastos financieros del Estado de Resultados y NO se descuentan del pasivo por facturas del Balance. Transcrita de la captura de HomeBank del 30/07/2026. | AA42: =IF(OR($C42="",$K42=0,$P42=""),"",VALUE(LEFT($P42,1))*100000+N($M42)+ROW()/100000) | AB42: =IF(OR($C42="",$K42=0,$AE42=""),"",$M42+ROW()/100000) | AC42: {=IF($C42="","",IFERROR(INDEX(Disponibilidad!$O$6:$O$18,MATCH($L42,Disponibilidad!$B$6:$B$18,0)),"Hogar"))} | AD42: =IF($C42="","",SUMIFS(Caja!$H$6:$H$505,Caja!$J$6:$J$505,$A42,Caja!$C$6:$C$505,"Pago")) | AE42: =IF($C42="","",IF(N($R42)>0,$R42,$H42)) | AF42: =TEXT(EDATE(TODAY(),1),"YYYY-MM") | AG42: =SUMIFS($K$6:$K$205,$O$6:$O$205,$AF42) | AH42: =COUNTIFS($O$6:$O$205,$AF42,$K$6:$K$205,">0") | AI42: =SUMIFS($I$6:$I$205,$O$6:$O$205,$AF42)-SUMIFS($K$6:$K$205,$O$6:$O$205,$AF42) | AJ42: =IF($AG42=0,"",REPT("█",MAX(1,ROUND($AG42/MAX($AG$40:$AG$51)*18,0))))
A43: =IF($C43="","",ROW()-5) | B43: Pendiente | C43: Karma Market | D43: Crédito comercial | E43: Credito por compra Lavadora y MIcroonda | F43: 46113 | G43: 46156 | H43: 46142 | I43: 98 | J43: 0 | K43: =IF($C43="","",IF($B43="Pagada",0,ROUND(MAX(0,N($I43)+N($T43)-N($J43)-N($AD43)),2))) | L43: Banco Bilbao Vizcaya (BBVA) | M43: =IF(OR($C43="",$AE43="",$K43=0),"",$AE43-TODAY()) | N43: =IF($C43="","",IF($K43=0,"✅ Saldada",IF($M43="","",IF($M43<0,IF(N($R43)>0,"🔴 APLAZADA VENCIDA","🔴 VENCIDA"),IF(N($R43)>0,"🕓 Aplazada",IF($M43<=3,"🟠 ≤3 días",IF($M43<=7,"🟡 ≤7 días",IF($M43<=30,"🔵 ≤30 días","⚪ >30 días")))))))) | O43: =IF($AE43="","",TEXT($AE43,"YYYY-MM")) | P43: 1 · Urgente | AA43: =IF(OR($C43="",$K43=0,$P43=""),"",VALUE(LEFT($P43,1))*100000+N($M43)+ROW()/100000) | AB43: =IF(OR($C43="",$K43=0,$AE43=""),"",$M43+ROW()/100000) | AC43: {=IF($C43="","",IFERROR(INDEX(Disponibilidad!$O$6:$O$18,MATCH($L43,Disponibilidad!$B$6:$B$18,0)),"Hogar"))} | AD43: =IF($C43="","",SUMIFS(Caja!$H$6:$H$505,Caja!$J$6:$J$505,$A43,Caja!$C$6:$C$505,"Pago")) | AE43: =IF($C43="","",IF(N($R43)>0,$R43,$H43)) | AF43: =TEXT(EDATE(TODAY(),2),"YYYY-MM") | AG43: =SUMIFS($K$6:$K$205,$O$6:$O$205,$AF43) | AH43: =COUNTIFS($O$6:$O$205,$AF43,$K$6:$K$205,">0") | AI43: =SUMIFS($I$6:$I$205,$O$6:$O$205,$AF43)-SUMIFS($K$6:$K$205,$O$6:$O$205,$AF43) | AJ43: =IF($AG43=0,"",REPT("█",MAX(1,ROUND($AG43/MAX($AG$40:$AG$51)*18,0))))
A44: =IF($C44="","",ROW()-5) | B44: Pendiente | C44: Karma Market | D44: Crédito comercial | E44: Credito por compra Lavadora y MIcroonda | F44: 46143 | H44: 46172 | I44: 98 | J44: 0 | K44: =IF($C44="","",IF($B44="Pagada",0,ROUND(MAX(0,N($I44)+N($T44)-N($J44)-N($AD44)),2))) | L44: Banco Bilbao Vizcaya (BBVA) | M44: =IF(OR($C44="",$AE44="",$K44=0),"",$AE44-TODAY()) | N44: =IF($C44="","",IF($K44=0,"✅ Saldada",IF($M44="","",IF($M44<0,IF(N($R44)>0,"🔴 APLAZADA VENCIDA","🔴 VENCIDA"),IF(N($R44)>0,"🕓 Aplazada",IF($M44<=3,"🟠 ≤3 días",IF($M44<=7,"🟡 ≤7 días",IF($M44<=30,"🔵 ≤30 días","⚪ >30 días")))))))) | O44: =IF($AE44="","",TEXT($AE44,"YYYY-MM")) | AA44: =IF(OR($C44="",$K44=0,$P44=""),"",VALUE(LEFT($P44,1))*100000+N($M44)+ROW()/100000) | AB44: =IF(OR($C44="",$K44=0,$AE44=""),"",$M44+ROW()/100000) | AC44: {=IF($C44="","",IFERROR(INDEX(Disponibilidad!$O$6:$O$18,MATCH($L44,Disponibilidad!$B$6:$B$18,0)),"Hogar"))} | AD44: =IF($C44="","",SUMIFS(Caja!$H$6:$H$505,Caja!$J$6:$J$505,$A44,Caja!$C$6:$C$505,"Pago")) | AE44: =IF($C44="","",IF(N($R44)>0,$R44,$H44)) | AF44: =TEXT(EDATE(TODAY(),3),"YYYY-MM") | AG44: =SUMIFS($K$6:$K$205,$O$6:$O$205,$AF44) | AH44: =COUNTIFS($O$6:$O$205,$AF44,$K$6:$K$205,">0") | AI44: =SUMIFS($I$6:$I$205,$O$6:$O$205,$AF44)-SUMIFS($K$6:$K$205,$O$6:$O$205,$AF44) | AJ44: =IF($AG44=0,"",REPT("█",MAX(1,ROUND($AG44/MAX($AG$40:$AG$51)*18,0))))
A45: =IF($C45="","",ROW()-5) | B45: Pendiente | C45: Karma Market | D45: Crédito comercial | E45: Credito por compra Lavadora y MIcroonda | F45: 46174 | H45: 46203 | I45: 98 | J45: 0 | K45: =IF($C45="","",IF($B45="Pagada",0,ROUND(MAX(0,N($I45)+N($T45)-N($J45)-N($AD45)),2))) | L45: Banco Bilbao Vizcaya (BBVA) | M45: =IF(OR($C45="",$AE45="",$K45=0),"",$AE45-TODAY()) | N45: =IF($C45="","",IF($K45=0,"✅ Saldada",IF($M45="","",IF($M45<0,IF(N($R45)>0,"🔴 APLAZADA VENCIDA","🔴 VENCIDA"),IF(N($R45)>0,"🕓 Aplazada",IF($M45<=3,"🟠 ≤3 días",IF($M45<=7,"🟡 ≤7 días",IF($M45<=30,"🔵 ≤30 días","⚪ >30 días")))))))) | O45: =IF($AE45="","",TEXT($AE45,"YYYY-MM")) | AA45: =IF(OR($C45="",$K45=0,$P45=""),"",VALUE(LEFT($P45,1))*100000+N($M45)+ROW()/100000) | AB45: =IF(OR($C45="",$K45=0,$AE45=""),"",$M45+ROW()/100000) | AC45: {=IF($C45="","",IFERROR(INDEX(Disponibilidad!$O$6:$O$18,MATCH($L45,Disponibilidad!$B$6:$B$18,0)),"Hogar"))} | AD45: =IF($C45="","",SUMIFS(Caja!$H$6:$H$505,Caja!$J$6:$J$505,$A45,Caja!$C$6:$C$505,"Pago")) | AE45: =IF($C45="","",IF(N($R45)>0,$R45,$H45)) | AF45: =TEXT(EDATE(TODAY(),4),"YYYY-MM") | AG45: =SUMIFS($K$6:$K$205,$O$6:$O$205,$AF45) | AH45: =COUNTIFS($O$6:$O$205,$AF45,$K$6:$K$205,">0") | AI45: =SUMIFS($I$6:$I$205,$O$6:$O$205,$AF45)-SUMIFS($K$6:$K$205,$O$6:$O$205,$AF45) | AJ45: =IF($AG45=0,"",REPT("█",MAX(1,ROUND($AG45/MAX($AG$40:$AG$51)*18,0))))
A46: =IF($C46="","",ROW()-5) | B46: Pendiente | C46: Jose Antonio Garcia | D46: Préstamo particular | E46: Prestamos | F46: P002 | H46: 46203 | I46: 2945 | J46: 0 | K46: =IF($C46="","",IF($B46="Pagada",0,ROUND(MAX(0,N($I46)+N($T46)-N($J46)-N($AD46)),2))) | L46: Efectivo | M46: =IF(OR($C46="",$AE46="",$K46=0),"",$AE46-TODAY()) | N46: =IF($C46="","",IF($K46=0,"✅ Saldada",IF($M46="","",IF($M46<0,IF(N($R46)>0,"🔴 APLAZADA VENCIDA","🔴 VENCIDA"),IF(N($R46)>0,"🕓 Aplazada",IF($M46<=3,"🟠 ≤3 días",IF($M46<=7,"🟡 ≤7 días",IF($M46<=30,"🔵 ≤30 días","⚪ >30 días")))))))) | O46: =IF($AE46="","",TEXT($AE46,"YYYY-MM")) | Q46: Préstamo recibido de un particular. Su saldo pendiente va a la cuenta "Préstamos de particulares" del Balance. | R46: 46387 | S46: motivos familiares | T46: 0 | AA46: =IF(OR($C46="",$K46=0,$P46=""),"",VALUE(LEFT($P46,1))*100000+N($M46)+ROW()/100000) | AB46: =IF(OR($C46="",$K46=0,$AE46=""),"",$M46+ROW()/100000) | AC46: {=IF($C46="","",IFERROR(INDEX(Disponibilidad!$O$6:$O$18,MATCH($L46,Disponibilidad!$B$6:$B$18,0)),"Hogar"))} | AD46: =IF($C46="","",SUMIFS(Caja!$H$6:$H$505,Caja!$J$6:$J$505,$A46,Caja!$C$6:$C$505,"Pago")) | AE46: =IF($C46="","",IF(N($R46)>0,$R46,$H46)) | AF46: =TEXT(EDATE(TODAY(),5),"YYYY-MM") | AG46: =SUMIFS($K$6:$K$205,$O$6:$O$205,$AF46) | AH46: =COUNTIFS($O$6:$O$205,$AF46,$K$6:$K$205,">0") | AI46: =SUMIFS($I$6:$I$205,$O$6:$O$205,$AF46)-SUMIFS($K$6:$K$205,$O$6:$O$205,$AF46) | AJ46: =IF($AG46=0,"",REPT("█",MAX(1,ROUND($AG46/MAX($AG$40:$AG$51)*18,0))))
A47: =IF($C47="","",ROW()-5) | B47: Pendiente | C47: Jose Stalin Garcia | D47: Préstamo particular | E47: Prestamos | F47: P003 | H47: 46203 | I47: 510 | J47: 60 | K47: =IF($C47="","",IF($B47="Pagada",0,ROUND(MAX(0,N($I47)+N($T47)-N($J47)-N($AD47)),2))) | L47: Revolut (corriente) | M47: =IF(OR($C47="",$AE47="",$K47=0),"",$AE47-TODAY()) | N47: =IF($C47="","",IF($K47=0,"✅ Saldada",IF($M47="","",IF($M47<0,IF(N($R47)>0,"🔴 APLAZADA VENCIDA","🔴 VENCIDA"),IF(N($R47)>0,"🕓 Aplazada",IF($M47<=3,"🟠 ≤3 días",IF($M47<=7,"🟡 ≤7 días",IF($M47<=30,"🔵 ≤30 días","⚪ >30 días")))))))) | O47: =IF($AE47="","",TEXT($AE47,"YYYY-MM")) | R47: 46388 | S47: motivos familiares | T47: 0 | AA47: =IF(OR($C47="",$K47=0,$P47=""),"",VALUE(LEFT($P47,1))*100000+N($M47)+ROW()/100000) | AB47: =IF(OR($C47="",$K47=0,$AE47=""),"",$M47+ROW()/100000) | AC47: {=IF($C47="","",IFERROR(INDEX(Disponibilidad!$O$6:$O$18,MATCH($L47,Disponibilidad!$B$6:$B$18,0)),"Hogar"))} | AD47: =IF($C47="","",SUMIFS(Caja!$H$6:$H$505,Caja!$J$6:$J$505,$A47,Caja!$C$6:$C$505,"Pago")) | AE47: =IF($C47="","",IF(N($R47)>0,$R47,$H47)) | AF47: =TEXT(EDATE(TODAY(),6),"YYYY-MM") | AG47: =SUMIFS($K$6:$K$205,$O$6:$O$205,$AF47) | AH47: =COUNTIFS($O$6:$O$205,$AF47,$K$6:$K$205,">0") | AI47: =SUMIFS($I$6:$I$205,$O$6:$O$205,$AF47)-SUMIFS($K$6:$K$205,$O$6:$O$205,$AF47) | AJ47: =IF($AG47=0,"",REPT("█",MAX(1,ROUND($AG47/MAX($AG$40:$AG$51)*18,0))))
A48: =IF($C48="","",ROW()-5) | B48: Pendiente | C48: Fulgencia Almanzar | D48: Préstamo particular | E48: Prestamo completivo Inicial Hipoteca | F48: P001 | H48: 45971 | I48: 3500 | J48: 0 | K48: =IF($C48="","",IF($B48="Pagada",0,ROUND(MAX(0,N($I48)+N($T48)-N($J48)-N($AD48)),2))) | L48: Efectivo | M48: =IF(OR($C48="",$AE48="",$K48=0),"",$AE48-TODAY()) | N48: =IF($C48="","",IF($K48=0,"✅ Saldada",IF($M48="","",IF($M48<0,IF(N($R48)>0,"🔴 APLAZADA VENCIDA","🔴 VENCIDA"),IF(N($R48)>0,"🕓 Aplazada",IF($M48<=3,"🟠 ≤3 días",IF($M48<=7,"🟡 ≤7 días",IF($M48<=30,"🔵 ≤30 días","⚪ >30 días")))))))) | O48: =IF($AE48="","",TEXT($AE48,"YYYY-MM")) | Q48: Préstamo recibido para completar la entrada de la hipoteca. Pasivo, no gasto. | R48: 46389 | S48: motivos familiares | T48: 0 | AA48: =IF(OR($C48="",$K48=0,$P48=""),"",VALUE(LEFT($P48,1))*100000+N($M48)+ROW()/100000) | AB48: =IF(OR($C48="",$K48=0,$AE48=""),"",$M48+ROW()/100000) | AC48: {=IF($C48="","",IFERROR(INDEX(Disponibilidad!$O$6:$O$18,MATCH($L48,Disponibilidad!$B$6:$B$18,0)),"Hogar"))} | AD48: =IF($C48="","",SUMIFS(Caja!$H$6:$H$505,Caja!$J$6:$J$505,$A48,Caja!$C$6:$C$505,"Pago")) | AE48: =IF($C48="","",IF(N($R48)>0,$R48,$H48)) | AF48: =TEXT(EDATE(TODAY(),7),"YYYY-MM") | AG48: =SUMIFS($K$6:$K$205,$O$6:$O$205,$AF48) | AH48: =COUNTIFS($O$6:$O$205,$AF48,$K$6:$K$205,">0") | AI48: =SUMIFS($I$6:$I$205,$O$6:$O$205,$AF48)-SUMIFS($K$6:$K$205,$O$6:$O$205,$AF48) | AJ48: =IF($AG48=0,"",REPT("█",MAX(1,ROUND($AG48/MAX($AG$40:$AG$51)*18,0))))
A49: =IF($C49="","",ROW()-5) | B49: Pendiente | C49: Jose Antonio Garcia | D49: Préstamo particular | E49: Prestamos | F49: P004 | H49: 46235 | I49: 115 | J49: 0 | K49: =IF($C49="","",IF($B49="Pagada",0,ROUND(MAX(0,N($I49)+N($T49)-N($J49)-N($AD49)),2))) | L49: Efectivo | M49: =IF(OR($C49="",$AE49="",$K49=0),"",$AE49-TODAY()) | N49: =IF($C49="","",IF($K49=0,"✅ Saldada",IF($M49="","",IF($M49<0,IF(N($R49)>0,"🔴 APLAZADA VENCIDA","🔴 VENCIDA"),IF(N($R49)>0,"🕓 Aplazada",IF($M49<=3,"🟠 ≤3 días",IF($M49<=7,"🟡 ≤7 días",IF($M49<=30,"🔵 ≤30 días","⚪ >30 días")))))))) | O49: =IF($AE49="","",TEXT($AE49,"YYYY-MM")) | R49: 46390 | S49: motivos familiares | T49: 0 | AA49: =IF(OR($C49="",$K49=0,$P49=""),"",VALUE(LEFT($P49,1))*100000+N($M49)+ROW()/100000) | AB49: =IF(OR($C49="",$K49=0,$AE49=""),"",$M49+ROW()/100000) | AC49: {=IF($C49="","",IFERROR(INDEX(Disponibilidad!$O$6:$O$18,MATCH($L49,Disponibilidad!$B$6:$B$18,0)),"Hogar"))} | AD49: =IF($C49="","",SUMIFS(Caja!$H$6:$H$505,Caja!$J$6:$J$505,$A49,Caja!$C$6:$C$505,"Pago")) | AE49: =IF($C49="","",IF(N($R49)>0,$R49,$H49)) | AF49: =TEXT(EDATE(TODAY(),8),"YYYY-MM") | AG49: =SUMIFS($K$6:$K$205,$O$6:$O$205,$AF49) | AH49: =COUNTIFS($O$6:$O$205,$AF49,$K$6:$K$205,">0") | AI49: =SUMIFS($I$6:$I$205,$O$6:$O$205,$AF49)-SUMIFS($K$6:$K$205,$O$6:$O$205,$AF49) | AJ49: =IF($AG49=0,"",REPT("█",MAX(1,ROUND($AG49/MAX($AG$40:$AG$51)*18,0))))
A50: =IF($C50="","",ROW()-5) | B50: Pendiente | C50: CaixaBank | D50: Tarjeta de crédito | E50: Cuota Tarjeta | F50: 46235 | H50: 46235 | I50: 50 | J50: 9.69 | K50: =IF($C50="","",IF($B50="Pagada",0,ROUND(MAX(0,N($I50)+N($T50)-N($J50)-N($AD50)),2))) | L50: CaixaBank (corriente 9914) | M50: =IF(OR($C50="",$AE50="",$K50=0),"",$AE50-TODAY()) | N50: =IF($C50="","",IF($K50=0,"✅ Saldada",IF($M50="","",IF($M50<0,IF(N($R50)>0,"🔴 APLAZADA VENCIDA","🔴 VENCIDA"),IF(N($R50)>0,"🕓 Aplazada",IF($M50<=3,"🟠 ≤3 días",IF($M50<=7,"🟡 ≤7 días",IF($M50<=30,"🔵 ≤30 días","⚪ >30 días")))))))) | O50: =IF($AE50="","",TEXT($AE50,"YYYY-MM")) | P50: 1 · Urgente | AA50: =IF(OR($C50="",$K50=0,$P50=""),"",VALUE(LEFT($P50,1))*100000+N($M50)+ROW()/100000) | AB50: =IF(OR($C50="",$K50=0,$AE50=""),"",$M50+ROW()/100000) | AC50: {=IF($C50="","",IFERROR(INDEX(Disponibilidad!$O$6:$O$18,MATCH($L50,Disponibilidad!$B$6:$B$18,0)),"Hogar"))} | AD50: =IF($C50="","",SUMIFS(Caja!$H$6:$H$505,Caja!$J$6:$J$505,$A50,Caja!$C$6:$C$505,"Pago")) | AE50: =IF($C50="","",IF(N($R50)>0,$R50,$H50)) | AF50: =TEXT(EDATE(TODAY(),9),"YYYY-MM") | AG50: =SUMIFS($K$6:$K$205,$O$6:$O$205,$AF50) | AH50: =COUNTIFS($O$6:$O$205,$AF50,$K$6:$K$205,">0") | AI50: =SUMIFS($I$6:$I$205,$O$6:$O$205,$AF50)-SUMIFS($K$6:$K$205,$O$6:$O$205,$AF50) | AJ50: =IF($AG50=0,"",REPT("█",MAX(1,ROUND($AG50/MAX($AG$40:$AG$51)*18,0))))
A51: =IF($C51="","",ROW()-5) | B51: Pendiente | C51: Deputacion de A coruña | D51: Impuestos y hacienda | E51: Deputacion de a coruña deuda de agua casa v. | F51: 260344872122 | H51: 46276 | I51: 46.72 | J51: 0 | K51: =IF($C51="","",IF($B51="Pagada",0,ROUND(MAX(0,N($I51)+N($T51)-N($J51)-N($AD51)),2))) | L51: Banco Bilbao Vizcaya (BBVA) | M51: =IF(OR($C51="",$AE51="",$K51=0),"",$AE51-TODAY()) | N51: =IF($C51="","",IF($K51=0,"✅ Saldada",IF($M51="","",IF($M51<0,IF(N($R51)>0,"🔴 APLAZADA VENCIDA","🔴 VENCIDA"),IF(N($R51)>0,"🕓 Aplazada",IF($M51<=3,"🟠 ≤3 días",IF($M51<=7,"🟡 ≤7 días",IF($M51<=30,"🔵 ≤30 días","⚪ >30 días")))))))) | O51: =IF($AE51="","",TEXT($AE51,"YYYY-MM")) | AA51: =IF(OR($C51="",$K51=0,$P51=""),"",VALUE(LEFT($P51,1))*100000+N($M51)+ROW()/100000) | AB51: =IF(OR($C51="",$K51=0,$AE51=""),"",$M51+ROW()/100000) | AC51: {=IF($C51="","",IFERROR(INDEX(Disponibilidad!$O$6:$O$18,MATCH($L51,Disponibilidad!$B$6:$B$18,0)),"Hogar"))} | AD51: =IF($C51="","",SUMIFS(Caja!$H$6:$H$505,Caja!$J$6:$J$505,$A51,Caja!$C$6:$C$505,"Pago")) | AE51: =IF($C51="","",IF(N($R51)>0,$R51,$H51)) | AF51: =TEXT(EDATE(TODAY(),10),"YYYY-MM") | AG51: =SUMIFS($K$6:$K$205,$O$6:$O$205,$AF51) | AH51: =COUNTIFS($O$6:$O$205,$AF51,$K$6:$K$205,">0") | AI51: =SUMIFS($I$6:$I$205,$O$6:$O$205,$AF51)-SUMIFS($K$6:$K$205,$O$6:$O$205,$AF51) | AJ51: =IF($AG51=0,"",REPT("█",MAX(1,ROUND($AG51/MAX($AG$40:$AG$51)*18,0))))
A52: =IF($C52="","",ROW()-5) | B52: Pagada | C52: DKV SEGUROS | D52: Otros | E52: Compra Poliza de seguro DKV (4 MIEMBROS) | F52: S001 | H52: 46266 | I52: 120.6 | K52: =IF($C52="","",IF($B52="Pagada",0,ROUND(MAX(0,N($I52)+N($T52)-N($J52)-N($AD52)),2))) | M52: =IF(OR($C52="",$AE52="",$K52=0),"",$AE52-TODAY()) | N52: =IF($C52="","",IF($K52=0,"✅ Saldada",IF($M52="","",IF($M52<0,IF(N($R52)>0,"🔴 APLAZADA VENCIDA","🔴 VENCIDA"),IF(N($R52)>0,"🕓 Aplazada",IF($M52<=3,"🟠 ≤3 días",IF($M52<=7,"🟡 ≤7 días",IF($M52<=30,"🔵 ≤30 días","⚪ >30 días")))))))) | O52: =IF($AE52="","",TEXT($AE52,"YYYY-MM")) | AA52: =IF(OR($C52="",$K52=0,$P52=""),"",VALUE(LEFT($P52,1))*100000+N($M52)+ROW()/100000) | AB52: =IF(OR($C52="",$K52=0,$AE52=""),"",$M52+ROW()/100000) | AC52: {=IF($C52="","",IFERROR(INDEX(Disponibilidad!$O$6:$O$18,MATCH($L52,Disponibilidad!$B$6:$B$18,0)),"Hogar"))} | AD52: =IF($C52="","",SUMIFS(Caja!$H$6:$H$505,Caja!$J$6:$J$505,$A52,Caja!$C$6:$C$505,"Pago")) | AE52: =IF($C52="","",IF(N($R52)>0,$R52,$H52)) | AF52: TOTAL | AG52: =SUM($AG$40:$AG$51) | AH52: =SUM($AH$40:$AH$51) | AI52: =SUM($AI$40:$AI$51)
A53: =IF($C53="","",ROW()-5) | B53: Pagada | C53: DKV SEGUROS | D53: Otros | E53: Compra Poliza de seguro DKV ( 1 MIEMBRO) | F53: S002 | H53: 46266 | I53: 68 | K53: =IF($C53="","",IF($B53="Pagada",0,ROUND(MAX(0,N($I53)+N($T53)-N($J53)-N($AD53)),2))) | M53: =IF(OR($C53="",$AE53="",$K53=0),"",$AE53-TODAY()) | N53: =IF($C53="","",IF($K53=0,"✅ Saldada",IF($M53="","",IF($M53<0,IF(N($R53)>0,"🔴 APLAZADA VENCIDA","🔴 VENCIDA"),IF(N($R53)>0,"🕓 Aplazada",IF($M53<=3,"🟠 ≤3 días",IF($M53<=7,"🟡 ≤7 días",IF($M53<=30,"🔵 ≤30 días","⚪ >30 días")))))))) | O53: =IF($AE53="","",TEXT($AE53,"YYYY-MM")) | AA53: =IF(OR($C53="",$K53=0,$P53=""),"",VALUE(LEFT($P53,1))*100000+N($M53)+ROW()/100000) | AB53: =IF(OR($C53="",$K53=0,$AE53=""),"",$M53+ROW()/100000) | AC53: {=IF($C53="","",IFERROR(INDEX(Disponibilidad!$O$6:$O$18,MATCH($L53,Disponibilidad!$B$6:$B$18,0)),"Hogar"))} | AD53: =IF($C53="","",SUMIFS(Caja!$H$6:$H$505,Caja!$J$6:$J$505,$A53,Caja!$C$6:$C$505,"Pago")) | AE53: =IF($C53="","",IF(N($R53)>0,$R53,$H53))
A54: =IF($C54="","",ROW()-5) | B54: Pagada | C54: Iberdrola | D54: Gas | E54: Fcatura de gas | F54: 368031 | H54: 46153 | I54: 103.73 | J54: 103.73 | K54: =IF($C54="","",IF($B54="Pagada",0,ROUND(MAX(0,N($I54)+N($T54)-N($J54)-N($AD54)),2))) | L54: Revolut (corriente) | M54: =IF(OR($C54="",$AE54="",$K54=0),"",$AE54-TODAY()) | N54: =IF($C54="","",IF($K54=0,"✅ Saldada",IF($M54="","",IF($M54<0,IF(N($R54)>0,"🔴 APLAZADA VENCIDA","🔴 VENCIDA"),IF(N($R54)>0,"🕓 Aplazada",IF($M54<=3,"🟠 ≤3 días",IF($M54<=7,"🟡 ≤7 días",IF($M54<=30,"🔵 ≤30 días","⚪ >30 días")))))))) | O54: =IF($AE54="","",TEXT($AE54,"YYYY-MM")) | P54: 1 · Urgente | AA54: =IF(OR($C54="",$K54=0,$P54=""),"",VALUE(LEFT($P54,1))*100000+N($M54)+ROW()/100000) | AB54: =IF(OR($C54="",$K54=0,$AE54=""),"",$M54+ROW()/100000) | AC54: {=IF($C54="","",IFERROR(INDEX(Disponibilidad!$O$6:$O$18,MATCH($L54,Disponibilidad!$B$6:$B$18,0)),"Hogar"))} | AD54: =IF($C54="","",SUMIFS(Caja!$H$6:$H$505,Caja!$J$6:$J$505,$A54,Caja!$C$6:$C$505,"Pago")) | AE54: =IF($C54="","",IF(N($R54)>0,$R54,$H54)) | AF54: La fila "Anteriores (atrasos)" recoge todo lo vencido antes del mes en curso, para que el bloque cuadre siempre con el saldo pendiente total.
A55: =IF($C55="","",ROW()-5) | B55: Pendiente | C55: Vivus.es | D55: Crédito comercial | E55: Prestamo a corto plazo | F55: 05082-2026 | G55: 46239 | H55: 46269 | I55: 301.5 | K55: =IF($C55="","",IF($B55="Pagada",0,ROUND(MAX(0,N($I55)+N($T55)-N($J55)-N($AD55)),2))) | L55: Revolut (corriente) | M55: =IF(OR($C55="",$AE55="",$K55=0),"",$AE55-TODAY()) | N55: =IF($C55="","",IF($K55=0,"✅ Saldada",IF($M55="","",IF($M55<0,IF(N($R55)>0,"🔴 APLAZADA VENCIDA","🔴 VENCIDA"),IF(N($R55)>0,"🕓 Aplazada",IF($M55<=3,"🟠 ≤3 días",IF($M55<=7,"🟡 ≤7 días",IF($M55<=30,"🔵 ≤30 días","⚪ >30 días")))))))) | O55: =IF($AE55="","",TEXT($AE55,"YYYY-MM")) | AA55: =IF(OR($C55="",$K55=0,$P55=""),"",VALUE(LEFT($P55,1))*100000+N($M55)+ROW()/100000) | AB55: =IF(OR($C55="",$K55=0,$AE55=""),"",$M55+ROW()/100000) | AC55: {=IF($C55="","",IFERROR(INDEX(Disponibilidad!$O$6:$O$18,MATCH($L55,Disponibilidad!$B$6:$B$18,0)),"Hogar"))} | AD55: =IF($C55="","",SUMIFS(Caja!$H$6:$H$505,Caja!$J$6:$J$505,$A55,Caja!$C$6:$C$505,"Pago")) | AE55: =IF($C55="","",IF(N($R55)>0,$R55,$H55))
A56: =IF($C56="","",ROW()-5) | K56: =IF($C56="","",IF($B56="Pagada",0,ROUND(MAX(0,N($I56)+N($T56)-N($J56)-N($AD56)),2))) | M56: =IF(OR($C56="",$AE56="",$K56=0),"",$AE56-TODAY()) | N56: =IF($C56="","",IF($K56=0,"✅ Saldada",IF($M56="","",IF($M56<0,IF(N($R56)>0,"🔴 APLAZADA VENCIDA","🔴 VENCIDA"),IF(N($R56)>0,"🕓 Aplazada",IF($M56<=3,"🟠 ≤3 días",IF($M56<=7,"🟡 ≤7 días",IF($M56<=30,"🔵 ≤30 días","⚪ >30 días")))))))) | O56: =IF($AE56="","",TEXT($AE56,"YYYY-MM")) | AA56: =IF(OR($C56="",$K56=0,$P56=""),"",VALUE(LEFT($P56,1))*100000+N($M56)+ROW()/100000) | AB56: =IF(OR($C56="",$K56=0,$AE56=""),"",$M56+ROW()/100000) | AC56: {=IF($C56="","",IFERROR(INDEX(Disponibilidad!$O$6:$O$18,MATCH($L56,Disponibilidad!$B$6:$B$18,0)),"Hogar"))} | AD56: =IF($C56="","",SUMIFS(Caja!$H$6:$H$505,Caja!$J$6:$J$505,$A56,Caja!$C$6:$C$505,"Pago")) | AE56: =IF($C56="","",IF(N($R56)>0,$R56,$H56)) | AF56: 6. APLAZAMIENTOS — qué has conseguido posponer
A57: =IF($C57="","",ROW()-5) | K57: =IF($C57="","",IF($B57="Pagada",0,ROUND(MAX(0,N($I57)+N($T57)-N($J57)-N($AD57)),2))) | M57: =IF(OR($C57="",$AE57="",$K57=0),"",$AE57-TODAY()) | N57: =IF($C57="","",IF($K57=0,"✅ Saldada",IF($M57="","",IF($M57<0,IF(N($R57)>0,"🔴 APLAZADA VENCIDA","🔴 VENCIDA"),IF(N($R57)>0,"🕓 Aplazada",IF($M57<=3,"🟠 ≤3 días",IF($M57<=7,"🟡 ≤7 días",IF($M57<=30,"🔵 ≤30 días","⚪ >30 días")))))))) | O57: =IF($AE57="","",TEXT($AE57,"YYYY-MM")) | AA57: =IF(OR($C57="",$K57=0,$P57=""),"",VALUE(LEFT($P57,1))*100000+N($M57)+ROW()/100000) | AB57: =IF(OR($C57="",$K57=0,$AE57=""),"",$M57+ROW()/100000) | AC57: {=IF($C57="","",IFERROR(INDEX(Disponibilidad!$O$6:$O$18,MATCH($L57,Disponibilidad!$B$6:$B$18,0)),"Hogar"))} | AD57: =IF($C57="","",SUMIFS(Caja!$H$6:$H$505,Caja!$J$6:$J$505,$A57,Caja!$C$6:$C$505,"Pago")) | AE57: =IF($C57="","",IF(N($R57)>0,$R57,$H57)) | AF57: Concepto | AG57: Importe (€) | AH57: Nº
A58: =IF($C58="","",ROW()-5) | K58: =IF($C58="","",IF($B58="Pagada",0,ROUND(MAX(0,N($I58)+N($T58)-N($J58)-N($AD58)),2))) | M58: =IF(OR($C58="",$AE58="",$K58=0),"",$AE58-TODAY()) | N58: =IF($C58="","",IF($K58=0,"✅ Saldada",IF($M58="","",IF($M58<0,IF(N($R58)>0,"🔴 APLAZADA VENCIDA","🔴 VENCIDA"),IF(N($R58)>0,"🕓 Aplazada",IF($M58<=3,"🟠 ≤3 días",IF($M58<=7,"🟡 ≤7 días",IF($M58<=30,"🔵 ≤30 días","⚪ >30 días")))))))) | O58: =IF($AE58="","",TEXT($AE58,"YYYY-MM")) | AA58: =IF(OR($C58="",$K58=0,$P58=""),"",VALUE(LEFT($P58,1))*100000+N($M58)+ROW()/100000) | AB58: =IF(OR($C58="",$K58=0,$AE58=""),"",$M58+ROW()/100000) | AC58: {=IF($C58="","",IFERROR(INDEX(Disponibilidad!$O$6:$O$18,MATCH($L58,Disponibilidad!$B$6:$B$18,0)),"Hogar"))} | AD58: =IF($C58="","",SUMIFS(Caja!$H$6:$H$505,Caja!$J$6:$J$505,$A58,Caja!$C$6:$C$505,"Pago")) | AE58: =IF($C58="","",IF(N($R58)>0,$R58,$H58)) | AF58: Saldo aplazado a una fecha nueva | AG58: =SUMIFS($K$6:$K$205,$R$6:$R$205,">0") | AH58: =COUNTIFS($R$6:$R$205,">0",$K$6:$K$205,">0")
A59: =IF($C59="","",ROW()-5) | K59: =IF($C59="","",IF($B59="Pagada",0,ROUND(MAX(0,N($I59)+N($T59)-N($J59)-N($AD59)),2))) | M59: =IF(OR($C59="",$AE59="",$K59=0),"",$AE59-TODAY()) | N59: =IF($C59="","",IF($K59=0,"✅ Saldada",IF($M59="","",IF($M59<0,IF(N($R59)>0,"🔴 APLAZADA VENCIDA","🔴 VENCIDA"),IF(N($R59)>0,"🕓 Aplazada",IF($M59<=3,"🟠 ≤3 días",IF($M59<=7,"🟡 ≤7 días",IF($M59<=30,"🔵 ≤30 días","⚪ >30 días")))))))) | O59: =IF($AE59="","",TEXT($AE59,"YYYY-MM")) | AA59: =IF(OR($C59="",$K59=0,$P59=""),"",VALUE(LEFT($P59,1))*100000+N($M59)+ROW()/100000) | AB59: =IF(OR($C59="",$K59=0,$AE59=""),"",$M59+ROW()/100000) | AC59: {=IF($C59="","",IFERROR(INDEX(Disponibilidad!$O$6:$O$18,MATCH($L59,Disponibilidad!$B$6:$B$18,0)),"Hogar"))} | AD59: =IF($C59="","",SUMIFS(Caja!$H$6:$H$505,Caja!$J$6:$J$505,$A59,Caja!$C$6:$C$505,"Pago")) | AE59: =IF($C59="","",IF(N($R59)>0,$R59,$H59)) | AF59: Recargos aceptados por aplazar | AG59: =SUM($T$6:$T$205) | AH59: =COUNTIFS($T$6:$T$205,">0")
A60: =IF($C60="","",ROW()-5) | K60: =IF($C60="","",IF($B60="Pagada",0,ROUND(MAX(0,N($I60)+N($T60)-N($J60)-N($AD60)),2))) | M60: =IF(OR($C60="",$AE60="",$K60=0),"",$AE60-TODAY()) | N60: =IF($C60="","",IF($K60=0,"✅ Saldada",IF($M60="","",IF($M60<0,IF(N($R60)>0,"🔴 APLAZADA VENCIDA","🔴 VENCIDA"),IF(N($R60)>0,"🕓 Aplazada",IF($M60<=3,"🟠 ≤3 días",IF($M60<=7,"🟡 ≤7 días",IF($M60<=30,"🔵 ≤30 días","⚪ >30 días")))))))) | O60: =IF($AE60="","",TEXT($AE60,"YYYY-MM")) | AA60: =IF(OR($C60="",$K60=0,$P60=""),"",VALUE(LEFT($P60,1))*100000+N($M60)+ROW()/100000) | AB60: =IF(OR($C60="",$K60=0,$AE60=""),"",$M60+ROW()/100000) | AC60: {=IF($C60="","",IFERROR(INDEX(Disponibilidad!$O$6:$O$18,MATCH($L60,Disponibilidad!$B$6:$B$18,0)),"Hogar"))} | AD60: =IF($C60="","",SUMIFS(Caja!$H$6:$H$505,Caja!$J$6:$J$505,$A60,Caja!$C$6:$C$505,"Pago")) | AE60: =IF($C60="","",IF(N($R60)>0,$R60,$H60)) | AF60: ⚠️ Aplazadas que YA han vuelto a vencer | AG60: =SUMIFS($K$6:$K$205,$R$6:$R$205,">0",$M$6:$M$205,"<0") | AH60: =COUNTIFS($R$6:$R$205,">0",$M$6:$M$205,"<0",$K$6:$K$205,">0")
A61: =IF($C61="","",ROW()-5) | K61: =IF($C61="","",IF($B61="Pagada",0,ROUND(MAX(0,N($I61)+N($T61)-N($J61)-N($AD61)),2))) | M61: =IF(OR($C61="",$AE61="",$K61=0),"",$AE61-TODAY()) | N61: =IF($C61="","",IF($K61=0,"✅ Saldada",IF($M61="","",IF($M61<0,IF(N($R61)>0,"🔴 APLAZADA VENCIDA","🔴 VENCIDA"),IF(N($R61)>0,"🕓 Aplazada",IF($M61<=3,"🟠 ≤3 días",IF($M61<=7,"🟡 ≤7 días",IF($M61<=30,"🔵 ≤30 días","⚪ >30 días")))))))) | O61: =IF($AE61="","",TEXT($AE61,"YYYY-MM")) | AA61: =IF(OR($C61="",$K61=0,$P61=""),"",VALUE(LEFT($P61,1))*100000+N($M61)+ROW()/100000) | AB61: =IF(OR($C61="",$K61=0,$AE61=""),"",$M61+ROW()/100000) | AC61: {=IF($C61="","",IFERROR(INDEX(Disponibilidad!$O$6:$O$18,MATCH($L61,Disponibilidad!$B$6:$B$18,0)),"Hogar"))} | AD61: =IF($C61="","",SUMIFS(Caja!$H$6:$H$505,Caja!$J$6:$J$505,$A61,Caja!$C$6:$C$505,"Pago")) | AE61: =IF($C61="","",IF(N($R61)>0,$R61,$H61)) | AF61: Próxima fecha aplazada que vence | AG61: =IFERROR(TEXT(MINIFS($R$6:$R$205,$R$6:$R$205,">0",$K$6:$K$205,">0"),"DD/MM/YYYY"),"—")
